Workbook
Name _AN859833: '[1]DAILY SALES DATA'!#REF!
Name Excel_BuiltIn_Print_Area: NA()
Name Excel_BuiltIn_Print_Area: NA()
Name Excel_BuiltIn_Print_Area: NA()
Name Excel_BuiltIn_Print_Area_2_1: NA()
Name Excel_BuiltIn_Print_Area_22_1: NA()
Name Excel_BuiltIn_Print_Area_30_1: NA()
Name Excel_BuiltIn_Print_Area_37_1: NA()
Name Excel_BuiltIn_Print_Area_39: NA()
Name Excel_BuiltIn_Print_Area_41: NA()
Name Excel_BuiltIn_Sheet_Title: "Individual Commission"
Name Excel_BuiltIn_Sheet_Title: "01"
Name Excel_BuiltIn_Sheet_Title: "01"
Name Excel_BuiltIn_Sheet_Title: "01"
Name Excel_BuiltIn_Sheet_Title: "01"
Name Excel_BuiltIn_Sheet_Title: "01"
Name Excel_BuiltIn_Sheet_Title: "SPPR _"
Name Excel_BuiltIn_Sheet_Title: "Traffic "

Sheet DS
A1: BVLGARI – Plaza Indonesia
A2: Daily Sales Transaction Report
A3: Periode | B3: 46266
AE4: HARUS DI ISI | AG4: HARUS DI ISI
A5: Date | B5: CB No. | C5: Sales Invoice No | D5: Customer Name | E5: Cosmo CRM ID | F5: Nationality | G5: New | H5: Old | I5: W | J5: F | K5: Category | L5: SAP Code | M5: Item Name | N5: Serial No | O5: Description | P5: Qty | Q5: Gross Sales | R5: Disc. % | S5: Net Sales | T5: Discount Given Reason | U5: Payment | AC5: Achievement | AD5: Daily Total Achievement | AE5: Served By | AF5: CA | AG5: Entitle | AH5: After Sales Support | AI5: DWA | AJ5: Other Remarks
U6: Deposit CB No | V6: Rp. | W6: Card | X6: OR No. | Y6: Bank Transfer To | Z6: EDC | AA6: Card Type | AB6: Card Commission
A7: 46266 | B7: NO SALE | R7: =(Q7-S7)/Q7*100 -> #DIV/0! | AB7: =W7*1.3% -> 0 | AC7: =(S7/1.11) -> 0 | AD7: =SUM(AC7) -> 0
A8: 46267 | B8: CBPI 11389 | C8: INV-550/2609/02803 | D8: Monica Selly Agresia | E8: 13104490 | F8: Indonesia | H8: 1 | J8: 1 | K8: JEWELRY | L8: 351051 | M8: CL857315 | N8: XH1WXK | O8: CL DIVA PG-5.0grs 1DIA-0.03ct 24PAVE-0.44ct PENDANT | P8: 1 | Q8: 174500000 | R8: =(Q8-S8)/Q8*100 -> 0 | S8: 174500000 | W8: 150000000 | Z8: BCA | AA8: V/HSBC | AB8: =W8*1.3% -> 1950000 | AC8: =(S8/1.11) -> 1.5720721e+08 | AE8: AJ | AF8: AJ | AG8: AJ | AH8: 807567 | AI8: 806422
R9: =(Q9-S9)/Q9*100 -> #DIV/0! | W9: 24500000 | Z9: BCA | AA9: V/HSBC | AB9: =W9*1.3% -> 318500 | AC9: =(S9/1.11) -> 0 | AH9: 806856
R10: =(Q10-S10)/Q10*100 -> #DIV/0! | AB10: =W10*1.3% -> 0 | AC10: =(S10/1.11) -> 0 | AH10: 807617
R11: =(Q11-S11)/Q11*100 -> #DIV/0! | AB11: =W11*7% -> 0 | AC11: =(S11/1.11) -> 0 | AD11: =SUM(AC8:AC11) -> 1.5720721e+08 | AH11: 806422
A12: 46268 | B12: CBPI 11392 | C12: INV-PI/2609/02806 | D12: Frisca Kargito | E12: 13571594 | F12: Indonesia | H12: 1 | J12: 1 | K12: JEWELRY | L12: 359949 | M12: OR859929 | N12: AA0X04 | O12: OR SVI PG-8.6grs 10PAVE-0.18ct | P12: 1 | Q12: 107900000 | R12: =(Q12-S12)/Q12*100 -> 0 | S12: =Q12 -> 107900000 | T12: CASHBACK BCA RP 2,500,000 | V12: 54400000 | W12: 51000000 | X12: 6612 | Z12: BCA | AA12: V/BCA 12X | AB12: =W12*5% -> 2550000 | AC12: =(S12/1.11) -> 97207207 | AE12: SD | AF12: SD | AG12: SD | AH12: 807570 | AI12: 806422 | AJ12: CASHBACK BCA RP 2,500,000
R13: =(Q13-S13)/Q13*100 -> #DIV/0! | AB13: =W13*5% -> 0 | AC13: =(S13/1.11) -> 0 | AH13: 806856
R14: =(Q14-S14)/Q14*100 -> #DIV/0! | AB14: =W14*3% -> 0 | AC14: =(S14/1.11) -> 0 | AH14: 807617
B15: CBPI 11393 | C15: INV-PI/2609/02807 | D15: Lisa Lissa | E15: 13664581 | F15: Indonesia | G15: 1 | I15: 1 | K15: JEWELRY | L15: 360467 | M15: AN859915 | N15: ARXF26 | O15: AN SVI 1ROW WG-7.0grs 6PAVE-0.14ct Sz 51-53 | P15: 1 | Q15: 91700000 | R15: =(Q15-S15)/Q15*100 -> 0 | S15: =Q15 -> 91700000 | V15: =S15+S16+S17+S18 -> 1004300000 | Y15: BCA | AB15: =W15*5% -> 0 | AC15: =(S15/1.11) -> 82612613 | AE15: SK | AF15: SK | AG15: SK | AH15: 807617 | AI15: 806422 | AJ15: GV 0238
K16: JEWELRY | L16: 361239 | M16: CL860213 | N16: AM0596 | O16: CL SVI PG-38,9grs TITANIUM-1.2 8PAVE-0.41ct Sz 36 | P16: 1 | Q16: 527700000 | R16: =(Q16-S16)/Q16*100 -> 0 | S16: =Q16 -> 527700000 | AB16: =W16*5% -> 0 | AC16: =(S16/1.11) -> 4.7540541e+08 | AH16: 806857 | AI16: 806422
K17: JEWELRY | L17: 361780 | M17: OR860393 | N17: AHF366 | O17: OR DIVA PG-6.1grs 2DIA-0.07ct 2MOP-0.08 22PAVE-0.18ct | P17: 1 | Q17: 106000000 | R17: =(Q17-S17)/Q17*100 -> 0 | S17: =Q17 -> 106000000 | AB17: =W17*5% -> 0 | AC17: =(S17/1.11) -> 95495495 | AH17: 806855 | AI17: 806422
K18: JEWELRY | L18: 360155 | M18: BR859759 | N18: ASRN57 | O18: BR SVI 1ROW BANGLE WG-17.8grs TITANIUM-1.7 8PAVE-0.47ct Sz 15 | P18: 1 | Q18: 278900000 | R18: =(Q18-S18)/Q18*100 -> 0 | S18: =Q18 -> 278900000 | AB18: =W18*0.15% -> 0 | AC18: =(S18/1.11) -> 2.5126126e+08 | AH18: 807573 | AI18: 806422
R19: =(Q19-S19)/Q19*100 -> #DIV/0! | AB19: =W19*2.2% -> 0 | AC19: =(S19/1.11) -> 0 | AH19: 807568
R20: =(Q20-S20)/Q20*100 -> #DIV/0! | AB20: =W20*1.3% -> 0 | AC20: =(S20/1.11) -> 0 | AH20: 807570
R21: =(Q21-S21)/Q21*100 -> #DIV/0! | AB21: =W21*2.25% -> 0 | AC21: =(S21/1.11) -> 0 | AH21: 807566
B22: CBPI 11394 | C22: SI-550/2609/37758 | D22: Jhon Levis | E22: 13367243 | F22: Indonesia | H22: 1 | J22: 1 | K22: JEWELRY | L22: 345209 | M22: AN855116 | N22: T5LYTF | O22: AN SVI 1ROW WG-9.2grs 75PAVE-1.58cts Sz S | P22: 1 | Q22: 574000000 | R22: =(Q22-S22)/Q22*100 -> 0 | S22: 574000000 | U22: CBPI 11326 | AB22: =W22*1.5% -> 0 | AC22: =(S22/1.11) -> 5.1711712e+08 | AE22: DP | AF22: DP | AG22: DP | AH22: 807617 | AI22: 806422 | AJ22: HOME DELIVERY
R23: =(Q23-S23)/Q23*100 -> #DIV/0! | AB23: =W23*1.4% -> 0 | AC23: =(S23/1.11) -> 0 | AH23: 806857 | AJ23: 80 : 20 (MM & HS)
R24: =(Q24-S24)/Q24*100 -> #DIV/0! | AB24: =W24*1.5% -> 0 | AC24: =(S24/1.11) -> 0 | AH24: 806856
R25: =(Q25-S25)/Q25*100 -> #DIV/0! | AB25: =W25*1.3% -> 0 | AC25: =(S25/1.11) -> 0 | AH25: 808138
B26: CBPI 11395 | C26: INV-550/2609/02811 | D26: Tiara Rinardi | E26: 13167381 | F26: Indonesia | H26: 1 | J26: 1 | K26: JEWELRY | L26: 360153 | M26: BR859759 | N26: AFH458 | O26: BR SVI 1ROW BANGLE WG-19.9grs TITANIUM-2.2 8PAVE-0.47ct Sz 17 | P26: 1 | Q26: 273000000 | R26: =(Q26-S26)/Q26*100 -> 0 | S26: 273000000 | U26: CBPI 11354 | AB26: =W26*0.15% -> 0 | AC26: =(S26/1.11) -> 2.4594595e+08 | AE26: HS | AF26: HS | AG26: HS | AH26: 806857 | AI26: 806422
R27: =(Q27-S27)/Q27*100 -> #DIV/0! | AB27: =W27*1.5% -> 0 | AC27: =(S27/1.11) -> 0 | AH27: 807617
R28: =(Q28-S28)/Q28*100 -> #DIV/0! | AB28: =W28*1.5% -> 0 | AC28: =(S28/1.11) -> 0 | AD28: =SUM(AC12:AC28) -> 1.765045e+09 | AH28: 807568
A29: 46269 | B29: CBPI 11397 | C29: SI-PI/2609/37768 | D29: Meksi Damara | E29: 13667214 | F29: Indonesia | M29: DEPOSIT | O29: DEPOSIT FULL PAYMENT RSI (349634 - ASP166) | R29: =(Q29-S29)/Q29*100 -> #DIV/0! | V29: 14800000 | Y29: BCA | AB29: =W29*1.4% -> 0 | AC29: =(S29/1.11) -> 0 | AE29: AL | AF29: AL
B30: CBPI 11398 | C30: INV-PI/2609/02814 | D30: Wina NR | E30: 13322899 | F30: Indonesia | H30: 1 | J30: 1 | K30: JEWELRY | L30: 348320 | M30: OR856498 | N30: AMT981 | O30: OR SER VIPER WG-18.6grs 112PAVE-2.08cts | P30: 1 | Q30: 792300000 | R30: =(Q30-S30)/Q30*100 -> 10 | S30: 713070000 | T30: DISC APP MS JESSICA | V30: =S30+S31 -> 1490490000 | X30: 6613 | AB30: =W30*1.3% -> 0 | AC30: =(S30/1.11) -> 6.4240541e+08 | AE30: SD | AF30: SD | AG30: SD | AH30: 808138 | AI30: 806422 | AJ30: HOME DELIVERY
K31: JEWELRY | L31: 347594 | M31: AN856156 | N31: A8RLX4 | O31: AN SVI 2ROWS PG-14.4grs 1RBLT-0.28 122HEADPAVE- 2.42cts Sz M | P31: 1 | Q31: 863800000 | R31: =(Q31-S31)/Q31*100 -> 10 | S31: 777420000 | AB31: =W31*1.3% -> 0 | AC31: =(S31/1.11) -> 7.0037838e+08 | AH31: 807570 | AI31: 806422
R32: =(Q32-S32)/Q32*100 -> #DIV/0! | AB32: =W32*2.25% -> 0 | AC32: =(S32/1.11) -> 0 | AH32: 804190
R33: =(Q33-S33)/Q33*100 -> #DIV/0! | AB33: =W33*0.15% -> 0 | AC33: =(S33/1.11) -> 0 | AH33: 806857
R34: =(Q34-S34)/Q34*100 -> #DIV/0! | AB34: =W34*0.15% -> 0 | AC34: =(S34/1.11) -> 0 | AH34: 807617
R35: =(Q35-S35)/Q35*100 -> #DIV/0! | AB35: =W35*1.5% -> 0 | AC35: =(S35/1.11) -> 0 | AD35: =SUM(AC29:AC35) -> 1.3427838e+09 | AH35: 807617
A36: 46270 | B36: CBPI 11400 | C36: SI-550/2609/37780 | D36: Matthew Aldo Susabda | E36: 13668547 | F36: Indonesia | G36: 1 | I36: 1 | K36: PERFUME | L36: 42504 | M36: PERFUME | N36: =L36 -> 42504 | O36: BVF EP THE IMPERIAL 25 EDT 75ML | P36: 1 | Q36: 2120000 | R36: =(Q36-S36)/Q36*100 -> 0 | S36: =Q36 -> 2120000 | W36: 48820000 | Z36: MDR | AA36: M/MDR 12X | AB36: =W36*5% -> 2441000 | AC36: =(S36/1.11) -> 1909909.9 | AE36: IR | AF36: IR | AG36: IR | AH36: 807567 | AI36: 806422
K37: JEWELRY | L37: 357255 | M37: CL858837 | N37: ARVK60 | O37: CL B01 MINI PG-7.2grs PENDANT | P37: 1 | Q37: 46700000 | R37: =(Q37-S37)/Q37*100 -> 0 | S37: =Q37 -> 46700000 | AB37: =W37*1.3% -> 0 | AC37: =(S37/1.11) -> 42072072 | AH37: 806856
R38: =(Q38-S38)/Q38*100 -> #DIV/0! | AB38: =W38*7% -> 0 | AC38: =(S38/1.11) -> 0 | AH38: 807617
B39: CBPI 11401 | C39: VOID | R39: =(Q39-S39)/Q39*100 -> #DIV/0! | AB39: =W39*1.5% -> 0 | AC39: =(S39/1.11) -> 0
B40: CBPI 11402 | C40: INV-550/2609/02817 | D40: Dhea Zautha | E40: 13669017 | F40: Indonesia | G40: 1 | I40: 1 | K40: WATCHES | L40: 103740 | M40: RE00020 | N40: BUBVZ73 | O40: W GG41 HMSD STE GRE STE AUT *LEAFLET & BOX OCTO ROMA | P40: 1 | Q40: 152300000 | R40: =(Q40-S40)/Q40*100 -> 0 | S40: =Q40 -> 152300000 | V40: =S40 -> 152300000 | Y40: BCA | AB40: =W40*1.5% -> 0 | AC40: =(S40/1.11) -> 1.3720721e+08 | AE40: SK | AF40: SK | AG40: SK | AH40: 804190 | AI40: 806422 | AJ40: EXCHANGE 3 DAYS
R41: =(Q41-S41)/Q41*100 -> #DIV/0! | AB41: =W41*0.15% -> 0 | AC41: =(S41/1.11) -> 0 | AH41: 807617
R42: =(Q42-S42)/Q42*100 -> #DIV/0! | AB42: =W42*1.5% -> 0 | AC42: =(S42/1.11) -> 0 | AH42: 806857
R43: =(Q43-S43)/Q43*100 -> #DIV/0! | AB43: =W43*1.5% -> 0 | AC43: =(S43/1.11) -> 0 | AH43: 807853
R44: =(Q44-S44)/Q44*100 -> #DIV/0! | AB44: =W44*1.5% -> 0 | AC44: =(S44/1.11) -> 0 | AH44: 807304
B45: CBPI 11403 | C45: SI-550/2609/37781 | D45: Disa Soraya | E45: 13121480 | F45: Indonesia | G45: 1 | I45: 1 | K45: JEWELRY | L45: 362394 | M45: CL860844 | N45: ARR775 | O45: CL B01 MINI WG-6.9grs 48PAVE-0.25ct ON THE EDGES PENDANT | P45: 1 | Q45: 81000000 | R45: =(Q45-S45)/Q45*100 -> 0 | S45: =Q45 -> 81000000 | W45: =S45 -> 81000000 | Z45: MDR | AA45: D/MDR | AB45: =W45*1.9% -> 1539000 | AC45: =(S45/1.11) -> 72972973 | AE45: JJ | AF45: JJ | AG45: JJ | AH45: 806856 | AI45: 806422
R46: =(Q46-S46)/Q46*100 -> #DIV/0! | AB46: =W46*1.3% -> 0 | AC46: =(S46/1.11) -> 0 | AH46: 807617
R47: =(Q47-S47)/Q47*100 -> #DIV/0! | AB47: =W47*1.5% -> 0 | AC47: =(S47/1.11) -> 0 | AH47: 807567
B48: CBPI 11405 | C48: INV-PI/2609/02819 | D48: Nana Eulia | E48: 13245846 | F48: Indonesia | H48: 1 | I48: 1 | K48: JEWELRY | L48: 357986 | M48: AN859090 | N48: TPAK8R | O48: AN B01 ROCK 2BANDS PG-9.4grs 2BCR-0.10 Sz 48 | P48: 1 | Q48: 69400000 | R48: =(Q48-S48)/Q48*100 -> 0 | S48: =Q48 -> 69400000 | V48: =S48 -> 69400000 | Y48: BCA | AB48: =W48*0.15% -> 0 | AC48: =(S48/1.11) -> 62522523 | AE48: JJ | AF48: JJ | AG48: JJ | AH48: 808138 | AI48: 806422
R49: =(Q49-S49)/Q49*100 -> #DIV/0! | AB49: =W49*2.25% -> 0 | AC49: =(S49/1.11) -> 0 | AH49: 806856
R50: =(Q50-S50)/Q50*100 -> #DIV/0! | AB50: =W50*1.5% -> 0 | AC50: =(S50/1.11) -> 0 | AH50: 807617
B51: CBPI 11406 | C51: INV-550/2609/02820 | D51: Yossi Leonita | E51: 13558612 | F51: Indonesia | H51: 1 | J51: 1 | K51: WATCHES | L51: 104277 | M51: RE00133 | N51: BUD653V | O51: W BB23 HM STE-GL3N WHT MOP STE-GL3N DIAM *LEAFLET | P51: 1 | Q51: 203800000 | R51: =(Q51-S51)/Q51*100 -> 0 | S51: =Q51 -> 203800000 | W51: 371400000 | Z51: MDR | AA51: D/MDR | AB51: =W51*1.9% -> 7056600 | AC51: =(S51/1.11) -> 1.836036e+08 | AE51: SK | AF51: SK | AG51: SK | AH51: 807853 | AI51: 806422
K52: JEWELRY | L52: 354731 | M52: OR858201 | N52: 6ZW8N1 | O52: OR (SINGLE) BGB PG-2.0grs 14PAVE-0.09ct | P52: 1 | Q52: 35100000 | R52: =(Q52-S52)/Q52*100 -> 0 | S52: =Q52 -> 35100000 | AB52: =W52*1.5% -> 0 | AC52: =(S52/1.11) -> 31621622 | AH52: 807617 | AI52: 806422
K53: JEWELRY | L53: 350641 | M53: BR857243 | N53: AR1P34 | O53: BR BGB PG-10.4grs 2MOP-0.35 2ONYX-0.33 Sz SM | P53: 1 | Q53: 97400000 | R53: =(Q53-S53)/Q53*100 -> 0 | S53: =Q53 -> 97400000 | AB53: =W53*1.5% -> 0 | AC53: =(S53/1.11) -> 87747748 | AH53: 804189 | AI53: 806422
K54: JEWELRY | L54: 354731 | M54: OR858201 | N54: AF3Y92 | O54: OR (SINGLE) BGB PG-2.0grs 14PAVE-0.09ct | P54: 1 | Q54: 35100000 | R54: =(Q54-S54)/Q54*100 -> 0 | S54: =Q54 -> 35100000 | AB54: =W54*1.5% -> 0 | AC54: =(S54/1.11) -> 31621622 | AH54: 804189 | AI54: 806422
R55: =(Q55-S55)/Q55*100 -> #DIV/0! | AB55: =W55*1.7% -> 0 | AC55: =(S55/1.11) -> 0 | AH55: 804279
R56: =(Q56-S56)/Q56*100 -> #DIV/0! | AB56: =W56*1.5% -> 0 | AC56: =(S56/1.11) -> 0 | AH56: 807569
R57: =(Q57-S57)/Q57*100 -> #DIV/0! | AB57: =W57*2.2% -> 0 | AC57: =(S57/1.11) -> 0 | AD57: =SUM(AC36:AC57) -> 6.5127928e+08 | AH57: 807572
A58: 46271 | B58: CBPI 11407 | C58: INV-550/2609/02821 | D58: Tiara Rinardi | E58: 13167381 | F58: Indonesia | H58: 1 | J58: 1 | K58: JEWELRY | L58: 357846 | M58: BR859000 | N58: R4P3LL | O58: BR B01 BANGLE WG-24.4grs 100PAVE-1.01cts Sz M | P58: 1 | Q58: 371000000 | R58: =(Q58-S58)/Q58*100 -> 0 | S58: 371000000 | U58: CBPI 11354 | AB58: =W58*1.75% -> 0 | AC58: =(S58/1.11) -> 3.3423423e+08 | AE58: HS | AF58: HS | AG58: HS | AH58: 806857 | AI58: 806422
R59: =(Q59-S59)/Q59*100 -> #DIV/0! | AB59: =W59*1.7% -> 0 | AC59: =(S59/1.11) -> 0 | AH59: 807568
B60: CBPI 11408 | C60: INV-550/2609/02822 | D60: Irma Kurniawati | E60: 13232721 | F60: Indonesia | H60: 1 | J60: 1 | K60: JEWELRY | L60: 357868 | M60: AN858824 | N60: AP3M65 | O60: AN SSC 2COILS PG-10.6grs 6PAVE-0.10ct ON HEAD & TAIL Sz L | P60: 1 | Q60: 114600000 | R60: =(Q60-S60)/Q60*100 -> 0 | S60: 114600000 | V60: 100000000 | Y60: MANDIRI | AB60: =W60*0.15% -> 0 | AC60: =(S60/1.11) -> 1.0324324e+08 | AE60: IR | AF60: IR | AG60: IR | AH60: 806857 | AI60: 806422 | AJ60: HOME DELIVERY
R61: =(Q61-S61)/Q61*100 -> #DIV/0! | W61: 14600000 | Z61: BCA | AA61: M/BCA | AB61: =W61*1.3% -> 189800 | AC61: =(S61/1.11) -> 0 | AH61: 806742 | AJ61: 80 : 20 (HS)
R62: =(Q62-S62)/Q62*100 -> #DIV/0! | AB62: =W62*2.2% -> 0 | AC62: =(S62/1.11) -> 0 | AH62: 807617
B63: CBPI 11409 | C63: SI-550/2609/37785 | D63: Valencia Saputra | E63: 13670056 | F63: Indonesia | H63: 1 | I63: 1 | M63: DEPOSIT | O63: Deposit RSI 360699 - OR859982 - 6EWXS7 | R63: =(Q63-S63)/Q63*100 -> #DIV/0! | W63: 100000000 | Z63: BCA | AA63: V/UOB | AB63: =W63*1.3% -> 1300000 | AC63: =(S63/1.11) -> 0 | AE63: JJ | AF63: JJ | AH63: 807617
B64: CBPI 11433 | C64: INV-550/2609/02823 | D64: Johny Wiraatmadja | E64: 13672905 | F64: Indonesia | G64: 1 | I64: 1 | K64: WATCHES | L64: 103689 | M64: BBL33C6SS/12/QZ | N64: BU9VB7J | O64: W BB33 HM STE ANT STE DIAM-STO D1 QTZ *LEAFLET | P64: 1 | Q64: 107900000 | R64: =(Q64-S64)/Q64*100 -> 0 | S64: 107900000 | W64: 107900000 | Z64: BCA | AA64: V/BCA | AB64: =W64*1.3% -> 1402700 | AC64: =(S64/1.11) -> 97207207 | AE64: SK | AF64: SK | AG64: SK | AH64: 807572 | AI64: 806422
R65: =(Q65-S65)/Q65*100 -> #DIV/0! | AB65: =W65*0.15% -> 0 | AC65: =(S65/1.11) -> 0 | AH65: 807617
R66: =(Q66-S66)/Q66*100 -> #DIV/0! | AB66: =W66*1.7% -> 0 | AC66: =(S66/1.11) -> 0 | AH66: 807853
R67: =(Q67-S67)/Q67*100 -> #DIV/0! | AB67: =W67*1.5% -> 0 | AC67: =(S67/1.11) -> 0 | AH67: 806857
B68: CBPI 11410 | C68: SI-PI/2609/37789 | D68: Felicia Mirabel | E68: 13357958 | F68: Indonesia | H68: 1 | J68: 1 | K68: JEWELRY | L68: 362344 | M68: CL860820 | N68: AR8391 | O68: CL B01 MINI PG-6.4grs 48PAVE-0.25ct ON THE EDGES PENDANT | P68: 1 | Q68: 76100000 | R68: =(Q68-S68)/Q68*100 -> 0 | S68: 76100000 | W68: 76100000 | Z68: BCA | AA68: D/BCA | AB68: =W68*0.15% -> 114150 | AC68: =(S68/1.11) -> 68558559 | AE68: IR | AF68: JJ | AG68: JJ | AH68: 806856 | AI68: 806422 | AJ68: 70 : 30
R69: =(Q69-S69)/Q69*100 -> #DIV/0! | AB69: =W69*7% -> 0 | AC69: =(S69/1.11) -> 0 | AH69: 807617
R70: =(Q70-S70)/Q70*100 -> #DIV/0! | AB70: =W70*1% -> 0 | AC70: =(S70/1.11) -> 0 | AH70: 807567
B71: CBPI 11411 | C71: SI-PI/2609/37790 | D71: Shania Maureen | E71: 13669946 | F71: Indonesia | H71: 1 | I71: 1 | M71: DEPOSIT | O71: Deposit RSI 336003 - TVTM44 & 349707 - 751H55 | R71: =(Q71-S71)/Q71*100 -> #DIV/0! | W71: 223900000 | Z71: MANDIRI | AA71: V/MANDIRI | AB71: =W71*1.9% -> 4254100 | AC71: =(S71/1.11) -> 0 | AE71: AL | AF71: AL | AH71: 807617
B72: CBPI 11412 | C72: SI-PI/2609/37791 | D72: Rica Septiyana | E72: 13435588 | F72: Indonesia | H72: 1 | J72: 1 | K72: JEWELRY | L72: 357794 | M72: CL858925 | N72: ARL648 | O72: CL SSC PG-12.6grs 7PAVE-0.13ct PENDANT | P72: 1 | Q72: 115500000 | R72: =(Q72-S72)/Q72*100 -> 0 | S72: 115500000 | T72: CASHBACK BCA RP 2,500,000 | W72: 113000000 | Z72: BCA | AA72: M/BCA(6X) | AB72: =W72*4% -> 4520000 | AC72: =(S72/1.11) -> 1.0405405e+08 | AE72: IR | AF72: IR | AG72: IR | AH72: 807567 | AI72: 806422 | AJ72: HOME DELIVERY
R73: =(Q73-S73)/Q73*100 -> #DIV/0! | AB73: =W73*0.15% -> 0 | AC73: =(S73/1.11) -> 0 | AH73: 807617 | AJ73: 80 : 20 (HS)
R74: =(Q74-S74)/Q74*100 -> #DIV/0! | AB74: =W74*0.15% -> 0 | AC74: =(S74/1.11) -> 0 | AD74: =SUM(AC58:AC74) -> 7.072973e+08 | AH74: 806856 | AJ74: CASHBACK BCA RP 2,500,000
A75: 46272 | B75: CBPI 11415 | C75: SI-PI/2609/37793 | D75: Wei Ge | E75: 13672609 | F75: China | G75: 1 | I75: 1 | K75: JEWELRY | L75: 361838 | M75: CL860377 | N75: ARX136 | O75: CL DIVA YG-6.0grs 1DIA-0.03ct 1ONYX-0.24 11PAVE-0.10ct PENDANT | P75: 1 | Q75: 75100000 | R75: =(Q75-S75)/Q75*100 -> 0 | S75: =Q75 -> 75100000 | W75: =S75 -> 75100000 | Z75: BRI | AA75: V/UNIONPAY | AB75: =W75*1.7% -> 1276700 | AC75: =(S75/1.11) -> 67657658 | AE75: DP | AF75: DP | AG75: DP | AH75: 806856 | AI75: 806422 | AJ75: VAT
R76: =(Q76-S76)/Q76*100 -> #DIV/0! | AB76: =W76*1.5% -> 0 | AC76: =(S76/1.11) -> 0 | AH76: 807617
R77: =(Q77-S77)/Q77*100 -> #DIV/0! | AB77: =W77*0.15% -> 0 | AC77: =(S77/1.11) -> 0 | AH77: 807567
B78: CBPI 11416 | C78: INV-PI/2609/02827 | D78: Sarah Tio | E78: 13644026 | F78: Indonesia | H78: 1 | J78: 1 | K78: JEWELRY | L78: 350898 | M78: BR857359 | N78: AMT565 | O78: BR B01 MINI WG-8.3grs 51PAVE-0.31ct Sz SM | P78: 1 | Q78: 113600000 | R78: =(Q78-S78)/Q78*100 -> 0 | S78: =Q78 -> 113600000 | W78: =S78 -> 113600000 | Z78: BCA | AA78: D/BCA | AB78: =W78*0.15% -> 170400 | AC78: =(S78/1.11) -> 1.0234234e+08 | AE78: AL | AF78: AL | AG78: AL | AH78: 807569 | AI78: 806422
R79: =(Q79-S79)/Q79*100 -> #DIV/0! | AB79: =W79*1.5% -> 0 | AC79: =(S79/1.11) -> 0 | AH79: 806856
R80: =(Q80-S80)/Q80*100 -> #DIV/0! | AB80: =W80*1.5% -> 0 | AC80: =(S80/1.11) -> 0 | AH80: 807617
B81: CBPI 11418 | C81: INV-PI/2609/02828 | D81: Donald Panggari | E81: 13671383 | F81: Indonesia | G81: 1 | I81: 1 | K81: JEWELRY | L81: 358228 | M81: AN859080 | N81: T4TRWM | O81: AN B01 ROCK 1BAND PG-9.1grs 2BCR-0.10 Sz 50 | P81: 1 | Q81: 59300000 | R81: =(Q81-S81)/Q81*100 -> 0 | S81: =Q81 -> 59300000 | W81: =S81 -> 59300000 | Z81: BCA | AA81: D/BCA | AB81: =W81*0.15% -> 88950 | AC81: =(S81/1.11) -> 53423423 | AE81: AL | AF81: AL | AG81: AL | AH81: 806856 | AI81: 806422 | AJ81: EXCHANGE 5 DAYS UNTIL 12/09/26 (MM)
R82: =(Q82-S82)/Q82*100 -> #DIV/0! | AB82: =W82*1.5% -> 0 | AC82: =(S82/1.11) -> 0 | AH82: 807617
R83: =(Q83-S83)/Q83*100 -> #DIV/0! | AB83: =W83*1.75% -> 0 | AC83: =(S83/1.11) -> 0 | AD83: =SUM(AC75:AC83) -> 2.2342342e+08 | AH83: 806742
A84: 46273 | B84: CBPI 11419 | C84: SI-PI/2609/37799 | D84: Valencia Saputra | E84: 13670056 | F84: Indonesia | G84: 1 | J84: 1 | K84: JEWELRY | L84: 360699 | M84: OR859982 | N84: 6EWXS7 | O84: OR DIVA PG-17.2grs 2DIA-0.40ct 2RBLT-0.60 3MOP-0.59 150PAVE-1.81cts | P84: 1 | Q84: 813700000 | R84: =(Q84-S84)/Q84*100 -> 5 | S84: 773015000 | T84: DISC APPROVAL BU PUTRI | U84: CBPI 11409 | V84: 673015000 | Y84: BCA | AB84: =W84*1.5% -> 0 | AC84: =(S84/1.11) -> 6.9640991e+08 | AE84: JJ | AF84: JJ | AG84: JJ | AH84: 807574 | AI84: 806422
R85: =(Q85-S85)/Q85*100 -> #DIV/0! | AB85: =W85*1.5% -> 0 | AC85: =(S85/1.11) -> 0 | AH85: 806857
R86: =(Q86-S86)/Q86*100 -> #DIV/0! | AB86: =W86*1.5% -> 0 | AC86: =(S86/1.11) -> 0 | AH86: 807617
B87: CBPI 11423 | C87: INV-PI/2609/02834 | D87: Elly Kartini | E87: 13236928 | F87: Indonesia | H87: 1 | J87: 1 | K87: JEWELRY | L87: 361839 | M87: OR860376 | N87: AF9K21 | O87: OR DIVA YG-2.7grs 2ONYX-0.18 48PAVE-0.10ct | P87: 1 | Q87: 67500000 | R87: =(Q87-S87)/Q87*100 -> 0 | S87: =Q87 -> 67500000 | W87: =S87 -> 67500000 | Z87: MDR | AA87: V/MDR | AB87: =W87*1.7% -> 1147500 | AC87: =(S87/1.11) -> 60810811 | AE87: AJ | AF87: AJ | AG87: AJ | AH87: 806856 | AI87: 806422
R88: =(Q88-S88)/Q88*100 -> #DIV/0! | AB88: =W88*1.5% -> 0 | AC88: =(S88/1.11) -> 0 | AH88: 807617
R89: =(Q89-S89)/Q89*100 -> #DIV/0! | AB89: =W89*1.5% -> 0 | AC89: =(S89/1.11) -> 0 | AD89: =SUM(AC84:AC89) -> 7.5722072e+08 | AH89: 807570
A90: 46274 | B90: CBPI 11424 | C90: SI-550/2609/37814 | D90: Valencia Saputra | E90: 13670056 | F90: Indonesia | H90: 1 | J90: 1 | K90: JEWELRY | L90: 361357 | M90: BR860201 | N90: 6AS9YL | O90: BR SVI 2ROW PG-38.4grs TITANIUM-4.2 126PAVE-5.30cts Sz 15 | P90: 1 | Q90: 1601600000 | R90: =(Q90-S90)/Q90*100 -> 10.402098 | S90: 1435000000 | T90: DISC APPROVAL BU PUTRI | V90: 1435000000 | Y90: BCA | AB90: =W90*1.4% -> 0 | AC90: =(S90/1.11) -> 1.2927928e+09 | AE90: JJ | AF90: JJ | AG90: JJ | AH90: 807571 | AI90: 806422 | AJ90: HOME DELIVERY
R91: =(Q91-S91)/Q91*100 -> #DIV/0! | AB91: =W91*1.5% -> 0 | AC91: =(S91/1.11) -> 0 | AH91: 806857 | AJ91: GV BHR
R92: =(Q92-S92)/Q92*100 -> #DIV/0! | AB92: =W92*1.5% -> 0 | AC92: =(S92/1.11) -> 0 | AH92: 807617
B93: CBPI 11426 | C93: INV-550/2609/02837 | D93: Christy Christy | E93: 13131082 | F93: Indonesia | H93: 1 | J93: 1 | K93: JEWELRY | L93: 351052 | M93: BR857363 | N93: 71EHX4 | O93: BR DIVA PG-3.9grs 24PAVE-0.26ct Sz SM | P93: 1 | Q93: 121500000 | R93: =(Q93-S93)/Q93*100 -> 0 | S93: 121500000 | V93: 121500000 | Y93: BCA | AB93: =W93*1.4% -> 0 | AC93: =(S93/1.11) -> 1.0945946e+08 | AE93: AJ | AF93: AJ | AG93: AJ | AH93: 807569 | AI93: 806422 | AJ93: HOME DELIVERY
R94: =(Q94-S94)/Q94*100 -> #DIV/0! | AB94: =W94*1.3% -> 0 | AC94: =(S94/1.11) -> 0 | AH94: 806856
R95: =(Q95-S95)/Q95*100 -> #DIV/0! | AB95: =W95*0.15% -> 0 | AC95: =(S95/1.11) -> 0 | AH95: 807617
B96: CBPI 11427 | C96: SI-550/2609/37819 | D96: Serly Serly | E96: 13180410 | F96: Indonesia | G96: 1 | I96: 1 | K96: JEWELRY | L96: 362345 | M96: CL860784 | N96: ALSS00 | O96: CL B01 MINI YG-6.6grs 48PAVE-0.25ct ON THE EDGES PENDANT | P96: 1 | Q96: 76100000 | R96: =(Q96-S96)/Q96*100 -> 0 | S96: 76100000 | T96: CASHBACK MAYBANK RP 2,500,000 | W96: 47500000 | Z96: MANDIRI | AA96: V/MAYBANK 3X | AB96: =W96*1% -> 475000 | AC96: =(S96/1.11) -> 68558559 | AE96: DP | AF96: DP | AG96: DP | AH96: 807567 | AI96: 806422 | AJ96: CASHBACK MAYBANK RP 2,500,000
R97: =(Q97-S97)/Q97*100 -> #DIV/0! | W97: 26100000 | Z97: BCA | AA97: V/BCA | AB97: =W97*1.3% -> 339300 | AC97: =(S97/1.11) -> 0 | AH97: 806856
R98: =(Q98-S98)/Q98*100 -> #DIV/0! | AB98: =W98*1.5% -> 0 | AC98: =(S98/1.11) -> 0 | AD98: =SUM(AC90:AC98) -> 1.4708108e+09 | AH98: 807617
A99: 46275 | B99: CBPI 11428 | C99: SI-PI/2609/37822 | D99: Lisa Lissa | E99: 13664581 | F99: Indonesia | H99: 1 | J99: 1 | K99: JEWELRY | L99: 362344 | M99: CL860820 | N99: AR6C37 | O99: CL B01 MINI PG-6.4grs 48PAVE-0.25ct ON THE EDGES PENDANT | P99: 1 | Q99: 76100000 | R99: =(Q99-S99)/Q99*100 -> 0 | S99: =Q99 -> 76100000 | V99: =S99 -> 76100000 | Y99: BCA | AB99: =W99*1.4% -> 0 | AC99: =(S99/1.11) -> 68558559 | AE99: SK | AF99: SK | AG99: SK | AH99: 807569 | AI99: 806422
R100: =(Q100-S100)/Q100*100 -> #DIV/0! | AB100: =W100*1.4% -> 0 | AC100: =(S100/1.11) -> 0 | AH100: 807617
...

Sheet SC
A1: =DS!A1 -> BVLGARI – Plaza Indonesia
A2: Service Center Transaction Report
A3: Periode | B3: =DS!B3 -> 46266
A5: Date | B5: CB No. | C5: Repair Bill No | D5: Sales Invoice No | E5: Customer Name | F5: Cosmo CRM ID | G5: Nationality | H5: New | I5: Old | J5: W | K5: F | L5: Category | M5: SAP Code | N5: Item Name | O5: Serial No | P5: Description | Q5: Qty | R5: Gross Sales | S5: Disc. % | T5: Net Sales | U5: Payment | AC5: Achievement | AD5: Daily Total Achievement | AE5: Served By | AF5: CA | AG5: Entitle | AH5: After Sales Support | AI5: DWA | AJ5: Discount Given Reason | AK5: Other Remarks
U6: Deposit CB No | V6: Rp. | W6: Card | X6: OR No. | Y6: Bank Transfer To | Z6: EDC | AA6: Card Type | AB6: Card Commission
A7: 46266 | B7: NO REPAIR | S7: =(R7-T7)/R7*100 -> #DIV/0! | AB7: =W7*1.4% -> 0 | AC7: =(T7/1.11) -> 0 | AD7: =SUM(AC7) -> 0
A8: 46267 | B8: CBPI 11386 | D8: SI-550/2609/37751 | E8: Susana Tatang | F8: 13669871 | G8: Indonesia | N8: DEPOSIT | P8: Deposit 50% RBPI 8094620 | S8: =(R8-T8)/R8*100 -> #DIV/0! | V8: 1200000 | Y8: BCA | AB8: =W8*1.3% -> 0 | AC8: =(T8/1.11) -> 0 | AE8: JJ | AF8: JJ
B9: CBPI 11387 | D9: SI-550/2609/37752 | E9: Felix Kuosanto | F9: 13669875 | G9: Indonesia | N9: DEPOSIT | P9: Deposit FULL PAYMENT RBPI 8094615 | S9: =(R9-T9)/R9*100 -> #DIV/0! | V9: 2400000 | Y9: BCA | AB9: =W9*1.4% -> 0 | AC9: =(T9/1.11) -> 0 | AE9: AJ | AF9: AJ
B10: CBPI 11388 | C10: 8094609 | D10: INV-RBPI/2609/02801 | E10: Ratna Tedja | F10: 13654905 | G10: Indonesia | I10: 1 | K10: 1 | L10: WATCHES | M10: 0 | N10: BB 26 SG | O10: L419712 | P10: Complete Service | Q10: 1 | R10: 7300000 | S10: =(R10-T10)/R10*100 -> 0 | T10: 7300000 | U10: CBPI 11346 | W10: 3650000 | Z10: BCA | AA10: V/BCA | AB10: =W10*1.3% -> 47450 | AC10: =(T10/1.11) -> 6576576.6 | AE10: JJ | AF10: JJ | AG10: JJ | AH10: 806855 | AK10: SI-PI/2609/37755 (Sales Support)
S11: =(R11-T11)/R11*100 -> #DIV/0! | AB11: =W11*1.4% -> 0 | AC11: =(T11/1.11) -> 0 | AH11: 807616
B12: CBPI 11390 | C12: 8094614 | D12: INV-RBPI/2609/02804 | E12: Jhon Levis | F12: 13367243 | G12: Indonesia | I12: 1 | K12: 1 | L12: JEWELRY | M12: 344492 | N12: CL BB | O12: APN000 | P12: Oth COS (Extend Chain) | Q12: 1 | R12: 6200000 | S12: =(R12-T12)/R12*100 -> 0 | T12: 6200000 | U12: CBPI 11343 | AB12: =W12*1.4% -> 0 | AC12: =(T12/1.11) -> 5585585.6 | AD12: =SUM(AC8:AC12) -> 12162162 | AE12: DP | AF12: DP | AG12: DP
A13: 46268 | B13: CBPI 11391 | D13: INV-PI/2609/02805 | E13: Eddy Kurniawan | F13: 13447191 | G13: Indonesia | I13: 1 | K13: 1 | L13: AFSS | M13: 100189572 | N13: 100189572 | O13: 100189572 | P13: KIT-POUCH BRA GG41 CAO-ACI BLU CDP S.S I | Q13: 1 | R13: 5800000 | S13: =(R13-T13)/R13*100 -> 0 | T13: =R13 -> 5800000 | U13: CBPI 11032 | AB13: =W13*2.2% -> 0 | AC13: =(T13/1.11) -> 5225225.2 | AE13: JJ | AF13: JJ | AG13: JJ | AH13: 807617 | AK13: INV-PI/2609/02805 (Sales Support)
S14: =(R14-T14)/R14*100 -> #DIV/0! | AB14: =W14*1.5% -> 0 | AC14: =(T14/1.11) -> 0 | AH14: 807616
S15: =(R15-T15)/R15*100 -> #DIV/0! | AB15: =W15*1.4% -> 0 | AC15: =(T15/1.11) -> 0 | AD15: =SUM(AC13:AC15) -> 5225225.2 | AH15: 806855
A16: 46269 | B16: NO REPAIR | S16: =(R16-T16)/R16*100 -> #DIV/0! | AB16: =W16*1.4% -> 0 | AC16: =(T16/1.11) -> 0
A17: 46270 | B17: CBPI 11399 | D17: SI-RBPI/2609/37774 | E17: Radityo Wibowo | F17: 13626668 | N17: DEPOSIT | P17: Deposit Full Payment RBPI 8094606 | S17: =(R17-T17)/R17*100 -> #DIV/0! | V17: 1200000 | Y17: BCA | AB17: =W17*1.4% -> 0 | AC17: =(T17/1.11) -> 0 | AE17: AL | AF17: AL
B18: FOC | C18: 8094618 | D18: SI-RBPI/2609/37775 | E18: Cindy Chandriani | F18: 13632600 | G18: Indonesia | I18: 1 | K18: 1 | L18: JEWELRY | M18: 360338 | O18: AM4383 | P18: Oth COS (Engrave) | S18: =(R18-T18)/R18*100 -> #DIV/0! | AB18: =W18*0.15% -> 0 | AC18: =(T18/1.11) -> 0 | AE18: AL | AF18: AL | AG18: AL
B19: FOC | C19: 8094619 | D19: SI-RBPI/2609/37776 | E19: Cindy Chandriani | F19: 13632600 | G19: Indonesia | I19: 1 | K19: 1 | L19: JEWELRY | M19: 360362 | O19: W51AYL | P19: Oth COS (Engrave) | S19: =(R19-T19)/R19*100 -> #DIV/0! | AB19: =W19*2.25% -> 0 | AC19: =(T19/1.11) -> 0 | AE19: AL | AF19: AL | AG19: AL
S20: =(R20-T20)/R20*100 -> #DIV/0! | AB20: =W20*2.25% -> 0 | AC20: =(T20/1.11) -> 0
B21: CBPI 11404 | C21: 8094576 | D21: INV-RBPI/2609/02818 | E21: Rizky Pulungan | F21: 13521092 | G21: Indonesia | I21: 1 | K21: 1 | L21: WATCHES | M21: 101353 | N21: BB26WSSD/N | O21: O4633 | P21: Complete Service | Q21: 1 | R21: 7300000 | S21: =(R21-T21)/R21*100 -> 0 | T21: =R21 -> 7300000 | U21: CBPI 11315 | W21: 3650000 | Z21: BCA | AA21: M/CIMB | AB21: =W21*1.3% -> 47450 | AC21: =(T21/1.11) -> 6576576.6 | AE21: AJ | AF21: AJ | AG21: AJ | AH21: 807616 | AK21: SI-PI/2609/37782 (Sales Support)
S22: =(R22-T22)/R22*100 -> #DIV/0! | AB22: =W22*1.5% -> 0 | AC22: =(T22/1.11) -> 0 | AH22: 807617
S23: =(R23-T23)/R23*100 -> #DIV/0! | AB23: =W23*0.15% -> 0 | AC23: =(T23/1.11) -> 0 | AD23: =SUM(AC17:AC23) -> 6576576.6 | AH23: 806855
A24: 46271 | B24: FOC | C24: 8094622 | D24: SI-RBPI/2609/37786 | E24: Sandredee Siwalette | F24: 13251950 | G24: Indonesia | I24: 1 | K24: 1 | L24: WATCHES | M24: 103471 | N24: RE00082 | O24: BUB64BG | P24: Basic Service (Purchase Warranty) | S24: =(R24-T24)/R24*100 -> #DIV/0! | AB24: =W24*0.15% -> 0 | AC24: =(T24/1.11) -> 0 | AD24: =SUM(AC24) -> 0 | AE24: DP | AF24: DP | AG24: DP | AH24: 806855 | AK24: SI-PI/2609/37787 (Sales Support)
A25: 46272 | B25: CBPI 11413 | D25: SI-RBPI/2609/37792 | E25: Cially Than | F25: 13209277 | N25: DEPOSIT | P25: DEPOSIT FULL PAYMENT RBPI 8094634 | S25: =(R25-T25)/R25*100 -> #DIV/0! | V25: 3500000 | Y25: BCA | AB25: =W25*1.4% -> 0 | AC25: =(T25/1.11) -> 0 | AE25: DP | AF25: DP | AH25: 807616
B26: CBPI 11414 | D26: INV-PI/2609/02826 | E26: Lely Natali | F26: 13675397 | G26: Indonesia | I26: 1 | K26: 1 | L26: AFSS | M26: 100117486 | N26: 100117486 | O26: 100117486 | P26: BRA BZ30 CLF BLK GLS S.M I16.00 B12.00 | Q26: 1 | R26: 4000000 | S26: =(R26-T26)/R26*100 -> 0 | T26: =R26 -> 4000000 | W26: =T26 -> 4000000 | Z26: BCA | AA26: V/UOB | AB26: =W26*1.3% -> 52000 | AC26: =(T26/1.11) -> 3603603.6 | AE26: AJ | AF26: DP | AG26: DP
B27: CBPI 11417 | D27: SI-RBPI/2609/37797 | E27: Alexandra Askandar | F27: 13481737 | N27: DEPOSIT | P27: DEPOSIT 50% RBPI 8094590 | S27: =(R27-T27)/R27*100 -> #DIV/0! | V27: 1200000 | Z27: MDR | AB27: =W27*1.5% -> 0 | AC27: =(T27/1.11) -> 0 | AD27: =SUM(AC25:AC27) -> 3603603.6 | AE27: IR | AF27: IR
A28: 46273 | B28: CBPI 11420 | C28: 8094627 | D28: INV-RBPI/2609/02830 | E28: Karima Anjani | F28: 13677331 | G28: Indonesia | I28: 1 | K28: 1 | L28: WATCHES | M28: 100264 | N28: BB33WSSD | O28: L9030 | P28: Diagnostic Fee | Q28: 1 | R28: 350000 | S28: =(R28-T28)/R28*100 -> 0 | T28: =R28 -> 350000 | W28: =T28 -> 350000 | Z28: BCA | AA28: V/BCA | AB28: =W28*1.25% -> 4375 | AC28: =(T28/1.11) -> 315315.32
B29: CBPI 11421 | C29: 8094606 | D29: INV-RBPI/2609/02831 | E29: Radityo Wibowo | F29: 13626668 | G29: Indonesia | I29: 1 | K29: 1 | L29: WATCHES | M29: 100233 | N29: BB30 SSD | O29: F32905 | P29: Basic Service | Q29: 1 | R29: 2400000 | S29: =(R29-T29)/R29*100 -> 0 | T29: =R29 -> 2400000 | U29: CBPI 11308, 11399 | AB29: =W29*1.5% -> 0 | AC29: =(T29/1.11) -> 2162162.2 | AE29: AK | AF29: AL | AG29: AL | AH29: 807617 | AK29: SI-PI/2609/37801 (Sales Support)
S30: =(R30-T30)/R30*100 -> #DIV/0! | AB30: =W30*1.3% -> 0 | AC30: =(T30/1.11) -> 0 | AH30: 807616
S31: =(R31-T31)/R31*100 -> #DIV/0! | AB31: =W31*1.5% -> 0 | AC31: =(T31/1.11) -> 0 | AH31: 806855
B32: FOC | C32: 8094632 | D32: SI-RBPI/2609/37802 | E32: Friska Theresia | F32: 13597281 | G32: Indonesia | I32: 1 | K32: 1 | L32: JEWELRY | M32: 358771 | N32: AN859325 | O32: 7LYWCR | P32: Oth COS (Engrave) | S32: =(R32-T32)/R32*100 -> #DIV/0! | AB32: =W32*1.5% -> 0 | AC32: =(T32/1.11) -> 0 | AE32: AK | AF32: AK | AG32: AK
B33: FOC | C33: 8094633 | D33: SI-RBPI/2609/37803 | E33: Friska Theresia | F33: 13597281 | G33: Indonesia | I33: 1 | K33: 1 | L33: JEWELRY | M33: 353268 | N33: AN857896 | O33: ANH353 | P33: Oth COS (Engrave) | S33: =(R33-T33)/R33*100 -> #DIV/0! | AB33: =W33*1.3% -> 0 | AC33: =(T33/1.11) -> 0 | AD33: =SUM(AC28:AC33) -> 2477477.5 | AE33: AK | AF33: AK | AG33: AK
A34: 46274 | B34: CBPI 11425 | D34: SI-RBPI/2609/37815 | E34: Andy Maulana | F34: 13677327 | G34: Indonesia | N34: DEPOSIT | P34: Deposit Full Payment RBPI 8094631 | S34: =(R34-T34)/R34*100 -> #DIV/0! | V34: 3600000 | Y34: BCA | AB34: =W34*1.5% -> 0 | AC34: =(T34/1.11) -> 0 | AD34: =SUM(AC34) -> 0 | AE34: AJ | AF34: AJ
A35: 46275 | B35: CBPI 11430 | C35: 8094601 | D35: INV-RBPI/2609/02839 | E35: Astari Napitupulu | F35: 13629783 | G35: Indonesia | I35: 1 | K35: 1 | L35: WATCHES | M35: 101886 | N35: BBL26WSS/12 | O35: PO4250 | P35: Basic Service | Q35: 1 | R35: 2400000 | S35: =(R35-T35)/R35*100 -> 0 | T35: =R35 -> 2400000 | U35: CBPI 11302 | W35: 1200000 | Z35: BCA | AA35: D/BCA | AB35: =W35*0.15% -> 1800 | AC35: =(T35/1.11) -> 2162162.2 | AE35: IR | AF35: SK | AG35: SK | AH35: 807616 | AK35: SI-PI/2609/37824 (Sales Support)
S36: =(R36-T36)/R36*100 -> #DIV/0! | T36: =R36 -> 0 | AB36: =W36*1.75% -> 0 | AC36: =(T36/1.11) -> 0 | AH36: 806855
S37: =(R37-T37)/R37*100 -> #DIV/0! | AB37: =W37*1.5% -> 0 | AC37: =(T37/1.11) -> 0 | AH37: 807617
A38: 46276 | B38: CBPI 11436 | C38: 8094620 | D38: INV-RBPI/2609/02843 | E38: Susana Tatang | F38: 13669871 | G38: Indonesia | I38: 1 | K38: 1 | L38: WATCHES | M38: 101887 | N38: BBL26WSPG/12 | O38: L5914 | P38: Basic Service | Q38: 1 | R38: 2400000 | S38: =(R38-T38)/R38*100 -> 0 | T38: =R38 -> 2400000 | U38: CBPI 11386 | W38: 1200000 | Z38: CIMBNIAGA | AA38: M//CIMBNIAGA | AB38: =W38*1.75% -> 21000 | AC38: =(T38/1.11) -> 2162162.2 | AE38: SK | AF38: JJ | AG38: JJ | AH38: 807617
S39: =(R39-T39)/R39*100 -> #DIV/0! | AB39: =W39*1.5% -> 0 | AC39: =(T39/1.11) -> 0 | AH39: 806855
S40: =(R40-T40)/R40*100 -> #DIV/0! | AB40: =W40*1.5% -> 0 | AC40: =(T40/1.11) -> 0 | AD40: =SUM(AC35:AC40) -> 4324324.3 | AH40: 807616 | AK40: SI-PI/2609/37833 (Sales Support)
A41: 46277 | B41: CBPI 11439 | C41: 8094566 | D41: INV-RBPI/2609/02848 | E41: Sita Satar | F41: 13570016 | G41: Indonesia | I41: 1 | K41: 1 | L41: WATCHES | M41: 100120 | N41: BB23 | O41: D107031 | P41: Complete Service | Q41: 1 | R41: 7300000 | S41: =(R41-T41)/R41*100 -> 0 | T41: 7300000 | U41: CBPI 11259 | W41: 3650000 | Z41: BCA | AA41: D/BCA | AB41: =W41*0.15% -> 5475 | AC41: =(T41/1.11) -> 6576576.6 | AE41: SK | AF41: SK | AG41: SK | AH41: 807616 | AK41: SI-PI/2609/37834 (Sales Support)
B42: CBPI 11440 | C42: 8094565 | D42: INV-RBPI/2609/02849 | E42: Sita Satar | F42: 13570016 | G42: Indonesia | L42: WATCHES | M42: 100765 | N42: RTC 49 S | O42: L5613 | P42: Basic Service | Q42: 1 | R42: 2800000 | S42: =(R42-T42)/R42*100 -> 0 | T42: 2800000 | U42: CBPI 11259 | W42: 1400000 | Z42: BCA | AA42: D/BCA | AB42: =W42*0.15% -> 2100 | AC42: =(T42/1.11) -> 2522522.5
B43: CBPI 11441 | D43: SI-RBPI/2609/37835 | E43: Sita Satar | F43: 13570016 | G43: Indonesia | N43: DEPOSIT | P43: DEPOSIT 50% RBPI 8094567 | S43: =(R43-T43)/R43*100 -> #DIV/0! | W43: 2525000 | Z43: BCA | AA43: V/DBS | AB43: =W43*1.3% -> 32825 | AC43: =(T43/1.11) -> 0 | AE43: SK | AF43: SK
S44: =(R44-T44)/R44*100 -> #DIV/0! | W44: 1125000 | Z44: BCA | AA44: D/BCA | AB44: =W44*0.15% -> 1687.5 | AC44: =(T44/1.11) -> 0
B45: CBPI 11442 | C45: 8094634 | D45: INV-RBPI/2609/02850 | E45: Cially Than | F45: 13209277 | G45: Indonesia | I45: 1 | K45: 1 | L45: JEWELRY | M45: 358349 | N45: CL859268 | O45: 7EA7AP | P45: Oth COS (Extend Chain) | Q45: 1 | R45: 3500000 | S45: =(R45-T45)/R45*100 -> 0 | T45: 3500000 | U45: CBPI 11413 | AB45: =W45*1.5% -> 0 | AC45: =(T45/1.11) -> 3153153.2 | AE45: DP | AF45: DP | AG45: DP
B46: FOC | C46: 8094621 | D46: SI-RBPI/2609/37840 | E46: Carrine Thunggawan | F46: 13646109 | G46: Indonesia | I46: 1 | K46: 1 | L46: JEWELRY | M46: 362345 | N46: CL860784 | O46: ANVA51 | P46: Oth COS (Extend Chain) | S46: =(R46-T46)/R46*100 -> #DIV/0! | AB46: =W46*1.5% -> 0 | AC46: =(T46/1.11) -> 0 | AE46: HS | AF46: HS | AG46: HS
B47: FOC | C47: 8094624 | D47: SI-RBPI/2609/37841 | E47: Michael Lee | F47: 13593245 | G47: Indonesia | I47: 1 | K47: 1 | L47: JEWELRY | M47: 362343 | N47: OR860719 | O47: ANVK23 | P47: Oth COS (SET PIN) | S47: =(R47-T47)/R47*100 -> #DIV/0! | AB47: =W47*1.4% -> 0 | AC47: =(T47/1.11) -> 0 | AE47: AL | AF47: AL | AG47: AL | AH47: 806855 | AK47: SI-PI/2609/37843 (Sales Support)
B48: FOC | C48: 8094623 | D48: SI-RBPI/2609/37842 | E48: Michael Lee | F48: 13593245 | L48: JEWELRY | M48: 362343 | N48: OR860719 | O48: ANVH31 | P48: Oth COS (SET PIN) | S48: =(R48-T48)/R48*100 -> #DIV/0! | AB48: =W48*0.15% -> 0 | AC48: =(T48/1.11) -> 0 | AE48: AL | AF48: AL | AG48: AL | AH48: 806775
B49: FOC | C49: 8094628 | D49: SI-RBPI/2609/37847 | E49: Sari Cahya | F49: 13114759 | G49: Indonesia | I49: 1 | K49: 1 | L49: JEWELRY | M49: 352815 | N49: CL857832 | O49: AHCZ41 | P49: Oth COS (Extend Chain) | S49: =(R49-T49)/R49*100 -> #DIV/0! | AB49: =W49*1.5% -> 0 | AC49: =(T49/1.11) -> 0 | AE49: JJ | AF49: JJ | AG49: JJ
B50: FOC | C50: 8094629 | D50: SI-RBPI/2609/37848 | E50: Sari Cahya | F50: 13114759 | L50: JEWELRY | M50: 361293 | N50: OR860238 | O50: 6WVM6T | P50: Oth COS (SET PIN) | S50: =(R50-T50)/R50*100 -> #DIV/0! | AB50: =W50*1.5% -> 0 | AC50: =(T50/1.11) -> 0 | AE50: JJ | AF50: JJ | AG50: JJ
B51: FOC | C51: 8094630 | D51: SI-RBPI/2609/37849 | E51: Sari Cahya | F51: 13114759 | L51: JEWELRY | M51: 362189 | N51: OR860558 | O51: AKZ333 | P51: Oth COS (SET PIN) | S51: =(R51-T51)/R51*100 -> #DIV/0! | AB51: =W51*1.5% -> 0 | AC51: =(T51/1.11) -> 0 | AD51: =SUM(AC41:AC51) -> 12252252 | AE51: JJ | AF51: JJ | AG51: JJ
A52: 46278 | B52: CBPI 11449 | C52: 8094608 | D52: INV-RBPI/2609/02857 | E52: Agistia Puspitasari | F52: 13643721 | G52: Indonesia | I52: 1 | K52: 1 | L52: WATCHES | M52: 100248 | N52: BB33SGD | O52: L171182 | P52: Complete Service | Q52: 1 | R52: 7300000 | S52: =(R52-T52)/R52*100 -> 0 | T52: 7300000 | U52: CBPI 11339 | W52: 3650000 | Z52: BCA | AA52: D/BCA | AB52: =W52*0.15% -> 5475 | AC52: =(T52/1.11) -> 6576576.6 | AE52: AK | AF52: AK | AG52: AK
B53: CBPI 11452 | C53: 8094602 | D53: INV-RBPI/2609/02859 | E53: Mellisa Woen | F53: 13636665 | G53: Indonesia | I53: 1 | K53: 1 | L53: WATCHES | M53: 100777 | N53: BB23SS | O53: J290623 | P53: Basic Service | Q53: 1 | R53: 2400000 | S53: =(R53-T53)/R53*100 -> 0 | T53: 2400000 | U53: CBPI 11316 | W53: 1200000 | Z53: BCA | AA53: M/UOB | AB53: =W53*1.3% -> 15600 | AC53: =(T53/1.11) -> 2162162.2 | AE53: HS | AF53: HS | AG53: HS | AH53: 806856 | AK53: SI-PI/2609/37856 (Sales Support)
B54: CBPI 11453 | C54: 8094603 | D54: INV-RBPI/2609/02860 | E54: Mellisa Woen | F54: 13636665 | L54: WATCHES | M54: 100865 | N54: BB26.2TG | O54: D313893 | P54: Basic Service | Q54: 1 | R54: 2400000 | S54: =(R54-T54)/R54*100 -> 0 | T54: 2400000 | U54: CBPI 11316 | W54: 1200000 | Z54: BCA | AA54: M/UOB | AB54: =W54*1.4% -> 16800 | AC54: =(T54/1.11) -> 2162162.2 | AE54: HS | AF54: HS | AG54: HS | AH54: 807617
S55: =(R55-T55)/R55*100 -> #DIV/0! | AB55: =W55*1.4% -> 0 | AC55: =(T55/1.11) -> 0 | AH55: 807616
S56: =(R56-T56)/R56*100 -> #DIV/0! | AB56: =W56*1.4% -> 0 | AC56: =(T56/1.11) -> 0 | AH56: 807616
B57: FOC | C57: 8094636 | D57: SI-RBPI/2609/37854 | E57: Richard Wong | F57: 13365856 | G57: Indonesia | I57: 1 | K57: 1 | L57: JEWELRY | M57: 360333 | N57: AN859948 | O57: AK9N47 | P57: Oth COS (Engrave) | S57: =(R57-T57)/R57*100 -> #DIV/0! | AB57: =W57*1.5% -> 0 | AC57: =(T57/1.11) -> 0 | AE57: AL | AF57: AL | AG57: AL
B58: FOC | C58: 8094637 | D58: SI-RBPI/2609/37855 | E58: Richard Wong | F58: 13365856 | L58: JEWELRY | M58: 360335 | N58: AN859948 | O58: 95XE77 | P58: Oth COS (Engrave) | S58: =(R58-T58)/R58*100 -> #DIV/0! | AB58: =W58*1.5% -> 0 | AC58: =(T58/1.11) -> 0 | AD58: =SUM(AC52:AC58) -> 10900901 | AE58: AL | AF58: AL | AG58: AL
A59: 46279 | B59: NO REPAIR | S59: =(R59-T59)/R59*100 -> #DIV/0! | AB59: =W59*1.4% -> 0 | AC59: =(T59/1.11) -> 0
A60: 46280 | B60: CBPI 11455 | C60: 8094605 | D60: INV-RBPI/2609/02869 | E60: Eka Setiawati | F60: 13258965 | G60: Indonesia | I60: 1 | K60: 1 | L60: WATCHES | M60: 101817 | N60: SP35C6SS.1T | O60: BUAMJVI | P60: Basic Service | Q60: 1 | R60: 2400000 | S60: =(R60-T60)/R60*100 -> 0 | T60: =R60 -> 2400000 | U60: CBPI 11358 | AB60: =W60*1.5% -> 0 | AC60: =(T60/1.11) -> 2162162.2 | AD60: =AC60 -> 2162162.2 | AE60: AJ | AF60: AJ | AG60: AJ | AH60: 807616 | AK60: SI-PI/2609/37870 (Sales Support)
B61: FOC | C61: 8094604 | D61: SI-RBPI/2609/37868 | E61: Eka Setiawati | F61: 13258965 | G61: Indonesia | I61: 1 | K61: 1 | L61: JEWELRY | M61: 362777 | N61: BR860954 | O61: ARC574 | P61: Others COS | S61: =(R61-T61)/R61*100 -> #DIV/0! | AB61: =W61*1.5% -> 0 | AC61: =(T61/1.11) -> 0 | AE61: AJ | AF61: AJ | AG61: AJ
A62: 46281 | B62: CBPI 11462 | C62: 8094585 | D62: INV-RBPI/2609/02874 | E62: Oei Ie Lan | F62: 13417083 | G62: Indonesia | I62: 1 | K62: 1 | L62: WATCHES | M62: 102532 | N62: SPC35BGDBCGD1.1T | O62: PO1334 | P62: Others COS | Q62: 1 | R62: 3400000 | S62: =(R62-T62)/R62*100 -> 0 | T62: =R62 -> 3400000 | U62: CBPI 11221 | AB62: =W62*1.5% -> 0 | AC62: =(T62/1.11) -> 3063063.1 | AD62: =AC62 -> 3063063.1 | AE62: HS | AF62: HS | AG62: HS | AH62: 807616 | AK62: SI-PI/2609/37876 (Sales Support)
A63: 46282 | B63: FOC | C63: 8094625 | D63: SI-RBPI/2609/37883 | E63: Alvin Ansari | F63: 13611412 | G63: Indonesia | L63: JEWELRY | M63: 353384 | O63: AF2M70 | P63: Others COS | S63: =(R63-T63)/R63*100 -> #DIV/0! | AB63: =W63*1.3% -> 0 | AC63: =(T63/1.11) -> 0
B64: FOC | C64: 8094624 | D64: SI-RBPI/2609/37884 | E64: Alvin Ansari | F64: 13611412 | G64: Indonesia | L64: JEWELRY | M64: 358816 | O64: APRY24 | P64: Others COS | S64: =(R64-T64)/R64*100 -> #DIV/0! | AB64: =W64*1.5% -> 0 | AC64: =(T64/1.11) -> 0
B65: CBPI 11467 | D65: SI-RBPI/2609/37886 | E65: Rindina Hundura | F65: 13690868 | N65: DEPOSIT | S65: =(R65-T65)/R65*100 -> #DIV/0! | V65: 1500000 | Y65: BCA | AB65: =W65*2.2% -> 0 | AC65: =(T65/1.11) -> 0 | AD65: =SUM(AC63:AC65) -> 0 | AE65: AJ | AF65: AJ
A66: 46283 | B66: CBPI 11468 | C66: 8094574 | D66: INV-RBPI/2609/02878 | E66: Fitria Al Habsy | F66: 13580951 | G66: Indonesia | I66: 1 | K66: 1 | L66: WATCHES | M66: - | N66: - | O66: LVF5FF | P66: Others COS | Q66: 1 | R66: 3100000 | S66: =(R66-T66)/R66*100 -> 0 | T66: =R66 -> 3100000 | U66: CBPI 11202 | V66: 1550000 | Y66: BCA | AB66: =W66*2.2% -> 0 | AC66: =(T66/1.11) -> 2792792.8 | AE66: AJ | AF66: AJ | AG66: AJ | AH66: 806855 | AK66: SI-PI/2609/37888 (Sales Support)
S67: =(R67-T67)/R67*100 -> #DIV/0! | AB67: =W67*0.15% -> 0 | AC67: =(T67/1.11) -> 0 | AD67: =SUM(AC66:AC67) -> 2792792.8 | AH67: 807612
A68: 46284 | B68: FOC | C68: 8094616 | D68: SI-RBPI/2609/37894 | E68: Christin Winata Halim | F68: 13114231 | G68: Indonesia | I68: 1 | K68: 1 | L68: JEWELRY | M68: 360310 | N68: CL859911 | O68: 6EX35V | P68: Others COS | S68: =(R68-T68)/R68*100 -> #DIV/0! | AB68: =W68*0.15% -> 0 | AC68: =(T68/1.11) -> 0 | AE68: IR | AF68: IR | AG68: IR
B69: FOC | C69: 8094598 | D69: SI-RBPI/2609/37898 | E69: Cindyana Puspa Dewi | F69: 13239795 | G69: Indonesia | I69: 1 | K69: 1 | L69: JEWELRY | M69: 336035 | N69: AN B01 | O69: CXT2SE | P69: Oth COS (Engrave) | S69: =(R69-T69)/R69*100 -> #DIV/0! | AB69: =W69*1.25% -> 0 | AC69: =(T69/1.11) -> 0 | AE69: HS | AF69: HS | AG69: HS | AH69: 806855 | AK69: SI-PI/2609/37900 (Sales Support)
B70: FOC | C70: 8094599 | D70: SI-RBPI/2609/37899 | E70: Cindyana Puspa Dewi | F70: 13239795 | L70: JEWELRY | M70: 336027 | N70: AN B01 | O70: AFME64 | P70: Oth COS (Engrave) | S70: =(R70-T70)/R70*100 -> #DIV/0! | AB70: =W70*0.15% -> 0 | AC70: =(T70/1.11) -> 0
B71: CBPI 11477 | D71: SI-RBPI/2609/37902 | E71: Henny Herjanto | G71: Indonesia | N71: DEPOSIT | P71: Deposit Full Payment RBPI 8094642 | S71: =(R71-T71)/R71*100 -> #DIV/0! | V71: 2400000 | Y71: BCA | AB71: =W71*1.5% -> 0 | AC71: =(T71/1.11) -> 0 | AD71: =SUM(AC68:AC71) -> 0 | AE71: AL | AF71: AL
A72: 46285 | B72: CBPI 11478 | C72: 8094635 | D72: INV-RBPI/2609/02888 | E72: Vilichea Sadikin | G72: Indonesia | I72: 1 | K72: 1 | L72: WATCHES | M72: - | N72: BJ02 | O72: G485 | P72: Diagnostic Fee | Q72: 1 | R72: 350000 | S72: =(R72-T72)/R72*100 -> 0 | T72: =R72 -> 350000 | W72: =T72 -> 350000 | Z72: CIMB NIAGA | AA72: M/CIMB NIAGA | AB72: =W72*0.15% -> 525 | AC72: =(T72/1.11) -> 315315.32 | AE72: AK | AF72: JJ | AG72: JJ | AH72: 807616 | AK72: SI-PI/2609/37906 (Sales Support)
S73: =(R73-T73)/R73*100 -> #DIV/0! | AB73: =W73*1.25% -> 0 | AC73: =(T73/1.11) -> 0 | AH73: 806855
B74: CBPI 11479 | D74: SI-RBPI/2609/37911 | E74: Mei Rita | N74: DEPOSIT | P74: Deposit 50% for RBPI 8094639 | S74: =(R74-T74)/R74*100 -> #DIV/0! | W74: 3650000 | Z74: BCA | AA74: M/UOB | AB74: =W74*1.3% -> 47450 | AC74: =(T74/1.11) -> 0 | AD74: =AC72 -> 315315.32 | AE74: AL | AF74: AL
S75: =(R75-T75)/R75*100 -> #DIV/0! | AB75: =W75*1.5% -> 0 | AC75: =(T75/1.11) -> 0
S76: =(R76-T76)/R76*100 -> #DIV/0! | AB76: =W76*1.5% -> 0 | AC76: =(T76/1.11) -> 0
S77: =(R77-T77)/R77*100 -> #DIV/0! | AB77: =W77*1.5% -> 0 | AC77: =(T77/1.11) -> 0
S78: =(R78-T78)/R78*100 -> #DIV/0! | AB78: =W78*1.5% -> 0 | AC78: =(T78/1.11) -> 0
S79: =(R79-T79)/R79*100 -> #DIV/0! | AB79: =W79*1.5% -> 0 | AC79: =(T79/1.11) -> 0
S80: =(R80-T80)/R80*100 -> #DIV/0! | AB80: =W80*1.3% -> 0 | AC80: =(T80/1.11) -> 0
S81: =(R81-T81)/R81*100 -> #DIV/0! | AB81: =W81*1.5% -> 0 | AC81: =(T81/1.11) -> 0
S82: =(R82-T82)/R82*100 -> #DIV/0! | AB82: =W82*1.5% -> 0 | AC82: =(T82/1.11) -> 0
S83: =(R83-T83)/R83*100 -> #DIV/0! | AB83: =W83*1.5% -> 0 | AC83: =(T83/1.11) -> 0
S84: =(R84-T84)/R84*100 -> #DIV/0! | AB84: =W84*1.7% -> 0 | AC84: =(T84/1.11) -> 0
S85: =(R85-T85)/R85*100 -> #DIV/0! | AB85: =W85*1.5% -> 0 | AC85: =(T85/1.11) -> 0
S86: =(R86-T86)/R86*100 -> #DIV/0! | AB86: =W86*1.5% -> 0 | AC86: =(T86/1.11) -> 0
S87: =(R87-T87)/R87*100 -> #DIV/0! | AB87: =W87*1.5% -> 0 | AC87: =(T87/1.11) -> 0
S88: =(R88-T88)/R88*100 -> #DIV/0! | AB88: =W88*1.3% -> 0 | AC88: =(T88/1.11) -> 0
S89: =(R89-T89)/R89*100 -> #DIV/0! | AB89: =W89*1.5% -> 0 | AC89: =(T89/1.11) -> 0
S90: =(R90-T90)/R90*100 -> #DIV/0! | AB90: =W90*1.5% -> 0 | AC90: =(T90/1.11) -> 0
S91: =(R91-T91)/R91*100 -> #DIV/0! | AB91: =W91*1.5% -> 0 | AC91: =(T91/1.11) -> 0
S92: =(R92-T92)/R92*100 -> #DIV/0! | AB92: =W92*1.5% -> 0 | AC92: =(T92/1.11) -> 0
S93: =(R93-T93)/R93*100 -> #DIV/0! | AB93: =W93*0.15% -> 0 | AC93: =(T93/1.11) -> 0
S94: =(R94-T94)/R94*100 -> #DIV/0! | AB94: =W94*1.5% -> 0 | AC94: =(T94/1.11) -> 0
S95: =(R95-T95)/R95*100 -> #DIV/0! | AB95: =W95*1.5% -> 0 | AC95: =(T95/1.11) -> 0
S96: =(R96-T96)/R96*100 -> #DIV/0! | AB96: =W96*1.4% -> 0 | AC96: =(T96/1.11) -> 0
S97: =(R97-T97)/R97*100 -> #DIV/0! | AB97: =W97*1.5% -> 0 | AC97: =(T97/1.11) -> 0
S98: =(R98-T98)/R98*100 -> #DIV/0! | AB98: =W98*1.5% -> 0 | AC98: =(T98/1.11) -> 0
S99: =(R99-T99)/R99*100 -> #DIV/0! | AB99: =W99*1.5% -> 0 | AC99: =(T99/1.11) -> 0
S100: =(R100-T100)/R100*100 -> #DIV/0! | AB100: =W100*1.5% -> 0 | AC100: =(T100/1.11) -> 0
S101: =(R101-T101)/R101*100 -> #DIV/0! | AB101: =W101*1.5% -> 0 | AC101: =(T101/1.11) -> 0
...

Sheet SMI
A1: =DS!A1 -> BVLGARI – Plaza Indonesia
A2: SMI Transaction Report
A3: Periode | B3: =DS!B3 -> 46266
AF4: HARUS DI ISI
A5: Date | B5: CB No. | C5: Sales Invoice No | D5: Customer Name | E5: Cosmo CRM ID | F5: Nationality | G5: New | H5: Old | I5: W | J5: F | K5: Category | L5: SAP Code | M5: Item Name | N5: Serial No | O5: Description | P5: Qty | Q5: Gross Sales | R5: Disc. % | S5: Net Sales | T5: Payment | AB5: Achievement | AC5: Daily Total Achievement | AD5: Served By | AE5: CA | AF5: Entitle | AG5: After Sales Support | AH5: DWA | AI5: SMI Commission | AJ5: Discount Given Reason | AK5: After Sales Support | AL5: Other Remarks
T6: Deposit CB No | U6: Rp. | V6: Card | W6: OR No. | X6: Bank Transfer To | Y6: EDC | Z6: Card Type | AA6: Card Commission
A7: 46269 | B7: CBPI 11396 | C7: INV-PI/2609/02812 | D7: Cially Than | E7: 13209277 | F7: Indonesia | H7: 1 | J7: 1 | K7: JEWELRY | L7: 358349 | M7: CL859268 | N7: 7EA7AP | O7: CL B01 ROCK LONG YG-24.9grs 76PAVE-0.38ct PENDANT | P7: 1 | Q7: 235200000 | R7: =(Q7-S7)/Q7*100 -> 0 | S7: =Q7 -> 235200000 | T7: CBPI 11327 | AA7: =V7*1.7% -> 0 | AB7: =(S7/1.11) -> 2.1189189e+08 | AC7: =(S7/1.11) -> 2.1189189e+08 | AD7: DP | AE7: DP | AF7: DP | AI7: 12000000 | AJ7: SMI | AK7: 807567 | AL7: 80 : 20 (MM & HS)
R8: =(Q8-S8)/Q8*100 -> #DIV/0! | AA8: =V8*1.7% -> 0 | AB8: =(S8/1.11) -> 0 | AK8: 807617
R9: =(Q9-S9)/Q9*100 -> #DIV/0! | AA9: =V9*1.5% -> 0 | AB9: =(S9/1.11) -> 0 | AK9: 806856
R10: =(Q10-S10)/Q10*100 -> #DIV/0! | AA10: =V10*1.3% -> 0 | AB10: =(S10/1.11) -> 0 | AK10: 806422
R11: =(Q11-S11)/Q11*100 -> #DIV/0! | AA11: =V11*1.5% -> 0 | AB11: =(S11/1.11) -> 0
R12: =(Q12-S12)/Q12*100 -> #DIV/0! | AA12: =V12*1.5% -> 0 | AB12: =(S12/1.11) -> 0
R13: =(Q13-S13)/Q13*100 -> #DIV/0! | AA13: =V13*1.5% -> 0 | AB13: =(S13/1.11) -> 0
R14: =(Q14-S14)/Q14*100 -> #DIV/0! | AA14: =V14*0.15% -> 0 | AB14: =(S14/1.11) -> 0
R15: =(Q15-S15)/Q15*100 -> #DIV/0! | AA15: =V15*1.5% -> 0 | AB15: =(S15/1.11) -> 0
R16: =(Q16-S16)/Q16*100 -> #DIV/0! | AA16: =V16*1.5% -> 0 | AB16: =(S16/1.11) -> 0
R17: =(Q17-S17)/Q17*100 -> #DIV/0! | AA17: =V17*1.5% -> 0 | AB17: =(S17/1.11) -> 0
R18: =(Q18-S18)/Q18*100 -> #DIV/0! | AA18: =V18*1.5% -> 0 | AB18: =(S18/1.11) -> 0
R19: =(Q19-S19)/Q19*100 -> #DIV/0! | AA19: =V19*1.5% -> 0 | AB19: =(S19/1.11) -> 0
R20: =(Q20-S20)/Q20*100 -> #DIV/0! | AA20: =V20*1.5% -> 0 | AB20: =(S20/1.11) -> 0
R21: =(Q21-S21)/Q21*100 -> #DIV/0! | AA21: =V21*1.5% -> 0 | AB21: =(S21/1.11) -> 0
R22: =(Q22-S22)/Q22*100 -> #DIV/0! | AA22: =V22*1.5% -> 0 | AB22: =(S22/1.11) -> 0
R23: =(Q23-S23)/Q23*100 -> #DIV/0! | AA23: =V23*1.5% -> 0 | AB23: =(S23/1.11) -> 0
R24: =(Q24-S24)/Q24*100 -> #DIV/0! | AA24: =V24*1.5% -> 0 | AB24: =(S24/1.11) -> 0
R25: =(Q25-S25)/Q25*100 -> #DIV/0! | AA25: =V25*1.5% -> 0 | AB25: =(S25/1.11) -> 0
R26: =(Q26-S26)/Q26*100 -> #DIV/0! | AA26: =V26*1.5% -> 0 | AB26: =(S26/1.11) -> 0
... R43: =(Q43-S43)/Q43*100 -> #DIV/0! | AA43: =V43*1.5% -> 0 | AB43: =(S43/1.11) -> 0
D44: TOTAL | G44: =SUM(G7:G43) -> 0 | H44: =SUM(H7:H43) -> 1 | I44: =SUM(I7:I43) -> 0 | J44: =SUM(J7:J43) -> 1 | P44: =SUM(P7:P43) -> 1 | Q44: =SUM(Q7:Q43) -> 235200000 | S44: =SUM(S7:S43) -> 235200000 | U44: =SUM(U7:U43) -> 0 | V44: =SUM(V7:V43) -> 0 | AA44: =SUM(AA7:AA43) -> 0 | AB44: =SUM(AB7:AB43) -> 2.1189189e+08 | AC44: =SUM(AC7:AC43) -> 2.1189189e+08
AB46: Store:
AB47: SMI: | AC47: =AB44 -> 2.1189189e+08
AB48: TOTAL: | AC48: =AC46+AC47 -> 2.1189189e+08
AB50: kurang sales: -
AC52: TOTAL ACHIEVEMENT
AC53: =AC48/AC59*100% -> 0.015695696
AB57: Target Store:: | AC57: =DS!AD322 -> 13500000000
AB58: Target SMI: | AC58: 0
AB59: Total Target: | AC59: =AC57 -> 13500000000

Sheet HO
A1: =DS!A1 -> BVLGARI – Plaza Indonesia
A2: Head Office Transaction Report
A3: Periode | B3: =DS!B3 -> 46266
A5: Date | B5: AB No. | C5: Sales Invoice No | D5: Customer Name | E5: Cosmo CRM ID | F5: Nationality | G5: New | H5: Old | I5: W | J5: F | K5: Category | L5: SAP Code | M5: Item Name | N5: Serial No | O5: Description | P5: Qty | Q5: Gross Sales | R5: Disc. % | S5: Net Sales | T5: Payment | AB5: Achievement | AC5: Daily Total Achievement | AD5: CA | AE5: After Sales Support | AF5: DWA | AG5: Other Remarks
T6: Deposit CB No | U6: Rp. | V6: Card | W6: OR No. | X6: Bank Transfer To | Y6: EDC | Z6: Card Type | AA6: Card Commission
R7: =(Q7-S7)/Q7*100 -> #DIV/0! | AB7: =(S7/1.11) -> 0
R8: =(Q8-S8)/Q8*100 -> #DIV/0! | AB8: =(S8/1.11) -> 0
R9: =(Q9-S9)/Q9*100 -> #DIV/0! | AB9: =(S9/1.11) -> 0
R10: =(Q10-S10)/Q10*100 -> #DIV/0! | AB10: =(S10/1.11) -> 0
R11: =(Q11-S11)/Q11*100 -> #DIV/0! | AB11: =(S11/1.11) -> 0
R12: =(Q12-S12)/Q12*100 -> #DIV/0! | AB12: =(S12/1.11) -> 0
R13: =(Q13-S13)/Q13*100 -> #DIV/0! | AB13: 0
R14: =(Q14-S14)/Q14*100 -> #DIV/0! | AB14: =(S14/1.11) -> 0
R15: =(Q15-S15)/Q15*100 -> #DIV/0! | AB15: =(S15/1.11) -> 0
R16: =(Q16-S16)/Q16*100 -> #DIV/0! | AB16: =(S16/1.11) -> 0
R17: =(Q17-S17)/Q17*100 -> #DIV/0! | AB17: =(S17/1.11) -> 0
R18: =(Q18-S18)/Q18*100 -> #DIV/0! | AB18: =(S18/1.11) -> 0
R19: =(Q19-S19)/Q19*100 -> #DIV/0! | AB19: =(S19/1.11) -> 0
R20: =(Q20-S20)/Q20*100 -> #DIV/0! | AB20: =(S20/1.11) -> 0
R21: =(Q21-S21)/Q21*100 -> #DIV/0! | AB21: =(S21/1.11) -> 0
R22: =(Q22-S22)/Q22*100 -> #DIV/0! | AB22: =(S22/1.11) -> 0
R23: =(Q23-S23)/Q23*100 -> #DIV/0! | AB23: =(S23/1.11) -> 0
R24: =(Q24-S24)/Q24*100 -> #DIV/0! | AB24: =(S24/1.11) -> 0
R25: =(Q25-S25)/Q25*100 -> #DIV/0! | AB25: =(S25/1.11) -> 0
... R32: =(Q32-S32)/Q32*100 -> #DIV/0! | AB32: =(S32/1.11) -> 0
D33: TOTAL | G33: =SUM(G7:G32) -> 0 | H33: =SUM(H7:H32) -> 0 | I33: =SUM(I7:I32) -> 0 | J33: =SUM(J7:J32) -> 0 | P33: =SUM(P7:P32) -> 0 | Q33: =SUM(Q7:Q32) -> 0 | S33: =SUM(S7:S32) -> 0 | U33: =SUM(U7:U32) -> 0 | V33: =SUM(V7:V32) -> 0 | AA33: =SUM(AA7:AA32) -> 0 | AB33: =SUM(AB7:AB32) -> 0 | AC33: =SUM(AC7:AC32) -> 0
AB35: Store:
AB36: SMI: | AC36: =SMI!AB44 -> 2.1189189e+08
AB37: TOTAL: | AC37: =AC35+AC36 -> 2.1189189e+08
AB39: kurang sales: -
AC41: TOTAL ACHIEVEMENT
AC42: =AC37/AC48*100% -> 0.015695696
AB46: Target Store:: | AC46: =DS!AD322 -> 13500000000
AB47: Target SMI: | AC47: 0
AB48: Total Target: | AC48: =AC46 -> 13500000000

Sheet MARKOM
A1: =DS!A1 -> BVLGARI – Plaza Indonesia
A2: Markom Transaction Report
A3: Periode | B3: =DS!B3 -> 46266 | C3: Markom tidak di hitung traffic, tidak ada achv individual, store, hanya ada komisi jika ada voucher nya
A5: Date | B5: CB No. | C5: Issue Receipt No. | D5: Customer Name | E5: Cosmo CRM ID | F5: Nationality | G5: New | H5: Old | I5: W | J5: F | K5: Category | L5: SAP Code | M5: Item Name | N5: Serial No | O5: Description | P5: Qty | Q5: Gross Sales | R5: Disc. % | S5: Net Sales | T5: Payment | AC5: Achievement | AD5: Daily Total Achievement | AE5: Served By | AF5: CA | AG5: Entitle | AH5: After Sales Support | AI5: DWA | AJ5: Spot Incentive | AK5: Other Remarks
T6: Deposit CB No | U6: Rp. | V6: Card | W6: GV No. | X6: Tanda Terima | Y6: Bank Transfer To | Z6: EDC | AA6: Card Type | AB6: Card Commission
R7: =(Q7-S7)/Q7*100 -> #DIV/0! | AB7: =V7*1.5% -> 0 | AC7: =(S7/1.11) -> 0
R8: =(Q8-S8)/Q8*100 -> #DIV/0! | AB8: =V8*1.5% -> 0 | AC8: =(S8/1.11) -> 0
R9: =(Q9-S9)/Q9*100 -> #DIV/0! | AB9: =V9*1.5% -> 0 | AC9: =(S9/1.11) -> 0
R10: =(Q10-S10)/Q10*100 -> #DIV/0! | AB10: =V10*1.3% -> 0 | AC10: =(S10/1.11) -> 0
R11: =(Q11-S11)/Q11*100 -> #DIV/0! | AB11: =V11*1.5% -> 0 | AC11: =(S11/1.11) -> 0
R12: =(Q12-S12)/Q12*100 -> #DIV/0! | AB12: =V12*1.5% -> 0 | AC12: =(S12/1.11) -> 0
R13: =(Q13-S13)/Q13*100 -> #DIV/0! | AB13: =V13*1.5% -> 0 | AC13: =(S13/1.11) -> 0
R14: =(Q14-S14)/Q14*100 -> #DIV/0! | AB14: =V14*1.5% -> 0 | AC14: =(S14/1.11) -> 0
R15: =(Q15-S15)/Q15*100 -> #DIV/0! | AB15: =V15*1.5% -> 0 | AC15: =(S15/1.11) -> 0
R16: =(Q16-S16)/Q16*100 -> #DIV/0! | AB16: =V16*1.5% -> 0 | AC16: =(S16/1.11) -> 0
R17: =(Q17-S17)/Q17*100 -> #DIV/0! | AB17: =V17*1.5% -> 0 | AC17: =(S17/1.11) -> 0
R18: =(Q18-S18)/Q18*100 -> #DIV/0! | AB18: =V18*1.5% -> 0 | AC18: =(S18/1.11) -> 0
R19: =(Q19-S19)/Q19*100 -> #DIV/0! | AB19: =V19*1.5% -> 0 | AC19: =(S19/1.11) -> 0
R20: =(Q20-S20)/Q20*100 -> #DIV/0! | AB20: =V20*1.5% -> 0 | AC20: =(S20/1.11) -> 0
R21: =(Q21-S21)/Q21*100 -> #DIV/0! | AB21: =V21*1.5% -> 0 | AC21: =(S21/1.11) -> 0
D22: TOTAL | G22: =SUM(G7:G21) -> 0 | H22: =SUM(H7:H21) -> 0 | I22: =SUM(I7:I21) -> 0 | J22: =SUM(J7:J21) -> 0 | P22: =SUM(P7:P21) -> 0 | Q22: =SUM(Q7:Q21) -> 0 | S22: =SUM(S7:S21) -> 0 | U22: =SUM(U7:U21) -> 0 | V22: =SUM(V7:V21) -> 0 | AB22: =SUM(AB7:AB21) -> 0 | AC22: =SUM(AC7:AC21) -> 0 | AD22: =SUM(AD7:AD21) -> 0 | AJ22: TOTAL
AC24: Store:
AC25: SMI: | AD25: =SMI!AB44 -> 2.1189189e+08
AC26: TOTAL: | AD26: =AD24+AD25 -> 2.1189189e+08
AC28: kurang sales: -
AD30: TOTAL ACHIEVEMENT
AD31: =AD26/AD37*100% -> 0.015695696
AC35: Target Store:: | AD35: =DS!AD322 -> 13500000000
AC36: Target SMI: | AD36: 0
AC37: Total Target: | AD37: =AD35 -> 13500000000

Sheet IN AND OUT
A1: =DS!A1 -> BVLGARI – Plaza Indonesia
A2: Daily Sales Transaction IN AND OUT Report
A3: Periode | B3: =DS!B3 -> 46266
A6: IN | AG6: HARUS DI ISI
A7: Date | B7: CB No. | C7: Sales Invoice No | D7: Customer Name | E7: Cosmo CRM ID | F7: Nationality | G7: New | H7: Old | I7: W | J7: F | K7: Category | L7: SAP Code | M7: Item Name | N7: Serial No | O7: Description | P7: Qty | Q7: Gross Sales | R7: Disc. % | S7: Net Sales | T7: Discount Given Reason | U7: Payment | AC7: Achievement | AD7: Daily Total Achievement | AE7: Served By | AF7: CA | AG7: Entitle | AH7: Other Remarks
U8: Deposit CB No | V8: Rp. | W8: Card | X8: OR No. | Y8: Bank Transfer To | Z8: EDC | AA8: Card Type | AB8: Card Commission
R9: =(Q9-S9)/Q9*100 -> #DIV/0! | AB9: =W9*0.15% -> 0 | AC9: =(S9/1.11) -> 0
R10: =(Q10-S10)/Q10*100 -> #DIV/0! | AB10: =W10*1.5% -> 0 | AC10: =(S10/1.11) -> 0
R11: =(Q11-S11)/Q11*100 -> #DIV/0! | AB11: =W11*1.5% -> 0 | AC11: =(S11/1.11) -> 0
R12: =(Q12-S12)/Q12*100 -> #DIV/0! | AB12: =W12*1.3% -> 0 | AC12: =(S12/1.11) -> 0
R13: =(Q13-S13)/Q13*100 -> #DIV/0! | AB13: =W13*1.3% -> 0 | AC13: =(S13/1.11) -> 0
R14: =(Q14-S14)/Q14*100 -> #DIV/0! | AB14: =W14*1.3% -> 0 | AC14: =(S14/1.11) -> 0
R15: =(Q15-S15)/Q15*100 -> #DIV/0! | AB15: =W15*1.3% -> 0 | AC15: =(S15/1.11) -> 0
R16: =(Q16-S16)/Q16*100 -> #DIV/0! | AB16: =W16*1.3% -> 0 | AC16: =(S16/1.11) -> 0
R17: =(Q17-S17)/Q17*100 -> #DIV/0! | AB17: =W17*1.3% -> 0 | AC17: =(S17/1.11) -> 0
R18: =(Q18-S18)/Q18*100 -> #DIV/0! | AB18: =W18*1.3% -> 0 | AC18: =(S18/1.11) -> 0
R19: =(Q19-S19)/Q19*100 -> #DIV/0! | AB19: =W19*1.3% -> 0 | AC19: =(S19/1.11) -> 0
R20: =(Q20-S20)/Q20*100 -> #DIV/0! | AB20: =W20*1.3% -> 0 | AC20: =(S20/1.11) -> 0
R21: =(Q21-S21)/Q21*100 -> #DIV/0! | AB21: =W21*1.3% -> 0 | AC21: =(S21/1.11) -> 0
R22: =(Q22-S22)/Q22*100 -> #DIV/0! | AB22: =W22*1.3% -> 0 | AC22: =(S22/1.11) -> 0
R23: =(Q23-S23)/Q23*100 -> #DIV/0! | AB23: =W23*1.9% -> 0 | AC23: =(S23/1.11) -> 0
R24: =(Q24-S24)/Q24*100 -> #DIV/0! | AB24: =W24*1.3% -> 0 | AC24: =(S24/1.11) -> 0
R25: =(Q25-S25)/Q25*100 -> #DIV/0! | AB25: =W25*1.3% -> 0 | AC25: =(S25/1.11) -> 0
R26: =(Q26-S26)/Q26*100 -> #DIV/0! | AB26: =W26*1.9% -> 0 | AC26: =(S26/1.11) -> 0
R27: =(Q27-S27)/Q27*100 -> #DIV/0! | AB27: =W27*1.3% -> 0 | AC27: =(S27/1.11) -> 0
D28: TOTAL | G28: =SUM(G9:G27) -> 0 | H28: =SUM(H9:H27) -> 0 | I28: =SUM(I9:I27) -> 0 | J28: =SUM(J9:J27) -> 0 | P28: =SUM(P9:P27) -> 0 | Q28: =SUM(Q9:Q27) -> 0 | S28: =SUM(S9:S27) -> 0 | V28: =SUM(V9:V27) -> 0 | W28: =SUM(W9:W27) -> 0 | AB28: =SUM(AB9:AB27) -> 0 | AC28: =SUM(AC9:AC27) -> 0 | AD28: =SUM(AD9:AD27) -> 0
A30: OUT
A31: Date | B31: CB No. | C31: Sales Invoice No | D31: Customer Name | E31: Cosmo CRM ID | F31: Nationality | G31: New | H31: Old | I31: W | J31: F | K31: Category | L31: SAP Code | M31: Item Name | N31: Serial No | O31: Description | P31: Qty | Q31: Gross Sales | R31: Disc. % | S31: Net Sales | T31: Discount Given Reason | U31: Payment | AC31: Achievement | AD31: Daily Total Achievement | AE31: Served By | AF31: CA | AG31: Entitle | AH31: DWA | AI31: Other Remarks
U32: Deposit CB No | V32: Rp. | W32: Card | X32: OR No. | Y32: Bank Transfer To | Z32: EDC | AA32: Card Type | AB32: Card Commission
R33: =(Q33-S33)/Q33*100 -> #DIV/0! | AB33: =W33*0.15% -> 0 | AC33: =(S33/1.11) -> 0
R34: =(Q34-S34)/Q34*100 -> #DIV/0! | AB34: =W34*1.4% -> 0 | AC34: =(S34/1.11) -> 0
R35: =(Q35-S35)/Q35*100 -> #DIV/0! | AB35: =W35*1.25% -> 0 | AC35: =(S35/1.11) -> 0
R36: =(Q36-S36)/Q36*100 -> #DIV/0! | AB36: =W36*1.5% -> 0 | AC36: =(S36/1.11) -> 0
R37: =(Q37-S37)/Q37*100 -> #DIV/0! | AB37: =W37*1.5% -> 0 | AC37: =(S37/1.11) -> 0
R38: =(Q38-S38)/Q38*100 -> #DIV/0! | AB38: =W38*1.3% -> 0 | AC38: =(S38/1.11) -> 0
R39: =(Q39-S39)/Q39*100 -> #DIV/0! | AB39: =W39*1.5% -> 0 | AC39: =(S39/1.11) -> 0
R40: =(Q40-S40)/Q40*100 -> #DIV/0! | AB40: =W40*1.5% -> 0 | AC40: =(S40/1.11) -> 0
R41: =(Q41-S41)/Q41*100 -> #DIV/0! | AB41: =W41*1.5% -> 0 | AC41: =(S41/1.11) -> 0
R42: =(Q42-S42)/Q42*100 -> #DIV/0! | AB42: =W42*1.5% -> 0 | AC42: =(S42/1.11) -> 0
R43: =(Q43-S43)/Q43*100 -> #DIV/0! | AB43: =W43*1.5% -> 0 | AC43: =(S43/1.11) -> 0
R44: =(Q44-S44)/Q44*100 -> #DIV/0! | AB44: =W44*1.5% -> 0 | AC44: =(S44/1.11) -> 0
R45: =(Q45-S45)/Q45*100 -> #DIV/0! | AB45: =W45*1.5% -> 0 | AC45: =(S45/1.11) -> 0
D46: TOTAL | G46: =SUM(G33:G45) -> 0 | H46: =SUM(H33:H45) -> 0 | I46: =SUM(I33:I45) -> 0 | J46: =SUM(J33:J45) -> 0 | P46: =SUM(P33:P45) -> 0 | Q46: =SUM(Q33:Q45) -> 0 | S46: =SUM(S33:S45) -> 0 | V46: =SUM(V40:V45) -> 0 | W46: =SUM(W40:W45) -> 0 | AB46: =SUM(AB33:AB45) -> 0 | AC46: =SUM(AC33:AC45) -> 0 | AD46: =SUM(AD33:AD45) -> 0
C49: ACTUAL | D49: =DS!AD325 -> 9.5825631e+09
C50: STORE ACHIEVEMENT : | D50: =D49-AD38+AD28 -> 9.5825631e+09
C51: TARGET : | D51: =DS!AD322 -> 13500000000
C52: % | D52: =(D50/D51)*100% -> 0.70981949

Sheet TRAFFIC & COMMISSION REPORT
A1: BVLGARI – PLAZA INDONESIA
A2: Traffic & Individual Commission Report
A3: =DS!B3 -> 46266
A5: RUMUS: | E5: Watches Specialist khusus penjualan Jam tangan
A6: DISC | B6: Peritem | C6: SHJ / LLG / OCTO | E6: DISC | F6: Others 1-2pc | G6: Others >3pc | H6: OCTO 1-2pc | I6: OCTO >3pc | K6: JEWEL 25 JUTA
A7: 0 | B7: 0.03 | C7: 0.036 | E7: 0 | F7: 0.033 | G7: 0.036 | H7: 0.0396 | I7: 0.036 | K7: WATCH 50 JUTA
A8: 1-10% | B8: 0.012 | C8: 0.024 | E8: 1-10% | F8: 0.0132 | G8: 0.0144 | H8: 0.022 | I8: 0.024 | K8: ACC 6 JUTA
A9: 11-15% | B9: 0.006 | C9: 0.012 | E9: 11-15% | F9: 0.0066 | G9: 0.0072 | H9: 0.011 | I9: 0.012
A10: >16% | B10: 0 | C10: 0.005 | E10: >16% | F10: 0 | G10: 0 | H10: 0.0055 | I10: 0.006
A12: Store Achievment | B12: Manager | C12: SPV
W14: Taret individual di bagi jumlah CA
BB16: 0.035 | BC16: 0.03 | BD16: 0.025 | BE16: 0.02 | BF16: 0.0175 | BG16: 0.01 | BH16: 0.007 | BI16: 0.005 | BJ16: 0.0035
H18: 3 | I18: 2.5 | J18: 2 | K18: 1 | L18: Target Butik | S18: 3 | T18: 2.5 | U18: 2 | V18: 1 | AF18: 3 | AG18: 2.5 | AH18: 2 | AI18: 1 | AQ18: 3 | AR18: 2.5 | AS18: 2 | AT18: 1 | BQ18: 3 | BR18: 2.5 | BS18: 2 | BT18: 1 | CB18: 3 | CC18: 2.5 | CD18: 2 | CE18: 1 | CM18: 3 | CN18: 2.5 | CO18: 2 | CP18: 1 | CX18: 3 | CY18: 2.5 | CZ18: 2 | DA18: 1 | DI18: 3 | DJ18: 2.5 | DK18: 2 | DL18: 1 | DT18: 3 | DU18: 2.5 | DV18: 2 | DW18: 1 | EE18: 3 | EF18: 2.5 | EG18: 2 | EH18: 1 | EP18: 3 | EQ18: 2.5 | ER18: 2 | ES18: 1 | FA18: 3 | FB18: 2.5 | FC18: 2 | FD18: 1 | FL18: 3 | FM18: 2.5 | FN18: 2 | FO18: 1
A19: BULAN | B19: MONIQ | L19: =DS!AD322 -> 13500000000 | M19: HERDY | W19: 1050000000 | X19: AJENG | AD19: Watches Specialist | AJ19: 1556250000 | AK19: SYANDY | AU19: =AJ19 -> 1556250000 | AV19: SISKA (VIP CA) | BJ19: =AJ19 -> 1556250000 | BK19: DIAN | BU19: =AJ19 -> 1556250000 | BV19: IRMA | CF19: =AJ19 -> 1556250000 | CG19: JOJO | CQ19: =AJ19 -> 1556250000 | CR19: ARI | DB19: =AJ19 -> 1556250000 | DC19: ALVIN | DM19: =AJ19 -> 1556250000 | DN19: ARIF PS | FQ19: TOTAL
B20: DAILY TRAFFIC | C20: TRAFFIC W/DATA | D20: QTY | E20: GROSS | F20: NETT | G20: After Tax & CC | H20: 0.036 | I20: 0.03 | J20: 0.024 | K20: 0.012 | L20: 0.006 | M20: DAILY TRAFFIC | N20: TRAFFIC W/DATA | O20: QTY | P20: GROSS | Q20: NETT | R20: After Tax & CC | S20: 0.036 | T20: 0.03 | U20: 0.024 | V20: 0.012 | W20: 0.006 | X20: DAILY TRAFFIC | Y20: TRAFFIC W/DATA | Z20: QTY | AA20: GROSS | AB20: NETT | AC20: After Tax & CC | AD20: 1-2pc | AE20: >3pc | AF20: 0.036 | AG20: 0.03 | AH20: 0.024 | AI20: 0.012 | AJ20: 0.006 | AK20: DAILY TRAFFIC | AL20: TRAFFIC W/DATA | AM20: QTY | AN20: GROSS | AO20: NETT | AP20: After Tax & CC | AQ20: 0.036 | AR20: 0.03 | AS20: 0.024 | AT20: 0.012 | AU20: 0.006 | AV20: DAILY TRAFFIC | AW20: TRAFFIC W/DATA | AX20: QTY | AY20: GROSS | AZ20: NETT | BA20: After Tax & CC | BB20: 0.042 | BC20: 0.036 | BD20: 0.03 | BE20: 0.024 | BF20: 0.021 | BG20: 0.012 | BH20: 0.0083 | BI20: 0.006 | BJ20: 0.0042 | BK20: DAILY TRAFFIC | BL20: TRAFFIC W/DATA | BM20: QTY | BN20: GROSS | BO20: NETT | BP20: After Tax & CC | BQ20: 0.036 | BR20: 0.03 | BS20: 0.024 | BT20: 0.012 | BU20: 0.006 | BV20: DAILY TRAFFIC | BW20: TRAFFIC W/DATA | BX20: QTY | BY20: GROSS | BZ20: NETT | CA20: After Tax & CC | CB20: 0.036 | CC20: 0.03 | CD20: 0.024 | CE20: 0.012 | CF20: 0.006 | CG20: DAILY TRAFFIC | CH20: TRAFFIC W/DATA | CI20: QTY | CJ20: GROSS | CK20: NETT | CL20: After Tax & CC | CM20: 0.036 | CN20: 0.03 | CO20: 0.024 | CP20: 0.012 | CQ20: 0.006 | CR20: DAILY TRAFFIC | CS20: TRAFFIC W/DATA | CT20: QTY | CU20: GROSS | CV20: NETT | CW20: After Tax & CC | CX20: 0.036 | CY20: 0.03 | CZ20: 0.024 | DA20: 0.012 | DB20: 0.006 | DC20: DAILY TRAFFIC | DD20: TRAFFIC W/DATA | DE20: QTY | DF20: GROSS | DG20: NETT | DH20: After Tax & CC | DI20: 0.036 | DJ20: 0.03 | DK20: 0.024 | DL20: 0.012 | DM20: 0.006 | DN20: DAILY TRAFFIC | DO20: TRAFFIC W/DATA | DP20: QTY | DQ20: GROSS | DR20: NETT | DS20: After Tax & CC | DT20: 0.036 | DU20: 0.03 | DV20: 0.024 | DW20: 0.012 | DX20: 0.006 | DY20: DAILY TRAFFIC | DZ20: TRAFFIC W/DATA | EA20: QTY | EB20: GROSS | EC20: NETT | ED20: After Tax & CC | EE20: 0.036 | EF20: 0.03 | EG20: 0.024 | EH20: 0.012 | EI20: 0.006 | EJ20: DAILY TRAFFIC | EK20: TRAFFIC W/DATA | EL20: QTY | EM20: GROSS | EN20: NETT | EO20: After Tax & CC | EP20: 0.036 | EQ20: 0.03 | ER20: 0.024 | ES20: 0.012 | ET20: 0.006 | EU20: DAILY TRAFFIC | EV20: TRAFFIC W/DATA | EW20: QTY | EX20: GROSS | EY20: NETT | EZ20: After Tax & CC | FA20: 0.036 | FB20: 0.03 | FC20: 0.024 | FD20: 0.012 | FE20: 0.006 | FF20: DAILY TRAFFIC | FG20: TRAFFIC W/DATA | FH20: QTY | FI20: GROSS | FJ20: NETT | FK20: After Tax & CC | FL20: 0.036 | FM20: 0.03 | FN20: 0.024 | FO20: 0.012 | FP20: 0.006 | FQ20: DAILY TRAFFIC | FR20: TRAFFIC W/DATA
A21: =DS!B3 -> 46266 | FS21: QTY | FT21: GROSS | FU21: NETT | FV21: AFTER TAX&CC | FW21: Achievement
A22: 1 | X22: 1 | AK22: 1 | CG22: 1 | CH22: 1 | FQ22: =SUM(FF22+EJ22+DY22+DN22+DC22+CR22+CG22+BV22+BK22+AV22+AK22+X22+M22+B22) -> 3 | FR22: =C22+N22+Y22+AL22+AW22+BL22+BW22+CH22+CS22+DD22+DO22+DZ22+EK22+FG22 -> 1 | FS22: =SUM(FH22+EL22+EA22+DP22+DE22+CT22+CI22+BX22+BM22+AX22+AM22+Z22+O22+D22) -> 0 | FT22: =SUM(FI22+EM22+EB22+DQ22+DF22+CU22+CJ22+BY22+BN22+AY22+AN22+AA22+P22+E22) -> 0 | FU22: =SUM(FJ22+EN22+EC22+DR22+DG22+CV22+CK22+BZ22+BO22+AZ22+AO22+AB22+Q22+F22) -> 0 | FV22: =SUM(FK22+EO22+ED22+DS22+DH22+CW22+CL22+CA22+BP22+BA22+AP22+AC22+R22+G22) -> 0 | FW22: =FV22 -> 0
A23: 2 | M23: 1 | N23: 1 | X23: 1 | Y23: 1 | Z23: 1 | AA23: =DS!Q8 -> 174500000 | AB23: =DS!S8 -> 174500000 | AC23: =DS!AC8 -> 1.5720721e+08 | AG23: =DS!AC8 -> 1.5720721e+08 | AV23: 1 | AW23: 1 | BK23: 1 | BL23: 1 | CG23: 1 | CH23: 1 | CR23: 1 | CS23: 1 | FQ23: =SUM(FF23+EJ23+DY23+DN23+DC23+CR23+CG23+BV23+BK23+AV23+AK23+X23+M23+B23) -> 6 | FR23: =C23+N23+Y23+AL23+AW23+BL23+BW23+CH23+CS23+DD23+DO23+DZ23+EK23+FG23 -> 6 | FS23: =SUM(FH23+EL23+EA23+DP23+DE23+CT23+CI23+BX23+BM23+AX23+AM23+Z23+O23+D23) -> 1 | FT23: =SUM(FI23+EM23+EB23+DQ23+DF23+CU23+CJ23+BY23+BN23+AY23+AN23+AA23+P23+E23) -> 174500000 | FU23: =SUM(FJ23+EN23+EC23+DR23+DG23+CV23+CK23+BZ23+BO23+AZ23+AO23+AB23+Q23+F23) -> 174500000 | FV23: =SUM(FK23+EO23+ED23+DS23+DH23+CW23+CL23+CA23+BP23+BA23+AP23+AC23+R23+G23) -> 1.5720721e+08 | FW23: =FV23 -> 1.5720721e+08
A24: 3 | M24: 1 | N24: 1 | O24: 1 | P24: =DS!Q26 -> 273000000 | Q24: =DS!S26 -> 273000000 | R24: =DS!AC26 -> 2.4594595e+08 | T24: =DS!AC26 -> 2.4594595e+08 | X24: 1 | Y24: 1 | AK24: 1 | AL24: 1 | AM24: 1 | AN24: =DS!Q12 -> 107900000 | AO24: =DS!S12 -> 107900000 | AP24: =DS!AC12 -> 97207207 | AR24: =DS!AC12 -> 97207207 | AV24: 1 | AW24: 1 | AX24: 4 | AY24: =DS!Q15+DS!Q16+DS!Q17+DS!Q18 -> 1004300000 | AZ24: =DS!S15+DS!S16+DS!S17+DS!S18 -> 1004300000 | BA24: =DS!AC15+DS!AC16+DS!AC17+DS!AC18 -> 9.0477477e+08 | BF24: =DS!AC15+DS!AC16+DS!AC17+DS!AC18 -> 9.0477477e+08 | BK24: 1 | BL24: 1 | BM24: 1 | BN24: =DS!Q22 -> 574000000 | BO24: =DS!S22 -> 574000000 | BP24: =DS!AC22 -> 5.1711712e+08 | BR24: =DS!AC22 -> 5.1711712e+08 | BV24: 1 | BW24: 1 | CG24: 1 | CH24: 1 | CR24: 2 | CS24: 1 | FQ24: =SUM(FF24+EJ24+DY24+DN24+DC24+CR24+CG24+BV24+BK24+AV24+AK24+X24+M24+B24) -> 9 | FR24: =C24+N24+Y24+AL24+AW24+BL24+BW24+CH24+CS24+DD24+DO24+DZ24+EK24+FG24 -> 8 | FS24: =SUM(FH24+EL24+EA24+DP24+DE24+CT24+CI24+BX24+BM24+AX24+AM24+Z24+O24+D24) -> 7 | FT24: =SUM(FI24+EM24+EB24+DQ24+DF24+CU24+CJ24+BY24+BN24+AY24+AN24+AA24+P24+E24) -> 1959200000 | FU24: =SUM(FJ24+EN24+EC24+DR24+DG24+CV24+CK24+BZ24+BO24+AZ24+AO24+AB24+Q24+F24) -> 1959200000 | FV24: =SUM(FK24+EO24+ED24+DS24+DH24+CW24+CL24+CA24+BP24+BA24+AP24+AC24+R24+G24) -> 1.765045e+09 | FW24: =FV24 -> 1.765045e+09
A25: 4 | X25: 3 | Y25: 3 | AK25: 1 | AL25: 1 | AM25: 2 | AN25: =DS!Q30+DS!Q31 -> 1656100000 | AO25: =DS!S30+DS!S31 -> 1490490000 | AP25: =DS!AC30+DS!AC31 -> 1.3427838e+09 | AT25: =DS!AC30+DS!AC31 -> 1.3427838e+09 | BK25: 4 | BL25: 4 | BM25: 1 | BN25: =SMI!Q7 -> 235200000 | BO25: =SMI!S7 -> 235200000 | BP25: =SMI!AB7 -> 2.1189189e+08 | CR25: 2 | CS25: 2 | FQ25: =SUM(FF25+EJ25+DY25+DN25+DC25+CR25+CG25+BV25+BK25+AV25+AK25+X25+M25+B25) -> 10 | FR25: =C25+N25+Y25+AL25+AW25+BL25+BW25+CH25+CS25+DD25+DO25+DZ25+EK25+FG25 -> 10 | FS25: =SUM(FH25+EL25+EA25+DP25+DE25+CT25+CI25+BX25+BM25+AX25+AM25+Z25+O25+D25) -> 3 | FT25: =SUM(FI25+EM25+EB25+DQ25+DF25+CU25+CJ25+BY25+BN25+AY25+AN25+AA25+P25+E25) -> 1891300000 | FU25: =SUM(FJ25+EN25+EC25+DR25+DG25+CV25+CK25+BZ25+BO25+AZ25+AO25+AB25+Q25+F25) -> 1725690000 | FV25: =SUM(FK25+EO25+ED25+DS25+DH25+CW25+CL25+CA25+BP25+BA25+AP25+AC25+R25+G25) -> 1.5546757e+09 | FW25: =FV25 -> 1.5546757e+09
A26: 5 | X26: 2 | Y26: 1 | AK26: 1 | AV26: 2 | AW26: 2 | AX26: 5 | AY26: =DS!Q40+DS!Q51+DS!Q52+DS!Q53+DS!Q54 -> 523700000 | AZ26: =DS!S40+DS!S51+DS!S52+DS!S53+DS!S54 -> 523700000 | BA26: =DS!AC40+DS!AC51+DS!AC52+DS!AC53+DS!AC54 -> 4.718018e+08 | BC26: =DS!AC40 -> 1.3720721e+08 | BF26: =DS!AC51+DS!AC52+DS!AC53+DS!AC54 -> 3.3459459e+08 | BV26: 3 | BW26: 2 | BX26: 2 | BY26: =DS!Q36+DS!Q37 -> 48820000 | BZ26: =DS!S36+DS!S37 -> 48820000 | CA26: =DS!AC36+DS!AC37 -> 43981982 | CC26: =DS!AC37 -> 42072072 | CG26: 2 | CH26: 2 | CI26: 2 | CJ26: =DS!Q45+DS!Q48 -> 150400000 | CK26: =DS!S45+DS!S48 -> 150400000 | CL26: =DS!AC45+DS!AC48 -> 1.354955e+08 | CN26: =DS!AC45+DS!AC48 -> 1.354955e+08 | DC26: 2 | DD26: 2 | FQ26: =FF26+EJ26+DY26+DN26+DC26+CR26+CG26+BV26+BK26+AV26+AK26+X26+M26+B26 -> 12 | FR26: =C26+N26+Y26+AL26+AW26+BL26+BW26+CH26+CS26+DD26+DO26+DZ26+EK26+FG26 -> 9 | FS26: =SUM(FH26+EL26+EA26+DP26+DE26+CT26+CI26+BX26+BM26+AX26+AM26+Z26+O26+D26) -> 9 | FT26: =SUM(FI26+EM26+EB26+DQ26+DF26+CU26+CJ26+BY26+BN26+AY26+AN26+AA26+P26+E26) -> 722920000 | FU26: =SUM(FJ26+EN26+EC26+DR26+DG26+CV26+CK26+BZ26+BO26+AZ26+AO26+AB26+Q26+F26) -> 722920000 | FV26: =SUM(FK26+EO26+ED26+DS26+DH26+CW26+CL26+CA26+BP26+BA26+AP26+AC26+R26+G26) -> 6.5127928e+08 | FW26: =FV26 -> 6.5127928e+08
A27: 6 | M27: 2 | N27: 2 | O27: 1 | P27: =DS!Q58 -> 371000000 | Q27: =DS!S58 -> 371000000 | R27: =DS!AC58 -> 3.3423423e+08 | T27: =DS!AC58 -> 3.3423423e+08 | AV27: 5 | AW27: 3 | AX27: 1 | AY27: =DS!Q64 -> 107900000 | AZ27: =DS!S64 -> 107900000 | BA27: =DS!AC64 -> 97207207 | BF27: =DS!AC64 -> 97207207 | BK27: 6 | BL27: 5 | BV27: 2 | BW27: 2 | BX27: 2 | BY27: =DS!Q60+DS!Q72 -> 230100000 | BZ27: =DS!S60+DS!S72 -> 230100000 | CA27: =DS!AC60+DS!AC72 -> 2.072973e+08 | CC27: =DS!AC60+DS!AC72 -> 2.072973e+08 | CG27: 2 | CH27: 2 | CI27: 1 | CJ27: =DS!Q68 -> 76100000 | CK27: =DS!S68 -> 76100000 | CL27: =DS!AC68 -> 68558559 | CN27: =DS!AC68 -> 68558559 | DC27: 4 | DD27: 4 | FQ27: =SUM(FF27+EJ27+DY27+DN27+DC27+CR27+CG27+BV27+BK27+AV27+AK27+X27+M27+B27) -> 21 | FR27: =C27+N27+Y27+AL27+AW27+BL27+BW27+CH27+CS27+DD27+DO27+DZ27+EK27+FG27 -> 18 | FS27: =SUM(FH27+EL27+EA27+DP27+DE27+CT27+CI27+BX27+BM27+AX27+AM27+Z27+O27+D27) -> 5 | FT27: =SUM(FI27+EM27+EB27+DQ27+DF27+CU27+CJ27+BY27+BN27+AY27+AN27+AA27+P27+E27) -> 785100000 | FU27: =SUM(FJ27+EN27+EC27+DR27+DG27+CV27+CK27+BZ27+BO27+AZ27+AO27+AB27+Q27+F27) -> 785100000 | FV27: =SUM(FK27+EO27+ED27+DS27+DH27+CW27+CL27+CA27+BP27+BA27+AP27+AC27+R27+G27) -> 7.072973e+08 | FW27: =FV27 -> 7.072973e+08
A28: 7 | X28: 1 | Y28: 1 | BK28: 2 | BL28: 2 | BM28: 1 | BN28: =DS!Q75 -> 75100000 | BO28: =DS!S75 -> 75100000 | BP28: =DS!AC75 -> 67657658 | BR28: =DS!AC75 -> 67657658 | DC28: 3 | DD28: 3 | DE28: 2 | DF28: =DS!Q78+DS!Q81 -> 172900000 | DG28: =DS!S78+DS!S81 -> 172900000 | DH28: =DS!AC78+DS!AC81 -> 1.5576577e+08 | DJ28: =DS!AC78+DS!AC81 -> 1.5576577e+08 | FQ28: =SUM(FF28+EJ28+DY28+DN28+DC28+CR28+CG28+BV28+BK28+AV28+AK28+X28+M28+B28) -> 6 | FR28: =C28+N28+Y28+AL28+AW28+BL28+BW28+CH28+CS28+DD28+DO28+DZ28+EK28+FG28 -> 6 | FS28: =SUM(FH28+EL28+EA28+DP28+DE28+CT28+CI28+BX28+BM28+AX28+AM28+Z28+O28+D28) -> 3 | FT28: =SUM(FI28+EM28+EB28+DQ28+DF28+CU28+CJ28+BY28+BN28+AY28+AN28+AA28+P28+E28) -> 248000000 | FU28: =SUM(FJ28+EN28+EC28+DR28+DG28+CV28+CK28+BZ28+BO28+AZ28+AO28+AB28+Q28+F28) -> 248000000 | FV28: =SUM(FK28+EO28+ED28+DS28+DH28+CW28+CL28+CA28+BP28+BA28+AP28+AC28+R28+G28) -> 2.2342342e+08 | FW28: =FV28 -> 2.2342342e+08
A29: 8 | X29: 1 | Y29: 1 | Z29: 1 | AA29: =DS!Q87 -> 67500000 | AB29: =DS!S87 -> 67500000 | AC29: =DS!AC87 -> 60810811 | AG29: =DS!AC87 -> 60810811 | AK29: 2 | AL29: 1 | BV29: 1 | BW29: 1 | CG29: 1 | CH29: 1 | CI29: 1 | CJ29: =DS!Q84 -> 813700000 | CK29: =DS!S84 -> 773015000 | CL29: =DS!AC84 -> 6.9640991e+08 | CP29: =DS!AC84 -> 6.9640991e+08 | CR29: 2 | CS29: 2 | FQ29: =SUM(FF29+EJ29+DY29+DN29+DC29+CR29+CG29+BV29+BK29+AV29+AK29+X29+M29+B29) -> 7 | FR29: =C29+N29+Y29+AL29+AW29+BL29+BW29+CH29+CS29+DD29+DO29+DZ29+EK29+FG29 -> 6 | FS29: =SUM(FH29+EL29+EA29+DP29+DE29+CT29+CI29+BX29+BM29+AX29+AM29+Z29+O29+D29) -> 2 | FT29: =SUM(FI29+EM29+EB29+DQ29+DF29+CU29+CJ29+BY29+BN29+AY29+AN29+AA29+P29+E29) -> 881200000 | FU29: =SUM(FJ29+EN29+EC29+DR29+DG29+CV29+CK29+BZ29+BO29+AZ29+AO29+AB29+Q29+F29) -> 840515000 | FV29: =SUM(FK29+EO29+ED29+DS29+DH29+CW29+CL29+CA29+BP29+BA29+AP29+AC29+R29+G29) -> 7.5722072e+08 | FW29: =FV29 -> 7.5722072e+08
A30: 9 | M30: 1 | X30: 1 | Y30: 1 | Z30: 1 | AA30: =DS!Q93 -> 121500000 | AB30: =DS!S93 -> 121500000 | AC30: =DS!AC93 -> 1.0945946e+08 | AG30: =DS!AC93 -> 1.0945946e+08 | AK30: 1 | AV30: 1 | BK30: 2 | BL30: 1 | BM30: 1 | BN30: =DS!Q96 -> 76100000 | BO30: =DS!S96 -> 76100000 | BP30: =DS!AC96 -> 68558559 | BR30: =DS!AC96 -> 68558559 | BV30: 1 | CG30: 2 | CH30: 2 | CI30: 1 | CJ30: =DS!Q90 -> 1601600000 | CK30: =DS!S90 -> 1435000000 | CL30: =DS!AC90 -> 1.2927928e+09 | CO30: =DS!AC90 -> 1.2927928e+09 | DC30: 2 | DD30: 1 | FQ30: =SUM(FF30+EJ30+DY30+DN30+DC30+CR30+CG30+BV30+BK30+AV30+AK30+X30+M30+B30) -> 11 | FR30: =C30+N30+Y30+AL30+AW30+BL30+BW30+CH30+CS30+DD30+DO30+DZ30+EK30+FG30 -> 5 | FS30: =SUM(FH30+EL30+EA30+DP30+DE30+CT30+CI30+BX30+BM30+AX30+AM30+Z30+O30+D30+EW30) -> 3 | FT30: =SUM(FI30+EM30+EB30+DQ30+DF30+CU30+CJ30+BY30+BN30+AY30+AN30+AA30+P30+E30+EX30) -> 1799200000 | FU30: =SUM(FJ30+EN30+EC30+DR30+DG30+CV30+CK30+BZ30+BO30+AZ30+AO30+AB30+Q30+F30+EY30) -> 1632600000 | FV30: =SUM(FK30+EO30+ED30+DS30+DH30+CW30+CL30+CA30+BP30+BA30+AP30+AC30+R30+G30+EZ30) -> 1.4708108e+09 | FW30: =FV30 -> 1.4708108e+09
A31: 10 | M31: 1 | AV31: 1 | AW31: 1 | AX31: 1 | AY31: =DS!Q99 -> 76100000 | AZ31: =DS!S99 -> 76100000 | BA31: =DS!AC99 -> 68558559 | BF31: =DS!AC99 -> 68558559 | BK31: 1 | BL31: 1 | BM31: 1 | BN31: =DS!Q102 -> 42400000 | BO31: =DS!S102 -> 42400000 | BP31: =DS!AC102 -> 38198198 | BR31: =DS!AC102 -> 38198198 | BV31: 1 | BW31: 1 | BX31: 1 | BY31: =DS!Q108 -> 85800000 | BZ31: =DS!S108 -> 85800000 | CA31: =DS!AC108 -> 77297297 | CC31: =DS!AC108 -> 77297297 | DC31: 3 | DD31: 3 | DE31: 2 | DF31: =DS!Q105+DS!Q106 -> 223900000 | DG31: =DS!S105+DS!S106 -> 223900000 | DH31: =DS!AC105+DS!AC106 -> 2.0171171e+08 | DJ31: =DS!AC105+DS!AC106 -> 2.0171171e+08 | FQ31: =SUM(FF31+EJ31+DY31+DN31+DC31+CR31+CG31+BV31+BK31+AV31+AK31+X31+M31+B31) -> 7 | FR31: =C31+N31+Y31+AL31+AW31+BL31+BW31+CH31+CS31+DD31+DO31+DZ31+EK31+FG31 -> 6 | FS31: =SUM(FH31+EL31+EA31+DP31+DE31+CT31+CI31+BX31+BM31+AX31+AM31+Z31+O31+D31) -> 5 | FT31: =SUM(FI31+EM31+EB31+DQ31+DF31+CU31+CJ31+BY31+BN31+AY31+AN31+AA31+P31+E31) -> 428200000 | FU31: =SUM(FJ31+EN31+EC31+DR31+DG31+CV31+CK31+BZ31+BO31+AZ31+AO31+AB31+Q31+F31) -> 428200000 | FV31: =SUM(FK31+EO31+ED31+DS31+DH31+CW31+CL31+CA31+BP31+BA31+AP31+AC31+R31+G31) -> 3.8576577e+08 | FW31: =FV31 -> 3.8576577e+08
A32: 11 | X32: 2 | Y32: 1 | Z32: 1 | AA32: =DS!Q115 -> 106000000 | AB32: =DS!S115 -> 106000000 | AC32: =DS!AC115 -> 95495495 | AG32: =DS!AC115 -> 95495495 | AK32: 1 | AL32: 1 | AV32: 2 | AW32: 1 | CG32: 1 | CH32: 1 | CI32: 1 | CJ32: =DS!Q119 -> 100300000 | CK32: =DS!S119 -> 100300000 | CL32: =DS!AC119 -> 90360360 | CN32: =DS!AC119 -> 90360360 | CR32: 1 | CS32: 1 | CT32: 1 | CU32: =DS!Q111 -> 77000000 | CV32: =DS!S111 -> 77000000 | CW32: =DS!AC111 -> 69369369 | CY32: =DS!AC111 -> 69369369 | FQ32: =SUM(FF32+EJ32+DY32+DN32+DC32+CR32+CG32+BV32+BK32+AV32+AK32+X32+M32+B32) -> 7 | FR32: =C32+N32+Y32+AL32+AW32+BL32+BW32+CH32+CS32+DD32+DO32+DZ32+EK32+FG32 -> 5 | FS32: =SUM(FH32+EL32+EA32+DP32+DE32+CT32+CI32+BX32+BM32+AX32+AM32+Z32+O32+D32) -> 3 | FT32: =SUM(FI32+EM32+EB32+DQ32+DF32+CU32+CJ32+BY32+BN32+AY32+AN32+AA32+P32+E32) -> 283300000 | FU32: =SUM(FJ32+EN32+EC32+DR32+DG32+CV32+CK32+BZ32+BO32+AZ32+AO32+AB32+Q32+F32) -> 283300000 | FV32: =SUM(FK32+EO32+ED32+DS32+DH32+CW32+CL32+CA32+BP32+BA32+AP32+AC32+R32+G32) -> 2.5522523e+08 | FW32: =FV32 -> 2.5522523e+08
A33: 12 | M33: 3 | N33: 3 | X33: 3 | Y33: 3 | Z33: 1 | AA33: =DS!Q130 -> 51700000 | AB33: =DS!S130 -> 51700000 | AC33: =DS!AC130 -> 46576577 | AG33: =DS!AC130 -> 46576577 | AK33: 2 | AL33: 2 | AV33: 1 | AW33: 1 | BK33: 2 | BL33: 2 | BV33: 2 | BW33: 1 | CG33: 3 | CH33: 3 | CI33: 2 | CJ33: =DS!Q125+DS!Q128 -> 79200000 | CK33: =DS!S125+DS!S128 -> 79200000 | CL33: =DS!AC125+DS!AC128 -> 71351351 | CN33: =DS!AC125+DS!AC128 -> 71351351 | DC33: 5 | DD33: 5 | FQ33: =SUM(FF33+EJ33+DY33+DN33+DC33+CR33+CG33+BV33+BK33+AV33+AK33+X33+M33+B33) -> 21 | FR33: =C33+N33+Y33+AL33+AW33+BL33+BW33+CH33+CS33+DD33+DO33+DZ33+EK33+FG33 -> 20 | FS33: =SUM(FH33+EL33+EA33+DP33+DE33+CT33+CI33+BX33+BM33+AX33+AM33+Z33+O33+D33) -> 3 | FT33: =SUM(FI33+EM33+EB33+DQ33+DF33+CU33+CJ33+BY33+BN33+AY33+AN33+AA33+P33+E33) -> 130900000 | FU33: =SUM(FJ33+EN33+EC33+DR33+DG33+CV33+CK33+BZ33+BO33+AZ33+AO33+AB33+Q33+F33) -> 130900000 | FV33: =SUM(FK33+EO33+ED33+DS33+DH33+CW33+CL33+CA33+BP33+BA33+AP33+AC33+R33+G33) -> 1.1792793e+08 | FW33: =FV33 -> 1.1792793e+08
A34: 13 | M34: 2 | N34: 2 | AV34: 3 | AW34: 1 | BV34: 5 | BW34: 4 | CG34: 2 | CH34: 2 | CR34: 4 | CS34: 2 | CT34: 1 | CU34: =DS!Q133 -> 3220000 | CV34: =DS!S133 -> 3220000 | CW34: =DS!AC133 -> 2900900.9 | DC34: 4 | DD34: 2 | DE34: 1 | DF34: =DS!Q135 -> 9800000 | DG34: =DS!S135 -> 9800000 | DH34: =DS!AC135 -> 8828828.8 | DJ34: =DS!AC135 -> 8828828.8 | FQ34: =SUM(FF34+EJ34+DY34+DN34+DC34+CR34+CG34+BV34+BK34+AV34+AK34+X34+M34+H35) -> 20 | FR34: =C34+N34+Y34+AL34+AW34+BL34+BW34+CH34+CS34+DD34+DO34+DZ34+EK34+FG34 -> 13 | FS34: =SUM(FH34+EL34+EA34+DP34+DE34+CT34+CI34+BX34+BM34+AX34+AM34+Z34+O34+I35) -> 2 | FT34: =SUM(FI34+EM34+EB34+DQ34+DF34+CU34+CJ34+BY34+BN34+AY34+AN34+AA34+P34+E34) -> 13020000 | FU34: =SUM(FJ34+EN34+EC34+DR34+DG34+CV34+CK34+BZ34+BO34+AZ34+AO34+AB34+Q34+F34) -> 13020000 | FV34: =SUM(FK34+EO34+ED34+DS34+DH34+CW34+CL34+CA34+BP34+BA34+AP34+AC34+R34+G34) -> 11729730 | FW34: =FV34 -> 11729730
A35: 14 | M35: 1 | X35: 1 | Y35: 1 | BV35: 1 | DC35: 1 | DD35: 1 | FQ35: =SUM(FF35+EJ35+DY35+DN35+DC35+CR35+CG35+BV35+BK35+AV35+AK35+X35+M35+B35) -> 4 | FR35: =C35+N35+Y35+AL35+AW35+BL35+BW35+CH35+CS35+DD35+DO35+DZ35+EK35+FG35 -> 2 | FS35: =SUM(FH35+EL35+EA35+DP35+DE35+CT35+CI35+BX35+BM35+AX35+AM35+Z35+O35+D35) -> 0 | FT35: =SUM(FI35+EM35+EB35+DQ35+DF35+CU35+CJ35+BY35+BN35+AY35+AN35+AA35+P35+E35) -> 0 | FU35: =SUM(FJ35+EN35+EC35+DR35+DG35+CV35+CK35+BZ35+BO35+AZ35+AO35+AB35+Q35+F35) -> 0 | FV35: =SUM(FK35+EO35+ED35+DS35+DH35+CW35+CL35+CA35+BP35+BA35+AP35+AC35+R35+G35) -> 0 | FW35: =FV35 -> 0
A36: 15 | M36: 1 | N36: 1 | O36: 1 | P36: =DS!Q138 -> 58700000 | Q36: =DS!S138 -> 58700000 | R36: =DS!AC138 -> 52882883 | T36: =DS!AC138 -> 52882883 | X36: 1 | Y36: 1 | AV36: 2 | AW36: 2 | AX36: 2 | AY36: =DS!Q144+DS!Q147 -> 132500000 | AZ36: =DS!S144+DS!S147 -> 132500000 | BA36: =DS!AC144+DS!AC147 -> 1.1936937e+08 | BF36: =DS!AC144+DS!AC147 -> 1.1936937e+08 | BK36: 2 | BL36: 1 | CR36: 2 | CS36: 1 | CT36: 1 | CU36: =DS!Q141 -> 36800000 | CV36: =DS!S141 -> 36800000 | CW36: =DS!AC141 -> 33153153 | CY36: =DS!AC141 -> 33153153 | FQ36: =SUM(FF36+EJ36+DY36+DN36+DC36+CR36+CG36+BV36+BK36+AV36+AK36+X36+M36+B36) -> 8 | FR36: =C36+N36+Y36+AL36+AW36+BL36+BW36+CH36+CS36+DD36+DO36+DZ36+EK36+FG36 -> 6 | FS36: =SUM(FH36+EL36+EA36+DP36+DE36+CT36+CI36+BX36+BM36+AX36+AM36+Z36+O36+D36) -> 4 | FT36: =SUM(FI36+EM36+EB36+DQ36+DF36+CU36+CJ36+BY36+BN36+AY36+AN36+AA36+P36+E36) -> 228000000 | FU36: =SUM(FJ36+EN36+EC36+DR36+DG36+CV36+CK36+BZ36+BO36+AZ36+AO36+AB36+Q36+F36) -> 228000000 | FV36: =SUM(FK36+EO36+ED36+DS36+DH36+CW36+CL36+CA36+BP36+BA36+AP36+AC36+R36+G36) -> 2.0540541e+08 | FW36: =FV36 -> 2.0540541e+08
A37: 16 | M37: 2 | N37: 2 | AV37: 1 | AW37: 1 | BK37: 1 | BL37: 1 | CR37: 2 | CS37: 2 | CT37: 1 | CU37: =DS!Q151 -> 159500000 | CV37: =DS!S151 -> 159500000 | CW37: =DS!AC151 -> 1.4369369e+08 | CY37: =DS!AC151 -> 1.4369369e+08 | DC37: 2 | DD37: 2 | DE37: 1 | DF37: =DS!Q155 -> 144500000 | DG37: =DS!S155 -> 144500000 | DH37: =DS!AC155 -> 1.3018018e+08 | DJ37: =DS!AC155 -> 1.3018018e+08 | DN37: 1 | DO37: 1 | DP37: 1 | DQ37: =DS!Q159 -> 58700000 | DR37: =DS!S159 -> 58700000 | DS37: =DS!AC159 -> 52882883 | DU37: =DS!AC159 -> 52882883 | FQ37: =SUM(FF37+EJ37+DY37+DN37+DC37+CR37+CG37+BV37+BK37+AV37+AK37+X37+M37+B37) -> 9 | FR37: =C37+N37+Y37+AL37+AW37+BL37+BW37+CH37+CS37+DD37+DO37+DZ37+EK37+FG37 -> 9 | FS37: =SUM(FH37+EL37+EA37+DP37+DE37+CT37+CI37+BX37+BM37+AX37+AM37+Z37+O37+D37+EW37) -> 3 | FT37: =SUM(FI37+EM37+EB37+DQ37+DF37+CU37+CJ37+BY37+BN37+AY37+AN37+AA37+P37+E37+EX37) -> 362700000 | FU37: =SUM(FJ37+EN37+EC37+DR37+DG37+CV37+CK37+BZ37+BO37+AZ37+AO37+AB37+Q37+F37+EY37) -> 362700000 | FV37: =SUM(FK37+EO37+ED37+DS37+DH37+CW37+CL37+CA37+BP37+BA37+AP37+AC37+R37+G37+EZ37) -> 3.2675676e+08 | FW37: =FV37 -> 3.2675676e+08
A38: 17 | M38: 2 | N38: 2 | O38: 2 | P38: =DS!Q162+DS!Q163 -> 41600000 | Q38: =DS!S162+DS!S163 -> 41600000 | R38: =DS!AC162+DS!AC163 -> 37477477 | T38: =DS!AC162+DS!AC163 -> 37477477 | BV38: 1 | BW38: 1 | BX38: 1 | BY38: =DS!Q165 -> 262500000 | BZ38: =DS!S165 -> 262500000 | CA38: =DS!AC165 -> 2.3648649e+08 | CC38: =DS!AC165 -> 2.3648649e+08 | DC38: 2 | DD38: 2 | FQ38: =SUM(FF38+EJ38+DY38+DN38+DC38+CR38+CG38+BV38+BK38+AV38+AK38+X38+M38+B38) -> 5 | FR38: =C38+N38+Y38+AL38+AW38+BL38+BW38+CH38+CS38+DD38+DO38+DZ38+EK38+FG38 -> 5 | FS38: =SUM(FH38+EL38+EA38+DP38+DE38+CT38+CI38+BX38+BM38+AX38+AM38+Z38+O38+D38+EW38) -> 3 | FT38: =SUM(FI38+EM38+EB38+DQ38+DF38+CU38+CJ38+BY38+BN38+AY38+AN38+AA38+P38+E38+EX38) -> 304100000 | FU38: =SUM(FJ38+EN38+EC38+DR38+DG38+CV38+CK38+BZ38+BO38+AZ38+AO38+AB38+Q38+F38+EY38) -> 304100000 | FV38: =SUM(FK38+EO38+ED38+DS38+DH38+CW38+CL38+CA38+BP38+BA38+AP38+AC38+R38+G38+EZ38) -> 2.7396396e+08 | FW38: =FV38 -> 2.7396396e+08
A39: 18 | X39: 2 | Y39: 1 | Z39: 1 | AA39: =DS!Q171 -> 91700000 | AB39: =DS!S171 -> 91700000 | AC39: =DS!AC171 -> 82612613 | AG39: =DS!AC171 -> 82612613 | AV39: 1 | AW39: 1 | BK39: 1 | BL39: 1 | BM39: 1 | BN39: =DS!Q177 -> 206000000 | BO39: =DS!S177 -> 206000000 | BP39: =DS!AC177 -> 1.8558559e+08 | BR39: =DS!AC177 -> 1.8558559e+08 | CR39: 1 | CS39: 1 | DC39: 2 | DD39: 2 | DE39: 2 | DF39: =DS!Q168+DS!Q174 -> 252700000 | DG39: =DS!S168+DS!S174 -> 252700000 | DH39: =DS!AC168+DS!AC174 -> 2.2765766e+08 | DJ39: =DS!AC168+DS!AC174 -> 2.2765766e+08 | FQ39: =SUM(FF39+EJ39+DY39+DN39+DC39+CR39+CG39+BV39+BK39+AV39+AK39+X39+M39+B39) -> 7 | FR39: =C39+N39+Y39+AL39+AW39+BL39+BW39+CH39+CS39+DD39+DO39+DZ39+EK39+FG39 -> 6 | FS39: =SUM(FH39+EL39+EA39+DP39+DE39+CT39+CI39+BX39+BM39+AX39+AM39+Z39+O39+D39) -> 4 | FT39: =SUM(FI39+EM39+EB39+DQ39+DF39+CU39+CJ39+BY39+BN39+AY39+AN39+AA39+P39+E39) -> 550400000 | FU39: =SUM(FJ39+EN39+EC39+DR39+DG39+CV39+CK39+BZ39+BO39+AZ39+AO39+AB39+Q39+F39) -> 550400000 | FV39: =SUM(FK39+EO39+ED39+DS39+DH39+CW39+CL39+CA39+BP39+BA39+AP39+AC39+R39+G39) -> 4.9585586e+08 | FW39: =FV39 -> 4.9585586e+08
A40: 19 | M40: 2 | N40: 2 | X40: 2 | Y40: 2 | AK40: 2 | AL40: 2 | AM40: 2 | AN40: =DS!Q186+DS!Q189 -> 145200000 | AO40: =DS!S186+DS!S189 -> 145200000 | AP40: =DS!AC186+DS!AC189 -> 1.3081081e+08 | AR40: =DS!AC186+DS!AC189 -> 1.3081081e+08 | BK40: 2 | BL40: 2 | BM40: 1 | BN40: =DS!Q180 -> 65500000 | BO40: =DS!S180 -> 65500000 | BP40: =DS!AC180 -> 59009009 | BR40: =DS!AC180 -> 59009009 | BV40: 2 | BW40: 2 | CG40: 1 | CH40: 1 | DC40: 3 | DD40: 2 | DE40: 1 | DF40: =DS!Q183 -> 36800000 | DG40: =DS!S183 -> 36800000 | DH40: =DS!AC183 -> 33153153 | DJ40: =DS!AC183 -> 33153153 | FQ40: =SUM(FF40+EJ40+DY40+DN40+DC40+CR40+CG40+BV40+BK40+AV40+AK40+X40+M40+B40) -> 14 | FR40: =C40+N40+Y40+AL40+AW40+BL40+BW40+CH40+CS40+DD40+DO40+DZ40+EK40+FG40 -> 13 | FS40: =SUM(FH40+EL40+EA40+DP40+DE40+CT40+CI40+BX40+BM40+AX40+AM40+Z40+O40+D40) -> 4 | FT40: =SUM(FI40+EM40+EB40+DQ40+DF40+CU40+CJ40+BY40+BN40+AY40+AN40+AA40+P40+E40) -> 247500000 | FU40: =SUM(FJ40+EN40+EC40+DR40+DG40+CV40+CK40+BZ40+BO40+AZ40+AO40+AB40+Q40+F40) -> 247500000 | FV40: =SUM(FK40+EO40+ED40+DS40+DH40+CW40+CL40+CA40+BP40+BA40+AP40+AC40+R40+G40) -> 2.2297297e+08 | FW40: =FV40 -> 2.2297297e+08
A41: 20 | M41: 2 | X41: 2 | Y41: 2 | AK41: 2 | AL41: 1 | BK41: 1 | BL41: 1 | BV41: 2 | BW41: 2 | CG41: 1 | CR41: 2 | CS41: 2 | FQ41: =SUM(FF41+EJ41+DY41+DN41+DC41+CR41+CG41+BV41+BK41+AV41+AK41+X41+M41+B41) -> 12 | FR41: =C41+N41+Y41+AL41+AW41+BL41+BW41+CH41+CS41+DD41+DO41+DZ41+EK41+FG41 -> 8 | FS41: =SUM(FH41+EL41+EA41+DP41+DE41+CT41+CI41+BX41+BM41+AX41+AM41+Z41+O41+D41) -> 0 | FT41: =SUM(FI41+EM41+EB41+DQ41+DF41+CU41+CJ41+BY41+BN41+AY41+AN41+AA41+P41+E41) -> 0 | FU41: =SUM(FJ41+EN41+EC41+DR41+DG41+CV41+CK41+BZ41+BO41+AZ41+AO41+AB41+Q41+F41) -> 0 | FV41: =SUM(FK41+EO41+ED41+DS41+DH41+CW41+CL41+CA41+BP41+BA41+AP41+AC41+R41+G41) -> 0 | FW41: =FV41 -> 0
A42: 21 | FQ42: =SUM(FF42+EJ42+DY42+DN42+DC42+CR42+CG42+BV42+BK42+AV42+AK42+X42+M42+B42) -> 0 | FR42: =C42+N42+Y42+AL42+AW42+BL42+BW42+CH42+CS42+DD42+DO42+DZ42+EK42+FG42 -> 0 | FS42: =SUM(FH42+EL42+EA42+DP42+DE42+CT42+CI42+BX42+BM42+AX42+AM42+Z42+O42+D42) -> 0 | FT42: =SUM(FI42+EM42+EB42+DQ42+DF42+CU42+CJ42+BY42+BN42+AY42+AN42+AA42+P42+E42) -> 0 | FU42: =SUM(FJ42+EN42+EC42+DR42+DG42+CV42+CK42+BZ42+BO42+AZ42+AO42+AB42+Q42+F42) -> 0 | FV42: =SUM(FK42+EO42+ED42+DS42+DH42+CW42+CL42+CA42+BP42+BA42+AP42+AC42+R42+G42) -> 0 | FW42: =FV42 -> 0
A43: 22 | FQ43: =SUM(FF43+EJ43+DY43+DN43+DC43+CR43+CG43+BV43+BK43+AV43+AK43+X43+M43+B43) -> 0 | FR43: =C43+N43+Y43+AL43+AW43+BL43+BW43+CH43+CS43+DD43+DO43+DZ43+EK43+FG43 -> 0 | FS43: =SUM(FH43+EL43+EA43+DP43+DE43+CT43+CI43+BX43+BM43+AX43+AM43+Z43+O43+D43) -> 0 | FT43: =SUM(FI43+EM43+EB43+DQ43+DF43+CU43+CJ43+BY43+BN43+AY43+AN43+AA43+P43+E43) -> 0 | FU43: =SUM(FJ43+EN43+EC43+DR43+DG43+CV43+CK43+BZ43+BO43+AZ43+AO43+AB43+Q43+F43) -> 0 | FV43: =SUM(FK43+EO43+ED43+DS43+DH43+CW43+CL43+CA43+BP43+BA43+AP43+AC43+R43+G43) -> 0 | FW43: =FV43 -> 0
A44: 23 | FQ44: =SUM(FF44+EJ44+DY44+DN44+DC44+CR44+CG44+BV44+BK44+AV44+AK44+X44+M44+B44) -> 0 | FR44: =C44+N44+Y44+AL44+AW44+BL44+BW44+CH44+CS44+DD44+DO44+DZ44+EK44+FG44 -> 0 | FS44: =SUM(FH44+EL44+EA44+DP44+DE44+CT44+CI44+BX44+BM44+AX44+AM44+Z44+O44+D44) -> 0 | FT44: =SUM(FI44+EM44+EB44+DQ44+DF44+CU44+CJ44+BY44+BN44+AY44+AN44+AA44+P44+E44) -> 0 | FU44: =SUM(FJ44+EN44+EC44+DR44+DG44+CV44+CK44+BZ44+BO44+AZ44+AO44+AB44+Q44+F44) -> 0 | FV44: =SUM(FK44+EO44+ED44+DS44+DH44+CW44+CL44+CA44+BP44+BA44+AP44+AC44+R44+G44) -> 0 | FW44: =FV44 -> 0
A45: 24 | FQ45: =SUM(FF45+EJ45+DY45+DN45+DC45+CR45+CG45+BV45+BK45+AV45+AK45+X45+M45+B45) -> 0 | FR45: =C45+N45+Y45+AL45+AW45+BL45+BW45+CH45+CS45+DD45+DO45+DZ45+EK45+FG45 -> 0 | FS45: =SUM(FH45+EL45+EA45+DP45+DE45+CT45+CI45+BX45+BM45+AX45+AM45+Z45+O45+D45) -> 0 | FT45: =SUM(FI45+EM45+EB45+DQ45+DF45+CU45+CJ45+BY45+BN45+AY45+AN45+AA45+P45+E45) -> 0 | FU45: =SUM(FJ45+EN45+EC45+DR45+DG45+CV45+CK45+BZ45+BO45+AZ45+AO45+AB45+Q45+F45) -> 0 | FV45: =SUM(FK45+EO45+ED45+DS45+DH45+CW45+CL45+CA45+BP45+BA45+AP45+AC45+R45+G45) -> 0 | FW45: =FV45 -> 0
A46: 25 | FQ46: =SUM(FF46+EJ46+DY46+DN46+DC46+CR46+CG46+BV46+BK46+AV46+AK46+X46+M46+B46) -> 0 | FR46: =C46+N46+Y46+AL46+AW46+BL46+BW46+CH46+CS46+DD46+DO46+DZ46+EK46+FG46 -> 0 | FS46: =SUM(FH46+EL46+EA46+DP46+DE46+CT46+CI46+BX46+BM46+AX46+AM46+Z46+O46+D46) -> 0 | FT46: =SUM(FI46+EM46+EB46+DQ46+DF46+CU46+CJ46+BY46+BN46+AY46+AN46+AA46+P46+E46) -> 0 | FU46: =SUM(FJ46+EN46+EC46+DR46+DG46+CV46+CK46+BZ46+BO46+AZ46+AO46+AB46+Q46+F46) -> 0 | FV46: =SUM(FK46+EO46+ED46+DS46+DH46+CW46+CL46+CA46+BP46+BA46+AP46+AC46+R46+G46) -> 0 | FW46: =FV46 -> 0
A47: 26 | FQ47: =SUM(FF47+EJ47+DY47+DN47+DC47+CR47+CG47+BV47+BK47+AV47+AK47+X47+M47+B47) -> 0 | FR47: =C47+N47+Y47+AL47+AW47+BL47+BW47+CH47+CS47+DD47+DO47+DZ47+EK47+FG47 -> 0 | FS47: =SUM(FH47+EL47+EA47+DP47+DE47+CT47+CI47+BX47+BM47+AX47+AM47+Z47+O47+D47) -> 0 | FT47: =SUM(FI47+EM47+EB47+DQ47+DF47+CU47+CJ47+BY47+BN47+AY47+AN47+AA47+P47+E47) -> 0 | FU47: =SUM(FJ47+EN47+EC47+DR47+DG47+CV47+CK47+BZ47+BO47+AZ47+AO47+AB47+Q47+F47) -> 0 | FV47: =SUM(FK47+EO47+ED47+DS47+DH47+CW47+CL47+CA47+BP47+BA47+AP47+AC47+R47+G47) -> 0 | FW47: =FV47 -> 0
A48: 27 | FQ48: =SUM(FF48+EJ48+DY48+DN48+DC48+CR48+CG48+BV48+BK48+AV48+AK48+X48+M48+B48) -> 0 | FR48: =C48+N48+Y48+AL48+AW48+BL48+BW48+CH48+CS48+DD48+DO48+DZ48+EK48+FG48 -> 0 | FS48: =SUM(FH48+EL48+EA48+DP48+DE48+CT48+CI48+BX48+BM48+AX48+AM48+Z48+O48+D48) -> 0 | FT48: =SUM(FI48+EM48+EB48+DQ48+DF48+CU48+CJ48+BY48+BN48+AY48+AN48+AA48+P48+E48) -> 0 | FU48: =SUM(FJ48+EN48+EC48+DR48+DG48+CV48+CK48+BZ48+BO48+AZ48+AO48+AB48+Q48+F48) -> 0 | FV48: =SUM(FK48+EO48+ED48+DS48+DH48+CW48+CL48+CA48+BP48+BA48+AP48+AC48+R48+G48) -> 0 | FW48: =FV48 -> 0
A49: 28 | FQ49: =SUM(FF49+EJ49+DY49+DN49+DC49+CR49+CG49+BV49+BK49+AV49+AK49+X49+M49+B49) -> 0 | FR49: =C49+N49+Y49+AL49+AW49+BL49+BW49+CH49+CS49+DD49+DO49+DZ49+EK49+FG49 -> 0 | FS49: =SUM(FH49+EL49+EA49+DP49+DE49+CT49+CI49+BX49+BM49+AX49+AM49+Z49+O49+D49) -> 0 | FT49: =SUM(FI49+EM49+EB49+DQ49+DF49+CU49+CJ49+BY49+BN49+AY49+AN49+AA49+P49+E49) -> 0 | FU49: =SUM(FJ49+EN49+EC49+DR49+DG49+CV49+CK49+BZ49+BO49+AZ49+AO49+AB49+Q49+F49) -> 0 | FV49: =SUM(FK49+EO49+ED49+DS49+DH49+CW49+CL49+CA49+BP49+BA49+AP49+AC49+R49+G49) -> 0 | FW49: =FV49 -> 0
A50: 29 | FQ50: =SUM(FF50+EJ50+DY50+DN50+DC50+CR50+CG50+BV50+BK50+AV50+AK50+X50+M50+B50) -> 0 | FR50: =C50+N50+Y50+AL50+AW50+BL50+BW50+CH50+CS50+DD50+DO50+DZ50+EK50+FG50 -> 0 | FS50: =SUM(FH50+EL50+EA50+DP50+DE50+CT50+CI50+BX50+BM50+AX50+AM50+Z50+O50+D50) -> 0 | FT50: =SUM(FI50+EM50+EB50+DQ50+DF50+CU50+CJ50+BY50+BN50+AY50+AN50+AA50+P50+E50) -> 0 | FU50: =SUM(FJ50+EN50+EC50+DR50+DG50+CV50+CK50+BZ50+BO50+AZ50+AO50+AB50+Q50+F50) -> 0 | FV50: =SUM(FK50+EO50+ED50+DS50+DH50+CW50+CL50+CA50+BP50+BA50+AP50+AC50+R50+G50) -> 0 | FW50: =FV50 -> 0
A51: 30 | FQ51: =SUM(FF51+EJ51+DY51+DN51+DC51+CR51+CG51+BV51+BK51+AV51+AK51+X51+M51+B51) -> 0 | FR51: =C51+N51+Y51+AL51+AW51+BL51+BW51+CH51+CS51+DD51+DO51+DZ51+EK51+FG51 -> 0 | FS51: =SUM(FH51+EL51+EA51+DP51+DE51+CT51+CI51+BX51+BM51+AX51+AM51+Z51+O51+D51) -> 0 | FT51: =SUM(FI51+EM51+EB51+DQ51+DF51+CU51+CJ51+BY51+BN51+AY51+AN51+AA51+P51+E51) -> 0 | FU51: =SUM(FJ51+EN51+EC51+DR51+DG51+CV51+CK51+BZ51+BO51+AZ51+AO51+AB51+Q51+F51) -> 0 | FV51: =SUM(FK51+EO51+ED51+DS51+DH51+CW51+CL51+CA51+BP51+BA51+AP51+AC51+R51+G51) -> 0 | FW51: =FV51 -> 0
A52: 31 | FQ52: =SUM(FF52+EJ52+DY52+DN52+DC52+CR52+CG52+BV52+BK52+AV52+AK52+X52+M52+B52) -> 0 | FR52: =C52+N52+Y52+AL52+AW52+BL52+BW52+CH52+CS52+DD52+DO52+DZ52+EK52+FG52 -> 0 | FS52: =SUM(FH52+EL52+EA52+DP52+DE52+CT52+CI52+BX52+BM52+AX52+AM52+Z52+O52+D52) -> 0 | FT52: =SUM(FI52+EM52+EB52+DQ52+DF52+CU52+CJ52+BY52+BN52+AY52+AN52+AA52+P52+E52) -> 0 | FU52: =SUM(FJ52+EN52+EC52+DR52+DG52+CV52+CK52+BZ52+BO52+AZ52+AO52+AB52+Q52+F52) -> 0 | FV52: =SUM(FK52+EO52+ED52+DS52+DH52+CW52+CL52+CA52+BP52+BA52+AP52+AC52+R52+G52) -> 0 | FW52: =FV52 -> 0
FQ53: =SUM(DY53+DN53+DC53+CR53+CG53+BV53+BK53+AV53+AK53+X53+M53+B53) -> 0 | FR53: =C53+N53+Y53+AL53+AW53+BL53+BW53+CH53+CS53+DD53+DO53+DZ53+EK53+FG53 -> 0 | FS53: =SUM(EA53+DP53+DE53+CT53+CI53+BX53+BM53+AX53+AM53+Z53+O53+D53) -> 0 | FT53: =SUM(EB53+DQ53+DF53+CU53+CJ53+BY53+BN53+AY53+AN53+AA53+P53+E53) -> 0 | FU53: =SUM(EC53+DR53+DG53+CV53+CK53+BZ53+BO53+AZ53+AO53+AB53+Q53+F53) -> 0 | FV53: =SUM(ED53+DS53+DH53+CW53+CL53+CA53+BP53+BA53+AP53+AC53+R53+G53) -> 0 | FW53: =FV53 -> 0
A54: TOTAL | B54: =SUM(B22:B52) -> 0 | C54: =SUM(C22:C52) -> 0 | D54: =SUM(D22:D52) -> 0 | E54: =SUM(E22:E52) -> 0 | F54: =SUM(F22:F52) -> 0 | G54: =SUM(G22:G53) -> 0 | H54: =SUM(H22:H53) -> 0 | I54: =SUM(I22:I53) -> 0 | J54: =SUM(J22:J53) -> 0 | K54: =SUM(K22:K53) -> 0 | L54: =SUM(L22:L53) -> 0 | M54: =SUM(M22:M52) -> 21 | N54: =SUM(N22:N52) -> 16 | O54: =SUM(O22:O52)+'IN AND OUT'!P10 -> 5 | P54: =SUM(P22:P53) -> 744300000 | Q54: =SUM(Q22:Q53) -> 744300000 | R54: =SUM(R22:R53) -> 6.7054054e+08 | S54: =SUM(S22:S53) -> 0 | T54: =SUM(T22:T53) -> 6.7054054e+08 | U54: =SUM(U22:U53) -> 0 | V54: =SUM(V22:V53) -> 0 | W54: =SUM(W22:W53) -> 0 | X54: =SUM(X22:X53) -> 24 | Y54: =SUM(Y22:Y52) -> 20 | Z54: =SUM(Z22:Z52) -> 6 | AA54: =SUM(AA22:AA53) -> 612900000 | AB54: =SUM(AB22:AB53) -> 612900000 | AC54: =SUM(AC22:AC53) -> 5.5216216e+08 | AD54: =SUM(AD22:AD53) -> 0 | AE54: =SUM(AE22:AE53) -> 0 | AF54: =SUM(AF22:AF53) -> 0 | AG54: =SUM(AG22:AG53) -> 5.5216216e+08 | AH54: =SUM(AH22:AH53) -> 0 | ... AJ54: =SUM(AJ22:AJ53) -> 0 | AK54: =SUM(AK22:AK52) -> 14 | AL54: =SUM(AL22:AL52) -> 9 | AM54: =SUM(AM22:AM52) -> 5 | AN54: =SUM(AN22:AN52) -> 1909200000 | AO54: =SUM(AO22:AO52) -> 1743590000 | AP54: =SUM(AP22:AP52) -> 1.5708018e+09 | AQ54: =SUM(AQ22:AQ52) -> 0 | AR54: =SUM(AR22:AR52) -> 2.2801802e+08 | ... BB54: =SUM(BB22:BB52) -> 0 | BC54: =SUM(BC22:BC53) -> 1.3720721e+08 | BD54: =SUM(BD22:BD53) -> 0 | BE54: =SUM(BE22:BE52) -> 0 | BF54: =SUM(BF22:BF52) -> 1.5245045e+09 | BG54: =SUM(BG22:BG52) -> 0 | BH54: =SUM(BH22:BH52) -> 0 | BI54: =SUM(BI22:BI52) -> 0 | BJ54: =SUM(BJ22:BJ52) -> 0 | BK54: =SUM(BK22:BK52) -> 26 | BL54: =SUM(BL22:BL52) -> 23 | ... BQ54: =SUM(BQ22:BQ52) -> 0 | BR54: =SUM(BR22:BR53) -> 9.3612613e+08 | BS54: =SUM(BS22:BS52) -> 0 | BT54: =SUM(BT22:BT52) -> 0 | BU54: =SUM(BU22:BU52) -> 0 | BV54: =SUM(BV22:BV52) -> 22 | BW54: =SUM(BW22:BW52) -> 17 | BX54: =SUM(BX22:BX52) -> 6 | BY54: =SUM(BY22:BY52) -> 627220000 | BZ54: =SUM(BZ22:BZ52) -> 627220000 | ... CH54: =SUM(CH22:CH52) -> 17 | CI54: =SUM(CI22:CI52)+'IN AND OUT'!P9 -> 8 | CJ54: =SUM(CJ22:CJ52) -> 2821300000 | CK54: =SUM(CK22:CK52) -> 2614015000 | CL54: =SUM(CL22:CL52) -> 2.3549685e+09 | CM54: =SUM(CM22:CM52) -> 0 | CN54: =SUM(CN22:CN52) -> 3.6576577e+08 | CO54: =SUM(CO22:CO52) -> 1.2927928e+09 | CP54: =SUM(CP22:CP52) -> 6.9640991e+08 | CQ54: =SUM(CQ22:CQ52) -> 0 | ... FP54: =SUM(FP22:FP52) -> 0 | FQ54: =SUM(FQ22:FQ53) -> 199 | FR54: =SUM(FR22:FR53) -> 162 | FS54: =SUM(FS22:FS53) -> 64 | FT54: =SUM(FT22:FT53) -> 11009540000 | FU54: =SUM(FU22:FU53) -> 10636645000 | FV54: =SUM(FV22:FV53) -> 9.5825631e+09 | FW54: =SUM(FW22:FW53) -> 9.5825631e+09
K55: TOTAL: | L55: =DS!AD328 -> 9.5825631e+09 | V55: TOTAL: | W55: =R54 -> 6.7054054e+08 | AI55: TOTAL: | AJ55: =AC54 -> 5.5216216e+08 | AT55: TOTAL: | AU55: =AP54 -> 1.5708018e+09 | BI55: TOTAL: | BJ55: =BA54 -> 1.6617117e+09 | BT55: TOTAL: | BU55: =BP54 -> 1.148018e+09 | CE55: TOTAL: | CF55: =CA54 -> 5.6506306e+08 | CP55: TOTAL: | CQ55: =CL54 -> 2.3549685e+09 | DA55: TOTAL: | DB55: =CW54 -> 2.4911712e+08 | DL55: TOTAL: | DM55: =DH54 -> 7.572973e+08 | DW55: TOTAL: | DX55: =DS54 -> 52882883 | EH55: TOTAL: | EI55: =ED54 -> 0 | ES55: TOTAL: | ET55: =EO54 -> 0 | FD55: TOTAL: | FE55: =EZ54 -> 0 | FO55: TOTAL: | FP55: =FK54 -> 0 | FR55: CROSSCHECK | FS55: =SMI!P44+DS!P320+'IN AND OUT'!P28 -> 64 | FT55: =SMI!Q44+DS!Q320+'IN AND OUT'!Q28 -> 11009540000 | FU55: =SMI!S44+DS!S320+'IN AND OUT'!S28 -> 10636645000 | FV55: =SMI!AB44+DS!AC320+'IN AND OUT'!AD28 -> 9.5825631e+09
K56: STORE: | L56: =DS!AD329 -> 0.70981949 | V56: PERSONAL % | W56: =SUM(W55/W19) -> 0.63861004 | AI56: Personal %: | AJ56: =SUM(AJ55/AJ19) -> 0.354803 | AT56: Personal %: | AU56: =SUM(AU55/AU19) -> 1.0093506 | BI56: Personal %: | BJ56: =SUM(BJ55/BJ19) -> 1.0677666 | BT56: Personal %: | BU56: =SUM(BU55/BU19) -> 0.73768226 | CE56: Personal %: | CF56: =SUM(CF55/CF19) -> 0.36309273 | CP56: Personal %: | CQ56: =SUM(CQ55/CQ19) -> 1.5132328 | DA56: Personal %: | DB56: =SUM(DB55/DB19) -> 0.16007526 | DL56: Personal %: | DM56: =SUM(DM55/DM19) -> 0.48661674 | DW56: Personal %: | DX56: =SUM(DX55/DX19) -> #DIV/0! | EH56: Personal %: | EI56: =SUM(EI55/EI19) -> #DIV/0! | ES56: Personal %: | ET56: =SUM(ET55/ET19) -> #DIV/0! | FD56: Personal %: | FE56: =SUM(FE55/FE19) -> #DIV/0! | FO56: Personal %: | FP56: =SUM(FP55/FP19) -> #DIV/0!
V57: STORE: | W57: =(W55/FV54)*100% -> 0.069975072 | AI57: Store %: | AJ57: =(AJ55/FV54)*100% -> 0.057621553 | AT57: Store %: | AU57: =(AU55/FV54)*100% -> 0.16392293 | BI57: Store %: | BJ57: =(BJ55/FV54)*100% -> 0.17340994 | BT57: Store %: | BU57: =(BU55/$FV$54)*100% -> 0.11980281 | CE57: Store %: | CF57: =(CF55/$FV$54)*100% -> 0.058967842 | CP57: Store %: | CQ57: =(CQ55/$FV$54)*100% -> 0.24575559 | DA57: Store %: | DB57: =(DB55/$FV$54)*100% -> 0.025996919 | DL57: Store %: | DM57: =(DM55/$FV$54)*100% -> 0.079028679 | DW57: Store %: | DX57: =(DX55/$FV$54)*100% -> 0.0055186574 | EH57: Store %: | EI57: =(EI55/$FV$54)*100% -> 0 | ES57: Store %: | ET57: =(ET55/$FV$54)*100% -> 0 | FD57: Store %: | FE57: =(FE55/$FV$54)*100% -> 0 | FO57: Store %: | FP57: =(FP55/$FV$54)*100% -> 0
FR58: Balancing | FS58: =FS54-FS55 -> 0 | FT58: =FT54-FT55 -> 0 | FU58: =FU54-FU55 -> 0 | FV58: =FV54-FV55 -> 0 | FW58: =FW54-FW55 -> 9.5825631e+09
G61: S.MANAGER | H61: =H20 -> 0.036 | I61: =I20 -> 0.03 | J61: =J20 -> 0.024 | K61: =K20 -> 0.012 | L61: =L20 -> 0.006 | R61: Komisi Individual | S61: =S20 -> 0.036 | T61: =T20 -> 0.03 | U61: =U20 -> 0.024 | V61: =V20 -> 0.012 | W61: =W20 -> 0.006 | AC61: SALES STAFF | AD61: 1-2pc | AE61: >3pc | AF61: =AF20 -> 0.036 | AG61: =AG20 -> 0.03 | AH61: =AH20 -> 0.024 | AI61: =AI20 -> 0.012 | AJ61: =AJ20 -> 0.006 | AP61: SALES STAFF | AQ61: =AQ20 -> 0.036 | AR61: =AR20 -> 0.03 | AS61: =AS20 -> 0.024 | AT61: =AT20 -> 0.012 | AU61: =AU20 -> 0.006 | BA61: SALES STAFF | BB61: =BB20 -> 0.042 | BC61: =BC20 -> 0.036 | BD61: =BD20 -> 0.03 | BE61: =BE20 -> 0.024 | BF61: =BF20 -> 0.021 | BG61: =BG20 -> 0.012 | BH61: =BH20 -> 0.0083 | BI61: =BI20 -> 0.006 | BJ61: =BJ20 -> 0.0042 | BP61: SALES STAFF | BQ61: =BQ20 -> 0.036 | BR61: =BR20 -> 0.03 | BS61: =BS20 -> 0.024 | BT61: =BT20 -> 0.012 | BU61: =BU20 -> 0.006 | CA61: SALES STAFF | CB61: =CB20 -> 0.036 | CC61: =CC20 -> 0.03 | CD61: =CD20 -> 0.024 | CE61: =CE20 -> 0.012 | CF61: =CF20 -> 0.006 | CL61: SALES STAFF | CM61: =CM20 -> 0.036 | CN61: =CN20 -> 0.03 | CO61: =CO20 -> 0.024 | CP61: =CP20 -> 0.012 | CQ61: =CQ20 -> 0.006 | CW61: SALES STAFF | CX61: =CX20 -> 0.036 | CY61: =CY20 -> 0.03 | CZ61: =CZ20 -> 0.024 | DA61: =DA20 -> 0.012 | DB61: =DB20 -> 0.006 | DH61: SALES STAFF | DI61: =DI20 -> 0.036 | DJ61: =DJ20 -> 0.03 | DK61: =DK20 -> 0.024 | DL61: =DL20 -> 0.012 | DM61: =DM20 -> 0.006 | DS61: SALES STAFF | DT61: =DT20 -> 0.036 | DU61: =DU20 -> 0.03 | DV61: =DV20 -> 0.024 | DW61: =DW20 -> 0.012 | DX61: =DX20 -> 0.006 | ED61: SALES STAFF | EE61: =EE20 -> 0.036 | EF61: =EF20 -> 0.03 | EG61: =EG20 -> 0.024 | EH61: =EH20 -> 0.012 | EI61: =EI20 -> 0.006 | EO61: SALES STAFF | EP61: 0.03 | EQ61: 0.025 | ER61: 0.02 | ES61: 0.01 | ET61: 0.005 | EZ61: SALES STAFF | FA61: 0.03 | FB61: 0.025 | FC61: 0.02 | FD61: 0.01 | FE61: 0.005 | FK61: SALES STAFF | FL61: 0.03 | FM61: 0.025 | FN61: 0.02 | FO61: 0.01 | FP61: 0.005
G62: Komisi Individual | H62: =H54*H61 -> 0 | I62: =I54*I61 -> 0 | J62: =J54 -> 0 | K62: =K54 -> 0 | L62: =L54 -> 0 | AC62: Komisi Individual | AD62: =AD54*F7 -> 0 | AE62: =AE54*G7 -> 0 | AF62: =AF54*AF61 -> 0 | AG62: =AG54*AG61 -> 16564865 | AH62: =AH54*AH61 -> 0 | AI62: =AI54*AI61 -> 0 | AJ62: =AJ54*AJ61 -> 0 | AP62: Komisi Individual | AQ62: =AQ54*AQ61 -> 0 | AR62: =AR54*AR61 -> 6840540.5 | AS62: =AS54*AS61 -> 0 | AT62: =AT54*AT61 -> 16113405 | AU62: =AU54*AU61 -> 0 | BA62: Komisi Individual | BB62: =BB54*BB61 -> 0 | BC62: =BC54*BC61 -> 4939459.5 | BD62: =BD54*BD61 -> 0 | BE62: =BE54*BE61 -> 0 | BF62: =BF54*BF61 -> 32014595 | BG62: =BG54*BG61 -> 0 | BH62: =BH54*BH61 -> 0 | BI62: =BI54*BI61 -> 0 | BJ62: =BJ54*BJ61 -> 0 | BP62: Komisi Individual | BQ62: =BQ54*BQ61 -> 0 | BR62: =BR54*BR61 -> 28083784 | BS62: =BS54*BS61 -> 0 | BT62: =BT54*BT61 -> 0 | BU62: =BU54*BU61 -> 0 | CA62: Komisi Individual | CB62: =CB54*CB61 -> 0 | CC62: =CC54*CC61 -> 16894595 | CD62: =CD54*CD61 -> 0 | CE62: =CE54*CE61 -> 0 | CF62: =CF54*CF61 -> 0 | CL62: Komisi Individual | CM62: =CM54*CM61 -> 0 | CN62: =CN54*CN61 -> 10972973 | CO62: =CO54*CO61 -> 31027027 | CP62: =CP54*CP61 -> 8356918.9 | CQ62: =CQ54*CQ61 -> 0 | CW62: Komisi Individual | CX62: =CX54*CX61 -> 0 | CY62: =CY54*CY61 -> 7386486.5 | CZ62: =CZ54*CZ61 -> 0 | DA62: =DA54*DA61 -> 0 | DB62: =DB54*DB61 -> 0 | DH62: Komisi Individual | DI62: =DI54*DI61 -> 0 | DJ62: =DJ54*DJ61 -> 22718919 | DK62: =DK54*DK61 -> 0 | DL62: =DL54*DL61 -> 0 | DM62: =DM54*DM61 -> 0 | DS62: Komisi Individual | DT62: =DT54*DT61 -> 0 | DU62: =DU54*DU61 -> 1586486.5 | DV62: =DV54*DV61 -> 0 | DW62: =DW54*DW61 -> 0 | DX62: =DX54*DX61 -> 0 | ED62: Komisi Individual | EE62: =EE54*EE61 -> 0 | EF62: =EF54*EF61 -> 0 | EG62: =EG54*EG61 -> 0 | EH62: =EH54*EH61 -> 0 | EI62: =EI54*EI61 -> 0 | EO62: Komisi Individual | EP62: =EP54*EP61 -> 0 | EQ62: =EQ54*EQ61 -> 0 | ER62: =ER54*ER61 -> 0 | ES62: =ES54*ES61 -> 0 | ET62: =ET54*ET61 -> 0 | EZ62: Komisi Individual | FA62: =FA54*FA61 -> 0 | FB62: =FB54*FB61 -> 0 | FC62: =FC54*FC61 -> 0 | FD62: =FD54*FD61 -> 0 | FE62: =FE54*FE61 -> 0 | FK62: Komisi Individual | FL62: =FL54*FL61 -> 0 | FM62: =FM54*FM61 -> 0 | FN62: =FN54*FN61 -> 0 | FO62: =FO54*FO61 -> 0 | FP62: =FP54*FP61 -> 0
K63: TOTAL: | L63: =H62+I62+J62+K62+L62 -> 0 | V63: TOTAL: | AI63: TOTAL: | AJ63: =SUM(AD62:AJ62) -> 16564865 | AT63: TOTAL: | AU63: =SUM(AQ62:AU62) -> 22953946 | BI63: TOTAL: | BJ63: =SUM(BB62:BJ62) -> 36954054 | BT63: TOTAL: | BU63: =SUM(BQ62:BU62) -> 28083784 | CE63: TOTAL: | CF63: =SUM(CB62:CF62) -> 16894595 | CP63: TOTAL: | CQ63: =SUM(CM62:CQ62) -> 50356919 | DA63: TOTAL: | DB63: =SUM(CX62:DB62) -> 7386486.5 | DL63: TOTAL: | DM63: =SUM(DI62:DM62) -> 22718919 | DW63: TOTAL: | DX63: =SUM(DT62:DX62) -> 1586486.5 | EH63: TOTAL: | EI63: =SUM(EE62:EI62) -> 0 | ES63: TOTAL: | ET63: =SUM(EP62:ET62) -> 0 | FD63: TOTAL: | FE63: =SUM(FA62:FE62) -> 0 | FO63: TOTAL: | FP63: =SUM(FL62:FP62) -> 0
AC64: KOMISI GLOBAL | AD64: 1 | AE64: 2 | AP64: KOMISI GLOBAL | AQ64: 1 | AR64: 2 | BA64: KOMISI GLOBAL | BB64: 1 | BC64: 2 | BP64: KOMISI GLOBAL | BQ64: 1 | BR64: 2 | CA64: KOMISI GLOBAL | CB64: 1 | CC64: 2 | CL64: KOMISI GLOBAL | CM64: 1 | CN64: 2 | CW64: KOMISI GLOBAL | CX64: 1 | CY64: 2 | DH64: KOMISI GLOBAL | DI64: 1 | DJ64: 2 | DS64: KOMISI GLOBAL | DT64: 1 | DU64: 2 | ED64: KOMISI GLOBAL | EE64: 1 | EF64: 2 | EO64: KOMISI GLOBAL | EP64: 1 | EQ64: 2 | EZ64: KOMISI GLOBAL | FA64: 1 | FB64: 2 | FK64: KOMISI GLOBAL | FL64: 1 | FM64: 2
G65: Komisi Store | H65: A3 | I65: A6 | J65: All | R65: Komisi Store | S65: A3 | T65: A6 | U65: ALL | AD65: =H69 -> 0 | AE65: =T66 -> 0 | AR65: =T66 -> 0 | BB65: =H69 -> 0 | BC65: =T66 -> 0 | BR65: =AP66 -> 0 | CB65: =AO69 -> 0 | CC65: =BA66 -> 0 | CM65: =AZ69 -> 0 | CN65: =BP66 -> 0 | CX65: =BO69 -> 0 | CY65: =CA66 -> 0 | DI65: =BZ69 -> 0 | DJ65: =CL66 -> 0 | DT65: =CK69 -> 0 | DU65: =CW66 -> 0 | EE65: =CV69 -> 0 | EF65: =DH66 -> 0 | EP65: =DG69 -> 0 | EQ65: =DS66 -> 0 | FA65: =DG69 -> 0 | FB65: =DS66 -> 0 | FL65: =DR69 -> 0 | FM65: =ED66 -> 0
AC67: TOTAL KOMISI | AD67: =AJ63+AD65 -> 16564865 | AP67: TOTAL KOMISI | AQ67: =AQ65+AU63 -> 22953946 | BA67: TOTAL KOMISI | BB67: =BJ63+BB65 -> 36954054 | BP67: TOTAL KOMISI | BQ67: =BU63+BR65+BQ65 -> 28083784 | CA67: TOTAL KOMISI | CB67: =CF63+CC65+CB65 -> 16894595 | CL67: TOTAL KOMISI | CM67: =CQ63+CN65+CM65 -> 50356919 | CW67: TOTAL KOMISI | CX67: =DB63+CY65+CX65 -> 7386486.5 | DH67: TOTAL KOMISI | DI67: =DM63+DJ65+DI65 -> 22718919 | DS67: TOTAL KOMISI | DT67: =DX63+DU65+DT65 -> 1586486.5 | ED67: TOTAL KOMISI | EE67: =EI63+EF65+EE65 -> 0 | EO67: TOTAL KOMISI | EP67: =ET63+EQ65+EP65 -> 0 | EZ67: TOTAL KOMISI | FA67: =FE63+FB65+FA65 -> 0 | FK67: TOTAL KOMISI | FL67: =FP63+FM65+FL65 -> 0
G68: GLOBAL | H68: 1 | I68: 2 | R68: KOMISI GLOBAL | S68: 1 | T68: 2
G71: TOTAL KOMISI | H71: =L63+I66+H69+H66+J66 -> 0 | R71: TOTAL KOMISI

Sheet Commission
A1: PT. MOGEMS PUTRI INTERNATIONAL | I1: Achievement Store | J1: =DS!AD328 -> 9.5825631e+09
A2: COMMISSION BVLGARI PLAZA INDONESIA | I2: Target Store | J2: =DS!AD322 -> 13500000000
A3: =DS!B3 -> 46266 | J3: =DS!AD329 -> 0.70981949
A6: Name | B6: % Personal Achiev. | C6: % Store Achiev | D6: Amount Achiv | E6: Cross Selling (net sales) <150 JT | L6: AFTER TAX | M6: Lacking Target | N6: Daily
E7: 0.36% (2 pcs ) | F7: 0.48% (3 pcs) | G7: TOTAL | H7: Spot Incentive / Month | I7: Total Slow Moving | J7: Individual Commission | K7: TOTAL
A9: ='TRAFFIC & COMMISSION REPORT'!B19 -> MONIQ | C9: ='TRAFFIC & COMMISSION REPORT'!L56 -> 0.70981949 | D9: ='TRAFFIC & COMMISSION REPORT'!L55 -> 9.5825631e+09 | L9: =K9*0.95 -> 0 | M9: =('TRAFFIC & COMMISSION REPORT'!L19-'TRAFFIC & COMMISSION REPORT'!L55)*1.11 -> 4.348355e+09 | N9: =M9/9 -> 4.8315056e+08
A11: ='TRAFFIC & COMMISSION REPORT'!M19 -> HERDY | B11: ='TRAFFIC & COMMISSION REPORT'!W56 -> 0.63861004 | C11: ='TRAFFIC & COMMISSION REPORT'!W57 -> 0.069975072 | D11: ='TRAFFIC & COMMISSION REPORT'!W55 -> 6.7054054e+08 | L11: =K11*0.95 -> 0 | M11: =('TRAFFIC & COMMISSION REPORT'!W19-'TRAFFIC & COMMISSION REPORT'!W55)*1.11 -> 4.212e+08
A13: ='TRAFFIC & COMMISSION REPORT'!X19 -> AJENG | B13: ='TRAFFIC & COMMISSION REPORT'!AJ56 -> 0.354803 | C13: ='TRAFFIC & COMMISSION REPORT'!AJ57 -> 0.057621553 | D13: ='TRAFFIC & COMMISSION REPORT'!AJ55 -> 5.5216216e+08 | J13: ='TRAFFIC & COMMISSION REPORT'!AD67 -> 16564865 | K13: =G13+H13+I13+J13 -> 16564865 | L13: =K13*0.95 -> 15736622 | M13: =('TRAFFIC & COMMISSION REPORT'!AJ19-'TRAFFIC & COMMISSION REPORT'!AJ55)*1.11 -> 1.1145375e+09
A15: ='TRAFFIC & COMMISSION REPORT'!AK19 -> SYANDY | B15: ='TRAFFIC & COMMISSION REPORT'!AU56 -> 1.0093506 | C15: ='TRAFFIC & COMMISSION REPORT'!AU57 -> 0.16392293 | D15: ='TRAFFIC & COMMISSION REPORT'!AU55 -> 1.5708018e+09 | J15: ='TRAFFIC & COMMISSION REPORT'!AQ67 -> 22953946 | K15: =G15+H15+I15+J15 -> 22953946 | L15: =K15*0.95 -> 21806249 | M15: =('TRAFFIC & COMMISSION REPORT'!AU19-'TRAFFIC & COMMISSION REPORT'!AU55)*1.11 -> -16152500
A17: ='TRAFFIC & COMMISSION REPORT'!AV19 -> SISKA (VIP CA) | B17: ='TRAFFIC & COMMISSION REPORT'!BJ56 -> 1.0677666 | C17: ='TRAFFIC & COMMISSION REPORT'!BJ57 -> 0.17340994 | D17: ='TRAFFIC & COMMISSION REPORT'!BJ55 -> 1.6617117e+09 | F17: =(DS!S51+DS!S52+DS!S53+DS!S54)*0.48% -> 1782720 | G17: =E17+F17 -> 1782720 | J17: ='TRAFFIC & COMMISSION REPORT'!BB67 -> 36954054 | K17: =G17+H17+I17+J17 -> 38736774 | L17: =K17*0.95 -> 36799935 | M17: =('TRAFFIC & COMMISSION REPORT'!BJ19-'TRAFFIC & COMMISSION REPORT'!BJ55)*1.11 -> -1.170625e+08
F18: CBPI 11406
A19: ='TRAFFIC & COMMISSION REPORT'!BK19 -> DIAN | B19: ='TRAFFIC & COMMISSION REPORT'!BU56 -> 0.73768226 | C19: ='TRAFFIC & COMMISSION REPORT'!BU57 -> 0.11980281 | D19: ='TRAFFIC & COMMISSION REPORT'!BU55 -> 1.148018e+09 | I19: =SMI!AI7 -> 12000000 | J19: ='TRAFFIC & COMMISSION REPORT'!BQ67 -> 28083784 | K19: =G19+H19+I19+J19 -> 40083784 | L19: =K19*0.95 -> 38079595 | M19: =('TRAFFIC & COMMISSION REPORT'!BU19-'TRAFFIC & COMMISSION REPORT'!BU55)*1.11 -> 4.531375e+08
I20: =SMI!B7 -> CBPI 11396
A21: ='TRAFFIC & COMMISSION REPORT'!BV19 -> IRMA | B21: ='TRAFFIC & COMMISSION REPORT'!CF56 -> 0.36309273 | C21: ='TRAFFIC & COMMISSION REPORT'!CF57 -> 0.058967842 | D21: ='TRAFFIC & COMMISSION REPORT'!CF55 -> 5.6506306e+08 | J21: ='TRAFFIC & COMMISSION REPORT'!CB67 -> 16894595 | K21: =G21+H21+I21+J21 -> 16894595 | L21: =K21*0.95 -> 16049865 | M21: =('TRAFFIC & COMMISSION REPORT'!CF19-'TRAFFIC & COMMISSION REPORT'!CF55)*1.11 -> 1.1002175e+09
A23: ='TRAFFIC & COMMISSION REPORT'!CG19 -> JOJO | B23: ='TRAFFIC & COMMISSION REPORT'!CQ56 -> 1.5132328 | C23: ='TRAFFIC & COMMISSION REPORT'!CQ57 -> 0.24575559 | D23: ='TRAFFIC & COMMISSION REPORT'!CQ55 -> 2.3549685e+09 | J23: ='TRAFFIC & COMMISSION REPORT'!CM67 -> 50356919 | K23: =G23+H23+I23+J23 -> 50356919 | L23: =K23*0.95 -> 47839073 | M23: =('TRAFFIC & COMMISSION REPORT'!CQ19-'TRAFFIC & COMMISSION REPORT'!CQ55)*1.11 -> -8.865775e+08
A25: ='TRAFFIC & COMMISSION REPORT'!CR19 -> ARI | B25: ='TRAFFIC & COMMISSION REPORT'!DB56 -> 0.16007526 | C25: ='TRAFFIC & COMMISSION REPORT'!DB57 -> 0.025996919 | D25: ='TRAFFIC & COMMISSION REPORT'!DB55 -> 2.4911712e+08 | J25: ='TRAFFIC & COMMISSION REPORT'!CX67 -> 7386486.5 | K25: =G25+H25+I25+J25+E25 -> 7386486.5 | L25: =K25*0.95 -> 7017162.2 | M25: =('TRAFFIC & COMMISSION REPORT'!DB19-'TRAFFIC & COMMISSION REPORT'!DB55)*1.11 -> 1450917500
A27: ='TRAFFIC & COMMISSION REPORT'!DC19 -> ALVIN | B27: ='TRAFFIC & COMMISSION REPORT'!DM56 -> 0.48661674 | C27: ='TRAFFIC & COMMISSION REPORT'!DM57 -> 0.079028679 | D27: ='TRAFFIC & COMMISSION REPORT'!DM55 -> 7.572973e+08 | J27: ='TRAFFIC & COMMISSION REPORT'!DI67 -> 22718919 | K27: =G27+H27+I27+J27 -> 22718919 | L27: =K27*0.95 -> 21582973 | M27: =('TRAFFIC & COMMISSION REPORT'!DM19-'TRAFFIC & COMMISSION REPORT'!DM55)*1.11 -> 8.868375e+08
A29: ='TRAFFIC & COMMISSION REPORT'!DN19 -> ARIF PS | B29: ='TRAFFIC & COMMISSION REPORT'!DX57 -> 0.0055186574 | C29: ='TRAFFIC & COMMISSION REPORT'!DX57 -> 0.0055186574 | D29: ='TRAFFIC & COMMISSION REPORT'!DX55 -> 52882883 | J29: ='TRAFFIC & COMMISSION REPORT'!DT67 -> 1586486.5 | K29: =G29+H29+I29+J29 -> 1586486.5 | L29: =K29*0.95 -> 1507162.2
A31: ='TRAFFIC & COMMISSION REPORT'!DY19 -> 0 | B31: ='TRAFFIC & COMMISSION REPORT'!DX59 -> 0 | C31: ='TRAFFIC & COMMISSION REPORT'!EI57 -> 0 | D31: ='TRAFFIC & COMMISSION REPORT'!EI55 -> 0 | J31: ='TRAFFIC & COMMISSION REPORT'!EE67 -> 0 | K31: =G31+H31+I31+J31 -> 0 | L31: =K31*0.95 -> 0
A33: ='TRAFFIC & COMMISSION REPORT'!EJ19 -> 0 | B33: ='TRAFFIC & COMMISSION REPORT'!DX62 -> 0 | C33: ='TRAFFIC & COMMISSION REPORT'!DB64 -> 0 | D33: ='TRAFFIC & COMMISSION REPORT'!ET55 -> 0 | J33: ='TRAFFIC & COMMISSION REPORT'!EP67 -> 0 | K33: =G33+H33+I33+J33 -> 0 | L33: =K33*0.95 -> 0
B35: ='TRAFFIC & COMMISSION REPORT'!DX64 -> 0 | C35: ='TRAFFIC & COMMISSION REPORT'!FP57 -> 0 | D35: ='TRAFFIC & COMMISSION REPORT'!FE55 -> 0 | J35: ='TRAFFIC & COMMISSION REPORT'!FA67 -> 0 | K35: =G35+H35+I35+J35 -> 0
J36: ='TRAFFIC & COMMISSION REPORT'!EP70 -> 0 | K36: =G36+H36+I36+J36 -> 0
J37: ='TRAFFIC & COMMISSION REPORT'!EP71 -> 0 | K37: =G37+H37+I37+J37 -> 0
A38: T O T A L | H38: =SUM(H15:H37) -> 0 | I38: =SUM(I9+I11+I13+I15+I17+I19+I21+I23+I25+I27+I29+I31+I33) -> 12000000 | J38: =SUM(J9+J11+J13+J15+J17+J19+J21+J23+J25+J27+J29+J31) -> 2.0350005e+08 | K38: =SUM(K9+K11+K13+K15+K17+K19+K21+K23+K25+K27+K29+K31) -> 2.1728277e+08 | L38: =SUM(L9+L11+L13+L15+L17+L19+L21+L23+L25+L27+L29+L31) -> 2.0641864e+08
A41: Prepared by,
A42: =A9 -> MONIQ

Sheet SPPR _
A1: SALES PERSON PRODUCTIVITY REPORT
A3: PERIOD | B3: =DS!B3 -> 46266
A5: STORE | B5: =DS!A1 -> BVLGARI – Plaza Indonesia
B6: Rubah intial | E6: Rubah intial
A7: NAME | B7: CODE | C7: DAILY TRAFFIC | D7: TRAFFIC WITH DATA | E7: CUSTOMER CLOSED | F7: CLOSING RATIO | G7: GROSS SALES Rp | H7: NETT SALES Rp | I7: % DISCOUNT | J7: PIECES SOLD | K7: AVERAGE SALES Rp
A8: =Commission!A9 -> MONIQ | B8: MM | C8: ='TRAFFIC & COMMISSION REPORT'!B54 -> 0 | D8: ='TRAFFIC & COMMISSION REPORT'!C54 -> 0 | E8: =COUNTIF(DS!AG:AG,"MM")+COUNTIF(SMI!AF:AF,"MM")+COUNTIF('IN AND OUT'!$AG$7:$AG$27,"MM") -> 0 | F8: =E8/C8 -> #DIV/0! | G8: ='TRAFFIC & COMMISSION REPORT'!E54 -> 0 | H8: ='TRAFFIC & COMMISSION REPORT'!F54 -> 0 | I8: =(G8-H8)/G8 -> #DIV/0! | J8: ='TRAFFIC & COMMISSION REPORT'!D54 -> 0 | K8: =G8/J8 -> #DIV/0!
A9: =Commission!A11 -> HERDY | B9: HS | C9: ='TRAFFIC & COMMISSION REPORT'!M54 -> 21 | D9: ='TRAFFIC & COMMISSION REPORT'!N54 -> 16 | E9: =COUNTIF(DS!AG:AG,"HS")+COUNTIF(SMI!AF:AF,"HS")+COUNTIF('IN AND OUT'!$AG$7:$AG$27,"HS") -> 4 | F9: =E9/C9 -> 0.19047619 | G9: ='TRAFFIC & COMMISSION REPORT'!P54 -> 744300000 | H9: ='TRAFFIC & COMMISSION REPORT'!Q54 -> 744300000 | I9: =(G9-H9)/G9 -> 0 | J9: ='TRAFFIC & COMMISSION REPORT'!O54 -> 5 | K9: =G9/J9 -> 148860000
A10: =Commission!A13 -> AJENG | B10: AJ | C10: ='TRAFFIC & COMMISSION REPORT'!X54 -> 24 | D10: ='TRAFFIC & COMMISSION REPORT'!Y54 -> 20 | E10: =COUNTIF(DS!AG:AG,"AJ")+COUNTIF(SMI!AF:AF,"AJ")+COUNTIF('IN AND OUT'!$AG$7:$AG$27,"AJ") -> 6 | F10: =E10/C10 -> 0.25 | G10: ='TRAFFIC & COMMISSION REPORT'!AA54 -> 612900000 | H10: ='TRAFFIC & COMMISSION REPORT'!AB54 -> 612900000 | I10: =(G10-H10)/G10 -> 0 | J10: ='TRAFFIC & COMMISSION REPORT'!Z54 -> 6 | K10: =G10/J10 -> 102150000
A11: =Commission!A15 -> SYANDY | B11: SD | C11: ='TRAFFIC & COMMISSION REPORT'!AK54 -> 14 | D11: ='TRAFFIC & COMMISSION REPORT'!AL54 -> 9 | E11: =COUNTIF(DS!AG:AG,"SD")+COUNTIF(SMI!AF:AF,"SD")+COUNTIF('IN AND OUT'!$AG$7:$AG$27,"SD") -> 4 | F11: =E11/C11 -> 0.28571429 | G11: ='TRAFFIC & COMMISSION REPORT'!AN54 -> 1909200000 | H11: ='TRAFFIC & COMMISSION REPORT'!AO54 -> 1743590000 | I11: =(G11-H11)/G11 -> 0.086743138 | J11: ='TRAFFIC & COMMISSION REPORT'!AM54 -> 5 | K11: =G11/J11 -> 381840000
A12: =Commission!A17 -> SISKA (VIP CA) | B12: SK | C12: ='TRAFFIC & COMMISSION REPORT'!AV54 -> 21 | D12: ='TRAFFIC & COMMISSION REPORT'!AW54 -> 15 | E12: =COUNTIF(DS!AG:AG,"SK")+COUNTIF(SMI!AF:AF,"SK")+COUNTIF('IN AND OUT'!$AG$7:$AG$27,"SK") -> 7 | F12: =E12/C12 -> 0.33333333 | G12: ='TRAFFIC & COMMISSION REPORT'!AY54 -> 1844500000 | H12: ='TRAFFIC & COMMISSION REPORT'!AZ54 -> 1844500000 | I12: =(G12-H12)/G12 -> 0 | J12: ='TRAFFIC & COMMISSION REPORT'!AX54 -> 13 | K12: =G12/J12 -> 1.4188462e+08
A13: =Commission!A19 -> DIAN | B13: DP | C13: ='TRAFFIC & COMMISSION REPORT'!BK54 -> 26 | D13: ='TRAFFIC & COMMISSION REPORT'!BL54 -> 23 | E13: =COUNTIF(DS!AG:AG,"DP")+COUNTIF(SMI!AF:AF,"DP")+COUNTIF('IN AND OUT'!$AG$7:$AG$27,"DP") -> 7 | F13: =E13/C13 -> 0.26923077 | G13: ='TRAFFIC & COMMISSION REPORT'!BN54 -> 1274300000 | H13: ='TRAFFIC & COMMISSION REPORT'!BO54 -> 1274300000 | I13: =(G13-H13)/G13 -> 0 | J13: ='TRAFFIC & COMMISSION REPORT'!BM54 -> 7 | K13: =G13/J13 -> 1.8204286e+08
A14: =Commission!A21 -> IRMA | B14: IR | C14: ='TRAFFIC & COMMISSION REPORT'!BV54 -> 22 | D14: ='TRAFFIC & COMMISSION REPORT'!BW54 -> 17 | E14: =COUNTIF(DS!AG:AG,"IR")+COUNTIF(SMI!AF:AF,"IR")+COUNTIF('IN AND OUT'!$AG$7:$AG$27,"IR") -> 5 | F14: =E14/C14 -> 0.22727273 | G14: ='TRAFFIC & COMMISSION REPORT'!BY54 -> 627220000 | H14: ='TRAFFIC & COMMISSION REPORT'!BZ54 -> 627220000 | I14: =(G14-H14)/G14 -> 0 | J14: ='TRAFFIC & COMMISSION REPORT'!BX54 -> 6 | K14: =G14/J14 -> 1.0453667e+08
A15: =Commission!A23 -> JOJO | B15: JJ | C15: ='TRAFFIC & COMMISSION REPORT'!CG54 -> 18 | D15: ='TRAFFIC & COMMISSION REPORT'!CH54 -> 17 | E15: =COUNTIF(DS!AG:AG,"JJ")+COUNTIF(SMI!AF:AF,"JJ")+COUNTIF('IN AND OUT'!$AG$7:$AG$27,"JJ") -> 8 | F15: =E15/C15 -> 0.44444444 | G15: ='TRAFFIC & COMMISSION REPORT'!CJ54 -> 2821300000 | H15: ='TRAFFIC & COMMISSION REPORT'!CK54 -> 2614015000 | I15: =(G15-H15)/G15 -> 0.073471449 | J15: ='TRAFFIC & COMMISSION REPORT'!CI54 -> 8 | K15: =G15/J15 -> 352662500
A16: =Commission!A25 -> ARI | B16: AK | C16: ='TRAFFIC & COMMISSION REPORT'!CR54 -> 19 | D16: ='TRAFFIC & COMMISSION REPORT'!CS54 -> 15 | E16: =COUNTIF(DS!AG:AG,"AK")+COUNTIF(SMI!AF:AF,"AK")+COUNTIF('IN AND OUT'!$AG$7:$AG$27,"AK") -> 4 | F16: =E16/C16 -> 0.21052632 | G16: ='TRAFFIC & COMMISSION REPORT'!CU54 -> 276520000 | H16: ='TRAFFIC & COMMISSION REPORT'!CV54 -> 276520000 | I16: =(G16-H16)/G16 -> 0 | J16: ='TRAFFIC & COMMISSION REPORT'!CT54 -> 4 | K16: =G16/J16 -> 69130000
A17: =Commission!A27 -> ALVIN | B17: AL | C17: ='TRAFFIC & COMMISSION REPORT'!DC54 -> 33 | D17: ='TRAFFIC & COMMISSION REPORT'!DD54 -> 29 | E17: =COUNTIF(DS!AG:AG,"AL")+COUNTIF(SMI!AF:AF,"AL")+COUNTIF('IN AND OUT'!$AG$7:$AG$27,"AL") -> 8 | F17: =E17/C17 -> 0.24242424 | G17: ='TRAFFIC & COMMISSION REPORT'!DF54 -> 840600000 | H17: ='TRAFFIC & COMMISSION REPORT'!DG54 -> 840600000 | I17: 0 | J17: ='TRAFFIC & COMMISSION REPORT'!DE54 -> 9 | K17: =G17/J17 -> 93400000
C18: ='TRAFFIC & COMMISSION REPORT'!DN54 -> 1 | D18: ='TRAFFIC & COMMISSION REPORT'!DO54 -> 1 | E18: =COUNTIF(DS!AG:AG,"IM")+COUNTIF(SMI!AF:AF,"IM")+COUNTIF('IN AND OUT'!$AG$7:$AG$27,"IM") -> 0 | F18: =E18/C18 -> 0 | G18: ='TRAFFIC & COMMISSION REPORT'!DQ54 -> 58700000 | H18: ='TRAFFIC & COMMISSION REPORT'!DR54 -> 58700000 | I18: 0 | J18: ='TRAFFIC & COMMISSION REPORT'!DP54 -> 1 | K18: =G18/J18 -> 58700000
A19: ='TRAFFIC & COMMISSION REPORT'!DY19 -> 0 | C19: ='TRAFFIC & COMMISSION REPORT'!DY54 -> 0 | D19: ='TRAFFIC & COMMISSION REPORT'!DZ54 -> 0 | E19: =COUNTIF(DS!AG:AG,"BD")+COUNTIF(SMI!AF:AF,"BD")+COUNTIF('IN AND OUT'!$AG$7:$AG$27,"BD") -> 0 | F19: =E19/C19 -> #DIV/0! | G19: ='TRAFFIC & COMMISSION REPORT'!EB54 -> 0 | H19: ='TRAFFIC & COMMISSION REPORT'!EC54 -> 0 | I19: 0 | J19: ='TRAFFIC & COMMISSION REPORT'!EA54 -> 0 | K19: =G19/J19 -> #DIV/0!
A20: ='TRAFFIC & COMMISSION REPORT'!EJ19 -> 0 | C20: ='TRAFFIC & COMMISSION REPORT'!EJ54 -> 0 | D20: ='TRAFFIC & COMMISSION REPORT'!EK54 -> 0 | E20: =COUNTIF(DS!AG:AG,"DN")+COUNTIF(SMI!AF:AF,"DN")+COUNTIF('IN AND OUT'!$AG$7:$AG$27,"DN") -> 0 | F20: =E20/C20 -> #DIV/0! | G20: ='TRAFFIC & COMMISSION REPORT'!EM54 -> 0 | H20: ='TRAFFIC & COMMISSION REPORT'!EN54 -> 0 | I20: 0 | J20: ='TRAFFIC & COMMISSION REPORT'!EL54 -> 0 | K20: =G20/J20 -> #DIV/0!
A21: ='TRAFFIC & COMMISSION REPORT'!EU19 -> 0 | C21: ='TRAFFIC & COMMISSION REPORT'!EU54 -> 0 | D21: ='TRAFFIC & COMMISSION REPORT'!EV54 -> 0 | E21: =COUNTIF(DS!AG:AG,"FA")+COUNTIF(SMI!AF:AF,"FA")+COUNTIF('IN AND OUT'!$AG$7:$AG$27,"FA") -> 0 | F21: =E21/C21 -> #DIV/0! | G21: ='TRAFFIC & COMMISSION REPORT'!EX54 -> 0 | H21: ='TRAFFIC & COMMISSION REPORT'!EY54 -> 0 | I21: 0 | J21: ='TRAFFIC & COMMISSION REPORT'!EW54 -> 0 | K21: =G21/J21 -> #DIV/0!
A22: ='TRAFFIC & COMMISSION REPORT'!FF19 -> 0 | C22: ='TRAFFIC & COMMISSION REPORT'!FF54 -> 0 | D22: ='TRAFFIC & COMMISSION REPORT'!FG54 -> 0 | E22: =COUNTIF(DS!AG:AG,"DN")+COUNTIF(SMI!AF:AF,"DN")+COUNTIF('IN AND OUT'!$AG$7:$AG$27,"DN") -> 0 | F22: =E22/C22 -> #DIV/0! | G22: ='TRAFFIC & COMMISSION REPORT'!FK54 -> 0 | H22: ='TRAFFIC & COMMISSION REPORT'!FJ54 -> 0 | I22: 0 | J22: ='TRAFFIC & COMMISSION REPORT'!FH54 -> 0 | K22: =G22/J22 -> #DIV/0!
A23: TOTAL | C23: =SUM(C8:C22) -> 199 | D23: =SUM(D8:D22) -> 162 | E23: =SUM(E8:E22) -> 53 | F23: =E23/C23 -> 0.26633166 | G23: =SUM(G8:G22) -> 11009540000 | H23: =SUM(H8:H22) -> 10636645000 | I23: =(G23-H23)/G23 -> 0.033870171 | J23: =SUM(J8:J22) -> 64 | K23: =H23/J23 -> 1.6619758e+08
A26: daily sales,smi,in-out
A27: NAME | B27: WALK IN | C27: FOLLOWED UP | D27: TOTAL | E27: NEW | F27: OLD
A28: =A8 -> MONIQ | B28: =COUNTIFS(DS!AG:AG,B8,DS!I:I,"1")+COUNTIFS(SMI!AF:AF,B8,SMI!I:I,"1")+COUNTIFS('IN AND OUT'!$AG$9:$AG$27,B8,'IN AND OUT'!$I$9:$I$27,"1") -> 0 | C28: =COUNTIFS(DS!AG:AG,B8,DS!J:J,"1")+COUNTIFS(SMI!AF:AF,B8,SMI!J:J,"1")+COUNTIFS('IN AND OUT'!$AG$9:$AG$27,B8,'IN AND OUT'!$J$9:$J$27,"1") -> 0 | D28: =B28+C28 -> 0 | E28: =COUNTIFS(DS!AG:AG,B8,DS!G:G,"1")+COUNTIFS(SMI!AF:AF,B8,SMI!G:G,"1")+COUNTIFS('IN AND OUT'!$AG$9:$AG$27,B8,'IN AND OUT'!$G$9:$G$27,"1") -> 0 | F28: =COUNTIFS(DS!AG:AG,B8,DS!H:H,"1")+COUNTIFS(SMI!AF:AF,B8,SMI!H:H,"1")+COUNTIFS('IN AND OUT'!$AG$9:$AG$27,B8,'IN AND OUT'!$H$9:$H$27,"1") -> 0
A29: =A9 -> HERDY | B29: =COUNTIFS(DS!AG:AG,B9,DS!I:I,"1")+COUNTIFS(SMI!AF:AF,B9,SMI!I:I,"1")+COUNTIFS('IN AND OUT'!$AG$9:$AG$27,B9,'IN AND OUT'!$I$9:$I$27,"1") -> 1 | C29: =COUNTIFS(DS!AG:AG,B9,DS!J:J,"1")+COUNTIFS(SMI!AF:AF,B9,SMI!J:J,"1")+COUNTIFS('IN AND OUT'!$AG$9:$AG$27,B9,'IN AND OUT'!$J$9:$J$27,"1") -> 3 | D29: =B29+C29 -> 4 | E29: =COUNTIFS(DS!AG:AG,B9,DS!G:G,"1")+COUNTIFS(SMI!AF:AF,B9,SMI!G:G,"1")+COUNTIFS('IN AND OUT'!$AG$9:$AG$27,B9,'IN AND OUT'!$G$9:$G$27,"1") -> 1 | F29: =COUNTIFS(DS!AG:AG,B9,DS!H:H,"1")+COUNTIFS(SMI!AF:AF,B9,SMI!H:H,"1")+COUNTIFS('IN AND OUT'!$AG$9:$AG$27,B9,'IN AND OUT'!$H$9:$H$27,"1") -> 3
A30: =A10 -> AJENG | B30: =COUNTIFS(DS!AG:AG,B10,DS!I:I,"1")+COUNTIFS(SMI!AF:AF,B10,SMI!I:I,"1")+COUNTIFS('IN AND OUT'!$AG$9:$AG$27,B10,'IN AND OUT'!$I$9:$I$27,"1") -> 2 | C30: =COUNTIFS(DS!AG:AG,B10,DS!J:J,"1")+COUNTIFS(SMI!AF:AF,B10,SMI!J:J,"1")+COUNTIFS('IN AND OUT'!$AG$9:$AG$27,B10,'IN AND OUT'!$J$9:$J$27,"1") -> 4 | D30: =B30+C30 -> 6 | E30: =COUNTIFS(DS!AG:AG,B10,DS!G:G,"1")+COUNTIFS(SMI!AF:AF,B10,SMI!G:G,"1")+COUNTIFS('IN AND OUT'!$AG$9:$AG$27,B10,'IN AND OUT'!$G$9:$G$27,"1") -> 2 | F30: =COUNTIFS(DS!AG:AG,B10,DS!H:H,"1")+COUNTIFS(SMI!AF:AF,B10,SMI!H:H,"1")+COUNTIFS('IN AND OUT'!$AG$9:$AG$27,B10,'IN AND OUT'!$H$9:$H$27,"1") -> 4
A31: =A11 -> SYANDY | B31: =COUNTIFS(DS!AG:AG,B11,DS!I:I,"1")+COUNTIFS(SMI!AF:AF,B11,SMI!I:I,"1")+COUNTIFS('IN AND OUT'!$AG$9:$AG$27,B11,'IN AND OUT'!$I$9:$I$27,"1") -> 0 | C31: =COUNTIFS(DS!AG:AG,B11,DS!J:J,"1")+COUNTIFS(SMI!AF:AF,B11,SMI!J:J,"1")+COUNTIFS('IN AND OUT'!$AG$9:$AG$27,B11,'IN AND OUT'!$J$9:$J$27,"1") -> 4 | D31: =B31+C31 -> 4 | E31: =COUNTIFS(DS!AG:AG,B11,DS!G:G,"1")+COUNTIFS(SMI!AF:AF,B11,SMI!G:G,"1")+COUNTIFS('IN AND OUT'!$AG$9:$AG$27,B11,'IN AND OUT'!$G$9:$G$27,"1") -> 0 | F31: =COUNTIFS(DS!AG:AG,B11,DS!H:H,"1")+COUNTIFS(SMI!AF:AF,B11,SMI!H:H,"1")+COUNTIFS('IN AND OUT'!$AG$9:$AG$27,B11,'IN AND OUT'!$H$9:$H$27,"1") -> 4
A32: =A12 -> SISKA (VIP CA) | B32: =COUNTIFS(DS!AG:AG,B12,DS!I:I,"1")+COUNTIFS(SMI!AF:AF,B12,SMI!I:I,"1")+COUNTIFS('IN AND OUT'!$AG$9:$AG$27,B12,'IN AND OUT'!$I$9:$I$27,"1") -> 4 | C32: =COUNTIFS(DS!AG:AG,B12,DS!J:J,"1")+COUNTIFS(SMI!AF:AF,B12,SMI!J:J,"1")+COUNTIFS('IN AND OUT'!$AG$9:$AG$27,B12,'IN AND OUT'!$J$9:$J$27,"1") -> 3 | D32: =B32+C32 -> 7 | E32: =COUNTIFS(DS!AG:AG,B12,DS!G:G,"1")+COUNTIFS(SMI!AF:AF,B12,SMI!G:G,"1")+COUNTIFS('IN AND OUT'!$AG$9:$AG$27,B12,'IN AND OUT'!$G$9:$G$27,"1") -> 5 | F32: =COUNTIFS(DS!AG:AG,B12,DS!H:H,"1")+COUNTIFS(SMI!AF:AF,B12,SMI!H:H,"1")+COUNTIFS('IN AND OUT'!$AG$9:$AG$27,B12,'IN AND OUT'!$H$9:$H$27,"1") -> 2
A33: =A13 -> DIAN | B33: =COUNTIFS(DS!AG:AG,B13,DS!I:I,"1")+COUNTIFS(SMI!AF:AF,B13,SMI!I:I,"1")+COUNTIFS('IN AND OUT'!$AG$9:$AG$27,B13,'IN AND OUT'!$I$9:$I$27,"1") -> 4 | C33: =COUNTIFS(DS!AG:AG,B13,DS!J:J,"1")+COUNTIFS(SMI!AF:AF,B13,SMI!J:J,"1")+COUNTIFS('IN AND OUT'!$AG$9:$AG$27,B13,'IN AND OUT'!$J$9:$J$27,"1") -> 3 | D33: =B33+C33 -> 7 | E33: =COUNTIFS(DS!AG:AG,B13,DS!G:G,"1")+COUNTIFS(SMI!AF:AF,B13,SMI!G:G,"1")+COUNTIFS('IN AND OUT'!$AG$9:$AG$27,B13,'IN AND OUT'!$G$9:$G$27,"1") -> 4 | F33: =COUNTIFS(DS!AG:AG,B13,DS!H:H,"1")+COUNTIFS(SMI!AF:AF,B13,SMI!H:H,"1")+COUNTIFS('IN AND OUT'!$AG$9:$AG$27,B13,'IN AND OUT'!$H$9:$H$27,"1") -> 3
A34: =A14 -> IRMA | B34: =COUNTIFS(DS!AG:AG,B14,DS!I:I,"1")+COUNTIFS(SMI!AF:AF,B14,SMI!I:I,"1")+COUNTIFS('IN AND OUT'!$AG$9:$AG$27,B14,'IN AND OUT'!$I$9:$I$27,"1") -> 2 | C34: =COUNTIFS(DS!AG:AG,B14,DS!J:J,"1")+COUNTIFS(SMI!AF:AF,B14,SMI!J:J,"1")+COUNTIFS('IN AND OUT'!$AG$9:$AG$27,B14,'IN AND OUT'!$J$9:$J$27,"1") -> 3 | D34: =B34+C34 -> 5 | E34: =COUNTIFS(DS!AG:AG,B14,DS!G:G,"1")+COUNTIFS(SMI!AF:AF,B14,SMI!G:G,"1")+COUNTIFS('IN AND OUT'!$AG$9:$AG$27,B14,'IN AND OUT'!$G$9:$G$27,"1") -> 3 | F34: =COUNTIFS(DS!AG:AG,B14,DS!H:H,"1")+COUNTIFS(SMI!AF:AF,B14,SMI!H:H,"1")+COUNTIFS('IN AND OUT'!$AG$9:$AG$27,B14,'IN AND OUT'!$H$9:$H$27,"1") -> 2
A35: =A15 -> JOJO | B35: =COUNTIFS(DS!AG:AG,B15,DS!I:I,"1")+COUNTIFS(SMI!AF:AF,B15,SMI!I:I,"1")+COUNTIFS('IN AND OUT'!$AG$9:$AG$27,B15,'IN AND OUT'!$I$9:$I$27,"1") -> 4 | C35: =COUNTIFS(DS!AG:AG,B15,DS!J:J,"1")+COUNTIFS(SMI!AF:AF,B15,SMI!J:J,"1")+COUNTIFS('IN AND OUT'!$AG$9:$AG$27,B15,'IN AND OUT'!$J$9:$J$27,"1") -> 3 | D35: =B35+C35 -> 7 | E35: =COUNTIFS(DS!AG:AG,B15,DS!G:G,"1")+COUNTIFS(SMI!AF:AF,B15,SMI!G:G,"1")+COUNTIFS('IN AND OUT'!$AG$9:$AG$27,B15,'IN AND OUT'!$G$9:$G$27,"1") -> 3 | F35: =COUNTIFS(DS!AG:AG,B15,DS!H:H,"1")+COUNTIFS(SMI!AF:AF,B15,SMI!H:H,"1")+COUNTIFS('IN AND OUT'!$AG$9:$AG$27,B15,'IN AND OUT'!$H$9:$H$27,"1") -> 4
A36: =A17 -> ALVIN | B36: =COUNTIFS(DS!AG:AG,B16,DS!I:I,"1")+COUNTIFS(SMI!AF:AF,B16,SMI!I:I,"1")+COUNTIFS('IN AND OUT'!$AG$9:$AG$27,B16,'IN AND OUT'!$I$9:$I$27,"1") -> 3 | C36: =COUNTIFS(DS!AG:AG,B16,DS!J:J,"1")+COUNTIFS(SMI!AF:AF,B16,SMI!J:J,"1")+COUNTIFS('IN AND OUT'!$AG$9:$AG$27,B16,'IN AND OUT'!$J$9:$J$27,"1") -> 1 | D36: =B36+C36 -> 4 | E36: =COUNTIFS(DS!AG:AG,B16,DS!G:G,"1")+COUNTIFS(SMI!AF:AF,B16,SMI!G:G,"1")+COUNTIFS('IN AND OUT'!$AG$9:$AG$27,B16,'IN AND OUT'!$G$9:$G$27,"1") -> 3 | F36: =COUNTIFS(DS!AG:AG,B16,DS!H:H,"1")+COUNTIFS(SMI!AF:AF,B16,SMI!H:H,"1")+COUNTIFS('IN AND OUT'!$AG$9:$AG$27,B16,'IN AND OUT'!$H$9:$H$27,"1") -> 1
A37: =A16 -> ARI | B37: =COUNTIFS(DS!AG:AG,B17,DS!I:I,"1")+COUNTIFS(SMI!AF:AF,B17,SMI!I:I,"1")+COUNTIFS('IN AND OUT'!$AG$9:$AG$27,B17,'IN AND OUT'!$I$9:$I$27,"1") -> 2 | C37: =COUNTIFS(DS!AG:AG,B17,DS!J:J,"1")+COUNTIFS(SMI!AF:AF,B17,SMI!J:J,"1")+COUNTIFS('IN AND OUT'!$AG$9:$AG$27,B17,'IN AND OUT'!$J$9:$J$27,"1") -> 6 | D37: =B37+C37 -> 8 | E37: =COUNTIFS(DS!AG:AG,B17,DS!G:G,"1")+COUNTIFS(SMI!AF:AF,B17,SMI!G:G,"1")+COUNTIFS('IN AND OUT'!$AG$9:$AG$27,B17,'IN AND OUT'!$G$9:$G$27,"1") -> 4 | F37: =COUNTIFS(DS!AG:AG,B17,DS!H:H,"1")+COUNTIFS(SMI!AF:AF,B17,SMI!H:H,"1")+COUNTIFS('IN AND OUT'!$AG$9:$AG$27,B17,'IN AND OUT'!$H$9:$H$27,"1") -> 4
A38: =A18 -> 0 | B38: =COUNTIFS(DS!AG:AG,B18,DS!I:I,"1")+COUNTIFS(SMI!AF:AF,B18,SMI!I:I,"1")+COUNTIFS('IN AND OUT'!$AG$9:$AG$27,B18,'IN AND OUT'!$I$9:$I$27,"1") -> 0 | C38: =COUNTIFS(DS!AG:AG,B18,DS!J:J,"1")+COUNTIFS(SMI!AF:AF,B18,SMI!J:J,"1")+COUNTIFS('IN AND OUT'!$AG$9:$AG$27,B18,'IN AND OUT'!$J$9:$J$27,"1") -> 0 | D38: =B38+C38 -> 0 | E38: =COUNTIFS(DS!AG:AG,B18,DS!G:G,"1")+COUNTIFS(SMI!AF:AF,B18,SMI!G:G,"1")+COUNTIFS('IN AND OUT'!$AG$9:$AG$27,B18,'IN AND OUT'!$G$9:$G$27,"1") -> 0 | F38: =COUNTIFS(DS!AG:AG,B18,DS!H:H,"1")+COUNTIFS(SMI!AF:AF,B18,SMI!H:H,"1")+COUNTIFS('IN AND OUT'!$AG$9:$AG$27,B18,'IN AND OUT'!$H$9:$H$27,"1") -> 0
A39: =A19 -> 0 | B39: =COUNTIFS(DS!AG:AG,B19,DS!I:I,"1")+COUNTIFS(SMI!AF:AF,B19,SMI!I:I,"1")+COUNTIFS('IN AND OUT'!$AG$9:$AG$27,B19,'IN AND OUT'!$I$9:$I$27,"1") -> 0 | C39: =COUNTIFS(DS!AG:AG,B19,DS!J:J,"1")+COUNTIFS(SMI!AF:AF,B19,SMI!J:J,"1")+COUNTIFS('IN AND OUT'!$AG$9:$AG$27,B19,'IN AND OUT'!$J$9:$J$27,"1") -> 0 | D39: =B39+C39 -> 0 | E39: =COUNTIFS(DS!AG:AG,B19,DS!G:G,"1")+COUNTIFS(SMI!AF:AF,B19,SMI!G:G,"1")+COUNTIFS('IN AND OUT'!$AG$9:$AG$27,B19,'IN AND OUT'!$G$9:$G$27,"1") -> 0 | F39: =COUNTIFS(DS!AG:AG,B19,DS!H:H,"1")+COUNTIFS(SMI!AF:AF,B19,SMI!H:H,"1")+COUNTIFS('IN AND OUT'!$AG$9:$AG$27,B19,'IN AND OUT'!$H$9:$H$27,"1") -> 0
A40: =A20 -> 0 | B40: =COUNTIFS(DS!AG:AG,B20,DS!I:I,"1")+COUNTIFS(SMI!AF:AF,B20,SMI!I:I,"1")+COUNTIFS('IN AND OUT'!$AG$9:$AG$27,B20,'IN AND OUT'!$I$9:$I$27,"1") -> 0 | C40: =COUNTIFS(DS!AG:AG,B20,DS!J:J,"1")+COUNTIFS(SMI!AF:AF,B20,SMI!J:J,"1")+COUNTIFS('IN AND OUT'!$AG$9:$AG$27,B20,'IN AND OUT'!$J$9:$J$27,"1") -> 0 | D40: =B40+C40 -> 0 | E40: =COUNTIFS(DS!AG:AG,B20,DS!G:G,"1")+COUNTIFS(SMI!AF:AF,B20,SMI!G:G,"1")+COUNTIFS('IN AND OUT'!$AG$9:$AG$27,B20,'IN AND OUT'!$G$9:$G$27,"1") -> 0 | F40: =COUNTIFS(DS!AG:AG,B20,DS!H:H,"1")+COUNTIFS(SMI!AF:AF,B20,SMI!H:H,"1")+COUNTIFS('IN AND OUT'!$AG$9:$AG$27,B20,'IN AND OUT'!$H$9:$H$27,"1") -> 0
A41: =A21 -> 0 | B41: =COUNTIFS(DS!AG:AG,B21,DS!I:I,"1")+COUNTIFS(SMI!AF:AF,B21,SMI!I:I,"1")+COUNTIFS('IN AND OUT'!$AG$9:$AG$27,B21,'IN AND OUT'!$I$9:$I$27,"1") -> 0 | C41: =COUNTIFS(DS!AG:AG,B21,DS!J:J,"1")+COUNTIFS(SMI!AF:AF,B21,SMI!J:J,"1")+COUNTIFS('IN AND OUT'!$AG$9:$AG$27,B21,'IN AND OUT'!$J$9:$J$27,"1") -> 0 | D41: =B41+C41 -> 0 | E41: =COUNTIFS(DS!AG:AG,B21,DS!G:G,"1")+COUNTIFS(SMI!AF:AF,B21,SMI!G:G,"1")+COUNTIFS('IN AND OUT'!$AG$9:$AG$27,B21,'IN AND OUT'!$G$9:$G$27,"1") -> 0 | F41: =COUNTIFS(DS!AG:AG,B21,DS!H:H,"1")+COUNTIFS(SMI!AF:AF,B21,SMI!H:H,"1")+COUNTIFS('IN AND OUT'!$AG$9:$AG$27,B21,'IN AND OUT'!$H$9:$H$27,"1") -> 0
A42: =A22 -> 0 | B42: =COUNTIFS(DS!AG:AG,B22,DS!I:I,"1")+COUNTIFS(SMI!AF:AF,B22,SMI!I:I,"1")+COUNTIFS('IN AND OUT'!$AG$9:$AG$27,B22,'IN AND OUT'!$I$9:$I$27,"1") -> 0 | C42: =COUNTIFS(DS!AG:AG,B22,DS!J:J,"1")+COUNTIFS(SMI!AF:AF,B22,SMI!J:J,"1")+COUNTIFS('IN AND OUT'!$AG$9:$AG$27,B22,'IN AND OUT'!$J$9:$J$27,"1") -> 0 | D42: =B42+C42 -> 0 | E42: =COUNTIFS(DS!AG:AG,B22,DS!G:G,"1")+COUNTIFS(SMI!AF:AF,B22,SMI!G:G,"1")+COUNTIFS('IN AND OUT'!$AG$9:$AG$27,B22,'IN AND OUT'!$G$9:$G$27,"1") -> 0 | F42: =COUNTIFS(DS!AG:AG,B22,DS!H:H,"1")+COUNTIFS(SMI!AF:AF,B22,SMI!H:H,"1")+COUNTIFS('IN AND OUT'!$AG$9:$AG$27,B22,'IN AND OUT'!$H$9:$H$27,"1") -> 0
B43: =COUNTIFS(DS!AG:AG,B23,DS!I:I,"1")+COUNTIFS(SMI!AF:AF,B23,SMI!I:I,"1")+COUNTIFS('IN AND OUT'!$AG$9:$AG$27,B23,'IN AND OUT'!$I$9:$I$27,"1") -> 0 | C43: =COUNTIFS(DS!AG:AG,B23,DS!J:J,"1")+COUNTIFS(SMI!AF:AF,B23,SMI!J:J,"1")+COUNTIFS('IN AND OUT'!$AG$9:$AG$27,B23,'IN AND OUT'!$J$9:$J$27,"1") -> 0 | D43: =B43+C43 -> 0 | E43: =COUNTIFS(DS!AG:AG,B23,DS!G:G,"1")+COUNTIFS(SMI!AF:AF,B23,SMI!G:G,"1")+COUNTIFS('IN AND OUT'!$AG$9:$AG$27,B23,'IN AND OUT'!$G$9:$G$27,"1") -> 0 | F43: =COUNTIFS(DS!AG:AG,B23,DS!H:H,"1")+COUNTIFS(SMI!AF:AF,B23,SMI!H:H,"1")+COUNTIFS('IN AND OUT'!$AG$9:$AG$27,B23,'IN AND OUT'!$H$9:$H$27,"1") -> 0
A44: TOTAL STORE | B44: =SUM(B28:B43) -> 22 | C44: =SUM(C28:C43) -> 30 | D44: =SUM(D28:D43) -> 52 | E44: =SUM(E28:E43) -> 25 | F44: =SUM(F28:F43) -> 27

Sheet Sales Support
A1: SKU | B1: Item Code | C1: Item Name | D1: Monthly use | F1: SKU | G1: Item Code | H1: Item Name | I1: Monthly use
A2: 800001 | B2: 800001 | C2: 90*90 SCARF BOX | D2: =COUNTIF(DS!AH:AI,'Sales Support'!A2)+COUNTIF(SC!AH:AI,'Sales Support'!A2)+COUNTIF(SMI!AG:AH,'Sales Support'!A2)+COUNTIF(HO!AE:AF,'Sales Support'!A2)+COUNTIF(MARKOM!AH:AI,'Sales Support'!A2)+COUNTIF('IN AND OUT'!#REF!,'Sales Support'!A2) -> #REF! | F2: 805319 | G2: 805319 | H2: DWA WATCHES + ENVELOPE | I2: =COUNTIF(DS!AH:AI,'Sales Support'!F2)+COUNTIF(SC!AH:AI,'Sales Support'!A2)+COUNTIF(SMI!AG:AH,'Sales Support'!F2)+COUNTIF(HO!AE:AF,'Sales Support'!F2)+COUNTIF(MARKOM!AH:AI,'Sales Support'!F2)+COUNTIF('IN AND OUT'!#REF!,'Sales Support'!F2) -> #REF!
A3: 801832 | B3: 801832 | C3: COTTON BAG FOR LEATHER GOODS (40X40) | D3: =COUNTIF(DS!AH:AI,'Sales Support'!A3)+COUNTIF(SC!AH:AI,'Sales Support'!A3)+COUNTIF(SMI!AG:AH,'Sales Support'!A3)+COUNTIF(HO!AE:AF,'Sales Support'!A3)+COUNTIF(MARKOM!AH:AI,'Sales Support'!A3)+COUNTIF('IN AND OUT'!#REF!,'Sales Support'!A3) -> #REF! | F3: 805553 | G3: 805553 | H3: PF DWA JWA + ENVELOPE | I3: =COUNTIF(DS!AH:AI,'Sales Support'!F3)+COUNTIF(SC!AH:AI,'Sales Support'!A3)+COUNTIF(SMI!AG:AH,'Sales Support'!F3)+COUNTIF(HO!AE:AF,'Sales Support'!F3)+COUNTIF(MARKOM!AH:AI,'Sales Support'!F3)+COUNTIF('IN AND OUT'!#REF!,'Sales Support'!F3) -> #REF!
A4: 801833 | B4: 801833 | C4: COTTON BAG FOR LEATHER GOODS (30X30) | D4: =COUNTIF(DS!AH:AI,'Sales Support'!A4)+COUNTIF(SC!AH:AI,'Sales Support'!A4)+COUNTIF(SMI!AG:AH,'Sales Support'!A4)+COUNTIF(HO!AE:AF,'Sales Support'!A4)+COUNTIF(MARKOM!AH:AI,'Sales Support'!A4)+COUNTIF('IN AND OUT'!#REF!,'Sales Support'!A4) -> #REF! | F4: 806422 | G4: 806422 | H4: PF DWA JWA + ENVELOPE | I4: =COUNTIF(DS!AH:AI,'Sales Support'!F4)+COUNTIF(SC!AH:AI,'Sales Support'!A4)+COUNTIF(SMI!AG:AH,'Sales Support'!F4)+COUNTIF(HO!AE:AF,'Sales Support'!F4)+COUNTIF(MARKOM!AH:AI,'Sales Support'!F4)+COUNTIF('IN AND OUT'!#REF!,'Sales Support'!F4) -> #REF!
A5: 801906 | B5: 801906 | C5: FOLDING BOX BB3 (40.5x38x20) | D5: =COUNTIF(DS!AH:AI,'Sales Support'!A5)+COUNTIF(SC!AH:AI,'Sales Support'!A5)+COUNTIF(SMI!AG:AH,'Sales Support'!A5)+COUNTIF(HO!AE:AF,'Sales Support'!A5)+COUNTIF(MARKOM!AH:AI,'Sales Support'!A5)+COUNTIF('IN AND OUT'!#REF!,'Sales Support'!A5) -> #REF!
A6: 801910 | B6: 801910 | C6: FOLDING BOX BB7 (32.5x27x14) | D6: =COUNTIF(DS!AH:AI,'Sales Support'!A6)+COUNTIF(SC!AH:AI,'Sales Support'!A6)+COUNTIF(SMI!AG:AH,'Sales Support'!A6)+COUNTIF(HO!AE:AF,'Sales Support'!A6)+COUNTIF(MARKOM!AH:AI,'Sales Support'!A6)+COUNTIF('IN AND OUT'!#REF!,'Sales Support'!A6) -> #REF!
A7: 801912 | B7: 801912 | C7: FOLDING BOX BB9 (32.5x20x13.5) | D7: =COUNTIF(DS!AH:AI,'Sales Support'!A7)+COUNTIF(SC!AH:AI,'Sales Support'!A7)+COUNTIF(SMI!AG:AH,'Sales Support'!A7)+COUNTIF(HO!AE:AF,'Sales Support'!A7)+COUNTIF(MARKOM!AH:AI,'Sales Support'!A7)+COUNTIF('IN AND OUT'!#REF!,'Sales Support'!A7) -> #REF!
A8: 802551 | B8: 802551 | C8: COTTON BAG FOR LEATHER GOODS (35X35) | D8: =COUNTIF(DS!AH:AI,'Sales Support'!A8)+COUNTIF(SC!AH:AI,'Sales Support'!A8)+COUNTIF(SMI!AG:AH,'Sales Support'!A8)+COUNTIF(HO!AE:AF,'Sales Support'!A8)+COUNTIF(MARKOM!AH:AI,'Sales Support'!A8)+COUNTIF('IN AND OUT'!#REF!,'Sales Support'!A8) -> #REF!
A9: 802744 | B9: 802744 | C9: HE Kit for Necklace PK/31HJ | D9: =COUNTIF(DS!AH:AI,'Sales Support'!A9)+COUNTIF(SC!AH:AI,'Sales Support'!A9)+COUNTIF(SMI!AG:AH,'Sales Support'!A9)+COUNTIF(HO!AE:AF,'Sales Support'!A9)+COUNTIF(MARKOM!AH:AI,'Sales Support'!A9)+COUNTIF('IN AND OUT'!#REF!,'Sales Support'!A9) -> #REF!
A10: 803152 | B10: 803152 | C10: PK/44 HE WATCH BOX MALE | D10: =COUNTIF(DS!AH:AI,'Sales Support'!A10)+COUNTIF(SC!AH:AI,'Sales Support'!A10)+COUNTIF(SMI!AG:AH,'Sales Support'!A10)+COUNTIF(HO!AE:AF,'Sales Support'!A10)+COUNTIF(MARKOM!AH:AI,'Sales Support'!A10)+COUNTIF('IN AND OUT'!#REF!,'Sales Support'!A10) -> #REF!
A11: 803153 | B11: 803153 | C11: PK/45 HE WATCH BOX FEMALE | D11: =COUNTIF(DS!AH:AI,'Sales Support'!A11)+COUNTIF(SC!AH:AI,'Sales Support'!A11)+COUNTIF(SMI!AG:AH,'Sales Support'!A11)+COUNTIF(HO!AE:AF,'Sales Support'!A11)+COUNTIF(MARKOM!AH:AI,'Sales Support'!A11)+COUNTIF('IN AND OUT'!#REF!,'Sales Support'!A11) -> #REF!
A12: 803223 | B12: 803223 | C12: WB/55 BOX FOR STC RING | D12: =COUNTIF(DS!AH:AI,'Sales Support'!A12)+COUNTIF(SC!AH:AI,'Sales Support'!A12)+COUNTIF(SMI!AG:AH,'Sales Support'!A12)+COUNTIF(HO!AE:AF,'Sales Support'!A12)+COUNTIF(MARKOM!AH:AI,'Sales Support'!A12)+COUNTIF('IN AND OUT'!#REF!,'Sales Support'!A12) -> #REF!
A13: 803227 | B13: 803227 | C13: PK/45M HE WATCH BOX SERPENTI PG | D13: =COUNTIF(DS!AH:AI,'Sales Support'!A13)+COUNTIF(SC!AH:AI,'Sales Support'!A13)+COUNTIF(SMI!AG:AH,'Sales Support'!A13)+COUNTIF(HO!AE:AF,'Sales Support'!A13)+COUNTIF(MARKOM!AH:AI,'Sales Support'!A13)+COUNTIF('IN AND OUT'!#REF!,'Sales Support'!A13) -> #REF!
A14: 803316 | B14: 803316 | C14: PK/50 HE SERPENTI PRECIOUS WATCH | D14: =COUNTIF(DS!AH:AI,'Sales Support'!A14)+COUNTIF(SC!AH:AI,'Sales Support'!A14)+COUNTIF(SMI!AG:AH,'Sales Support'!A14)+COUNTIF(HO!AE:AF,'Sales Support'!A14)+COUNTIF(MARKOM!AH:AI,'Sales Support'!A14)+COUNTIF('IN AND OUT'!#REF!,'Sales Support'!A14) -> #REF!
A15: 803457 | B15: 803457 | C15: Small Kit for Bzero1 Earrings BK/9MBS | D15: =COUNTIF(DS!AH:AI,'Sales Support'!A15)+COUNTIF(SC!AH:AI,'Sales Support'!A15)+COUNTIF(SMI!AG:AH,'Sales Support'!A15)+COUNTIF(HO!AE:AF,'Sales Support'!A15)+COUNTIF(MARKOM!AH:AI,'Sales Support'!A15)+COUNTIF('IN AND OUT'!#REF!,'Sales Support'!A15) -> #REF!
A16: 803610 | B16: 803610 | C16: Kit for Watch Serpenti Steel FIX/2MBS | D16: =COUNTIF(DS!AH:AI,'Sales Support'!A16)+COUNTIF(SC!AH:AI,'Sales Support'!A16)+COUNTIF(SMI!AG:AH,'Sales Support'!A16)+COUNTIF(HO!AE:AF,'Sales Support'!A16)+COUNTIF(MARKOM!AH:AI,'Sales Support'!A16)+COUNTIF('IN AND OUT'!#REF!,'Sales Support'!A16) -> #REF!
... A46: 805256 | B46: 805256 | C46: WB/58 BOX FOR STC BRACELET | D46: =COUNTIF(DS!AH:AI,'Sales Support'!A46)+COUNTIF(SC!AH:AI,'Sales Support'!A46)+COUNTIF(SMI!AG:AH,'Sales Support'!A46)+COUNTIF(HO!AE:AF,'Sales Support'!A46)+COUNTIF(MARKOM!AH:AI,'Sales Support'!A46)+COUNTIF('IN AND OUT'!#REF!,'Sales Support'!A46) -> #REF!
A47: 805331 | B47: 805331 | C47: Watch Box With Tray FIX/2MT | D47: =COUNTIF(DS!AH:AI,'Sales Support'!A47)+COUNTIF(SC!AH:AI,'Sales Support'!A47)+COUNTIF(SMI!AG:AH,'Sales Support'!A47)+COUNTIF(HO!AE:AF,'Sales Support'!A47)+COUNTIF(MARKOM!AH:AI,'Sales Support'!A47)+COUNTIF('IN AND OUT'!$AH$33:$AH$37,'Sales Support'!A47) -> 0
A48: 805426 | B48: 805426 | C48: HE WATCH BOX OCTO STRIKING | D48: =COUNTIF(DS!AH:AI,'Sales Support'!A48)+COUNTIF(SC!AH:AI,'Sales Support'!A48)+COUNTIF(SMI!AG:AH,'Sales Support'!A48)+COUNTIF(HO!AE:AF,'Sales Support'!A48)+COUNTIF(MARKOM!AH:AI,'Sales Support'!A48)+COUNTIF('IN AND OUT'!#REF!,'Sales Support'!A48) -> #REF!
A49: 805468 | B49: 805468 | C49: 70*190 SCARF BOX | D49: =COUNTIF(DS!AH:AI,'Sales Support'!A49)+COUNTIF(SC!AH:AI,'Sales Support'!A49)+COUNTIF(SMI!AG:AH,'Sales Support'!A49)+COUNTIF(HO!AE:AF,'Sales Support'!A49)+COUNTIF(MARKOM!AH:AI,'Sales Support'!A49)+COUNTIF('IN AND OUT'!#REF!,'Sales Support'!A49) -> #REF!
A50: 805560 | B50: 805560 | C50: FRGMNT WATCH BOC CBWTP/1 | D50: =COUNTIF(DS!AH:AI,'Sales Support'!A50)+COUNTIF(SC!AH:AI,'Sales Support'!A50)+COUNTIF(SMI!AG:AH,'Sales Support'!A50)+COUNTIF(HO!AE:AF,'Sales Support'!A50)+COUNTIF(MARKOM!AH:AI,'Sales Support'!A50)+COUNTIF('IN AND OUT'!#REF!,'Sales Support'!A50) -> #REF!
A51: 805579 | B51: 805579 | C51: WATCH BOX WITH CUSHION FIX/2B | D51: =COUNTIF(DS!AH:AI,'Sales Support'!A51)+COUNTIF(SC!AH:AI,'Sales Support'!A51)+COUNTIF(SMI!AG:AH,'Sales Support'!A51)+COUNTIF(HO!AE:AF,'Sales Support'!A51)+COUNTIF(MARKOM!AH:AI,'Sales Support'!A51)+COUNTIF('IN AND OUT'!#REF!,'Sales Support'!A51) -> #REF!
A52: 805838 | B52: 805838 | C52: PK/17HJF FUCHSIA HE KIT FOR LONG EARRINGS | D52: =COUNTIF(DS!AH:AI,'Sales Support'!A52)+COUNTIF(SC!AH:AI,'Sales Support'!A52)+COUNTIF(SMI!AG:AH,'Sales Support'!A52)+COUNTIF(HO!AE:AF,'Sales Support'!A52)+COUNTIF(MARKOM!AH:AI,'Sales Support'!A52)+COUNTIF('IN AND OUT'!#REF!,'Sales Support'!A52) -> #REF!
A53: 805839 | B53: 805839 | C53: FUSCHIA HE KIT FOR BANGLE | D53: =COUNTIF(DS!AH:AI,'Sales Support'!A53)+COUNTIF(SC!AH:AI,'Sales Support'!A53)+COUNTIF(SMI!AG:AH,'Sales Support'!A53)+COUNTIF(HO!AE:AF,'Sales Support'!A53)+COUNTIF(MARKOM!AH:AI,'Sales Support'!A53)+COUNTIF('IN AND OUT'!#REF!,'Sales Support'!A53) -> #REF!
A54: 805843 | B54: 805843 | C54: FUCHSIA HE KIT FOR NECKLACE LARGE | D54: =COUNTIF(DS!AH:AI,'Sales Support'!A54)+COUNTIF(SC!AH:AI,'Sales Support'!A54)+COUNTIF(SMI!AG:AH,'Sales Support'!A54)+COUNTIF(HO!AE:AF,'Sales Support'!A54)+COUNTIF(MARKOM!AH:AI,'Sales Support'!A54)+COUNTIF('IN AND OUT'!#REF!,'Sales Support'!A54) -> #REF!
A55: 805874 | B55: 805874 | C55: PF/12 PAD FOR CIRCULAR EARING | D55: =COUNTIF(DS!AH:AI,'Sales Support'!A55)+COUNTIF(SC!AH:AI,'Sales Support'!A55)+COUNTIF(SMI!AG:AH,'Sales Support'!A55)+COUNTIF(HO!AE:AF,'Sales Support'!A55)+COUNTIF(MARKOM!AH:AI,'Sales Support'!A55)+COUNTIF('IN AND OUT'!#REF!,'Sales Support'!A55) -> #REF!
A56: 806404 | B56: 806404 | C56: FUSCHIA HJ TRAVEL POUCH FOR RECTANGULAR NECKLACE | D56: =COUNTIF(DS!AH:AI,'Sales Support'!A56)+COUNTIF(SC!AH:AI,'Sales Support'!A56)+COUNTIF(SMI!AG:AH,'Sales Support'!A56)+COUNTIF(HO!AE:AF,'Sales Support'!A56)+COUNTIF(MARKOM!AH:AI,'Sales Support'!A56)+COUNTIF('IN AND OUT'!#REF!,'Sales Support'!A56) -> #REF!
A57: 806438 | B57: 806438 | C57: SCARF BOX 18x7x2.5 | D57: =COUNTIF(DS!AH:AI,'Sales Support'!A57)+COUNTIF(SC!AH:AI,'Sales Support'!A57)+COUNTIF(SMI!AG:AH,'Sales Support'!A57)+COUNTIF(HO!AE:AF,'Sales Support'!A57)+COUNTIF(MARKOM!AH:AI,'Sales Support'!A57)+COUNTIF('IN AND OUT'!#REF!,'Sales Support'!A57) -> #REF!
A58: 806503 | B58: 806503 | C58: FOLDING BOX BB17 (26.5x25x13) | D58: =COUNTIF(DS!AH:AI,'Sales Support'!A58)+COUNTIF(SC!AH:AI,'Sales Support'!A58)+COUNTIF(SMI!AG:AH,'Sales Support'!A58)+COUNTIF(HO!AE:AF,'Sales Support'!A58)+COUNTIF(MARKOM!AH:AI,'Sales Support'!A58)+COUNTIF('IN AND OUT'!#REF!,'Sales Support'!A58) -> #REF!
A59: 806504 | B59: 806504 | C59: WATCH BOX FOR BB AL | D59: =COUNTIF(DS!AH:AI,'Sales Support'!A59)+COUNTIF(SC!AH:AI,'Sales Support'!A59)+COUNTIF(SMI!AG:AH,'Sales Support'!A59)+COUNTIF(HO!AE:AF,'Sales Support'!A59)+COUNTIF(MARKOM!AH:AI,'Sales Support'!A59)+COUNTIF('IN AND OUT'!#REF!,'Sales Support'!A59) -> #REF!
... A109: 807853 | B109: 807853 | C109: DATAMATRIX LEAFLET | D109: =COUNTIF(DS!AH:AI,'Sales Support'!A109)+COUNTIF(SC!AH:AI,'Sales Support'!A109)+COUNTIF(SMI!AG:AH,'Sales Support'!A109)+COUNTIF(HO!AE:AF,'Sales Support'!A109)+COUNTIF(MARKOM!AH:AI,'Sales Support'!A109)+COUNTIF('IN AND OUT'!#REF!,'Sales Support'!A109) -> #REF!

Sheet Data
A1: COUNTRY | B1: CODE | D1: JEWELRY
A2: Afghanistan | B2: AFG | D2: WATCHES
A3: Albania | B3: ALB | D3: PERFUME
A4: Algeria | B4: DZA | D4: LLGA
A5: American Samoa | B5: ASM | D5: AFSS
A6: Andorra | B6: AND | D6: HE WATCHES
A7: Angola | B7: AGO | D7: JHJEWELRY
A8: Anguilla | B8: AIA
A9: Antarctica | B9: ATA
A10: Antigua and Barbuda | B10: ATG
A11: Argentina | B11: ARG
A12: Armenia | B12: ARM
A13: Aruba | B13: ABW
A14: Australia | B14: AUS
A15: Austria | B15: AUT
A16: Azerbaijan | B16: AZE
A17: Bahamas (the) | B17: BHS
A18: Bahrain | B18: BHR
A19: Bangladesh | B19: BGD
... A249: Åland Islands | B249: ALA
